Workbook

Sheet 3月加热汇总
A1: 发布日期 | B1: 投放截止日期 | C1: 状态 | D1: 达人名称 | E1: 链接 | F1: 投放记录 xx日投放xx元 | G1: 标题 | H1: 投前互动量 | I1: 投放互动量 | J1: 总互动量 | K1: 总投放金额 | L1: 综合cpe *投入/笔记外层互动数据 | M1: 一级分类 | N1: 二级分类 | O1: 备注 | P1: 最终互动量 | Q1: 爆款定级
A2: 汇总 | H2: - | I2: - | J2: =SUM(J3:J99) | K2: =SUM(K3:K99) | L2: =K2/J2 | P2: =SUM(P3:P98)
A3: 46082 | B3: =A3+7 | C3: 投放完毕 | D3: 酸奶吐司 | E3: https://www.douyin.com/video/7612207816275352497 | F3: 2026/3/2投放500元 2026/3/3投放1000元2026/3/4投放500元2026/3/5投放500元2026/3/9投放500元 | G3: 广州的滴滴车也太可爱了吧！坐得心情都美美的#广州 #广州滴滴 | H3: 112 | I3: ='详细数据'!AC2+'详细数据'!AC16+'详细数据'!AC20+'详细数据'!AC26+'详细数据'!AC38 | J3: 37471 | K3: =1000+500+500+'详细数据'!J26+'详细数据'!J38 | L3: =K3/J3 | M3: 车内 | N3: 车内整洁 | P3: 37471 | Q3: =IF(J3="","",IF(J3>=500000,"S 级",IF(J3>=100000,"A 级",IF(J3>=50000,"B 级","C 级"))))
A4: 46081 | B4: =A4+7 | C4: 投放完毕 | D4: 尚雅求真 | E4: https://www.douyin.com/video/7611743676641705295 | F4: 2026/3/2投放500元 | G4: “滴滴”赞 | H4: 74 | I4: 1094 | J4: 1204 | K4: 500 | L4: =K4/J4 | M4: 地广/活动 | N4: 品牌 | P4: 1204 | Q4: =IF(J4="","",IF(J4>=500000,"S 级",IF(J4>=100000,"A 级",IF(J4>=50000,"B 级","C 级"))))
A5: 46082 | B5: =A5+7 | C5: 投放完毕 | D5: Mr钟又离 | E5: https://www.douyin.com/video/7612244922887857787 | F5: 2026/3/2投放500元 2026/3/3投放1000元 | G5: 太酷了 男滴滴司机的公主车： 啥样生活都是经营出来的不是吗#温暖治愈 #人间烟火#滴滴司机 #非标准人生#清醒的选负责到底 | H5: 128 | I5: =1427+'详细数据'!AC14 | J5: 5167 | K5: 1500 | L5: =K5/J5 | M5: 车内 | N5: 特殊车型/车衣 | P5: 5167 | Q5: =IF(J5="","",IF(J5>=500000,"S 级",IF(J5>=100000,"A 级",IF(J5>=50000,"B 级","C 级"))))
A6: 46082 | B6: =A6+7 | C6: 投放完毕 | D6: 白开水泡茶 | E6: https://www.douyin.com/note/7612110532075037129 | F6: 2026/3/2投放500元 2026/3/3投放1000元 | G6: 武汉下雨天，我打了辆滴滴准备回学校。 | H6: 909 | I6: =1280+'详细数据'!AC13 | J6: 5887 | K6: 1500 | L6: =K6/J6 | M6: 场景 | N6: 通勤上下班 | P6: 5887 | Q6: =IF(J6="","",IF(J6>=500000,"S 级",IF(J6>=100000,"A 级",IF(J6>=50000,"B 级","C 级"))))
A7: 46082 | B7: =A7+7 | C7: 投放完毕 | D7: 清风✨ | E7: https://www.douyin.com/video/7612087271226903844 | F7: 2026/3/2投放500元 2026/3/3投放1000元2026/3/4投放500元2026/3/5投放500元2026/3/9投放500元 | G7: 小同志，磁场又弱了吧，是时候充电了 #天安门 #士兵突击 #滴滴司机 感谢北京的滴滴师傅，放慢车速让我们看天安门夜景 | H7: 1056 | I7: =2871+'详细数据'!AC12+'详细数据'!AC21+'详细数据'!AC31+'详细数据'!AC37 | J7: 36628 | K7: =1000+500+500+'详细数据'!J31+'详细数据'!J37 | L7: =K7/J7 | M7: 司机 | N7: 司机服务 | P7: 36628 | Q7: =IF(J7="","",IF(J7>=500000,"S 级",IF(J7>=100000,"A 级",IF(J7>=50000,"B 级","C 级"))))
A8: 46081 | B8: =A8+7 | C8: 投放完毕 | D8: 北辰 | E8: https://www.douyin.com/note/7611832044951303909 | F8: 2026/3/2投放500元 | G8: 第2集 | 爱心：爱的传递。这是我遇见的最暖心的滴滴司机师傅，太原的成师傅， | H8: 99 | I8: 1073 | J8: 1222 | K8: 500 | L8: =K8/J8 | M8: 司机 | N8: 司乘温暖 | P8: 1222 | Q8: =IF(J8="","",IF(J8>=500000,"S 级",IF(J8>=100000,"A 级",IF(J8>=50000,"B 级","C 级"))))
A9: 46080 | B9: =A9+7 | C9: 投放完毕 | D9: 一生有你 | E9: https://www.douyin.com/note/7611432494563328113 | F9: 2026/3/2投放500元 2026/3/3投放1000元2026/3/4投放500元 | G9: 人生第一次打到滴滴女司机，技术稳得一批，完全不输男司机👍 | H9: 985 | I9: =1292+'详细数据'!AC15+'详细数据'!AC19 | J9: 8264 | K9: =1000+500+500 | L9: =K9/J9 | M9: 司机 | N9: 女司机 | P9: 8264 | Q9: =IF(J9="","",IF(J9>=500000,"S 级",IF(J9>=100000,"A 级",IF(J9>=50000,"B 级","C 级"))))
A10: 46080 | B10: =A10+7 | C10: 投放完毕 | D10: Saffron | E10: https://www.douyin.com/note/7611499522330631857 | F10: 2026/3/2投放500元 2026/3/3投放1000元2026/3/4投放500元 | G10: 下班遇到了一位温暖的滴滴司机，椅背贴了一张纸条，口袋里放了两本小册子，两支笔和一面镜子 | H10: 261 | I10: =1301+'详细数据'!AC11+'详细数据'!AC22 | J10: 7509 | K10: =1000+500+500 | L10: =K10/J10 | M10: 车内 | N10: 司机自发装置 | P10: 7509 | Q10: =IF(J10="","",IF(J10>=500000,"S 级",IF(J10>=100000,"A 级",IF(J10>=50000,"B 级","C 级"))))
A11: 46079 | B11: =A11+7 | C11: 投放完毕 | D11: 康老师(武汉少儿阅读) | E11: https://www.douyin.com/video/7611192244423229139 | F11: 2026/3/2投放500元 | G11: 武汉有滴滴公交啦！学名响应式公交 | H11: 147 | I11: 1145 | J11: 1371 | K11: 500 | L11: =K11/J11 | M11: 产品力 | N11: 网约公交 | P11: 1371 | Q11: =IF(J11="","",IF(J11>=500000,"S 级",IF(J11>=100000,"A 级",IF(J11>=50000,"B 级","C 级"))))
A12: 46079 | B12: =A12+7 | C12: 投放完毕 | D12: 馬壹榴·我是眠眠呀 | E12: https://www.douyin.com/video/7611742459936919402 | F12: 2026/3/3投放500元 | G12: 今天打车遇到一个很有童趣的师傅，哈哈！#滴滴 #滴滴司机 #滴滴打车 | H12: 71 | I12: ='详细数据'!AC18 | J12: 282 | K12: 500 | L12: =K12/J12 | M12: 司机 | N12: 司乘互动 | P12: 282 | Q12: =IF(J12="","",IF(J12>=500000,"S 级",IF(J12>=100000,"A 级",IF(J12>=50000,"B 级","C 级"))))
A13: 46083 | B13: =A13+7 | C13: 投放完毕 | D13: 小红碎花裤衩儿 | E13: https://www.douyin.com/video/7612686487277578602 | F13: 2026/3/3投放500元2026/3/4投放500元 | G13: 第30集 | 这马师傅上车给我俩整蒙了，太有活儿了，威海rapper #威海旅游 #滴滴司机 #威海马大帅 #加油奥利给 #马年说马 | H13: 93 | I13: ='详细数据'!AC17+'详细数据'!AC23 | J13: 4251 | K13: =500+500 | L13: =K13/J13 | M13: 司机 | N13: 司乘互动 | P13: 4251 | Q13: =IF(J13="","",IF(J13>=500000,"S 级",IF(J13>=100000,"A 级",IF(J13>=50000,"B 级","C 级"))))
A14: 46084 | B14: =A14+7 | C14: 投放完毕 | D14: 一場、流★雨 | E14: https://www.douyin.com/video/7612918993481033330 | F14: 2026/3/4投放500元 | G14: 这辈子第一次坐RR，居然是在滴滴订单里😂😂 | H14: 90 | I14: ='详细数据'!AC25 | J14: 2159 | K14: 500 | L14: =K14/J14 | M14: 产品力 | N14: 专车/豪华车 | P14: 2159 | Q14: =IF(J14="","",IF(J14>=500000,"S 级",IF(J14>=100000,"A 级",IF(J14>=50000,"B 级","C 级"))))
B15: =A15+7 | C15: 无法投放 | D15: 娜L. | E15: https://www.douyin.com/video/7612865593025511337 | F15: 2026/3/4投放500元 | G15: 这是一段很酷也非常有意义的事情！刚到北京那年，本想着去找一辆自行车夜骑天安门，搜索了附近离我们最近的自行车停放点，但是路程太远，最终还是没有夜骑上。后面就打了一辆滴滴车，司机师傅人超级好，首先问我们赶时间吗？然后就带我们绕路经过天安门，到了天安门车速给我们放慢啦，还往里开了一点，好让我们拍视频，还让我们多拍几个做纪念，因为不知道我们下一次来北京是什么时候啦。#天安门夜景 #人活着不就为了这几个瞬间 #祖国万岁 #世界和平 #北京滴滴司机 | H15: 108 | I15: 0 | K15: 0 | L15: =K15/J15 | M15: 司机
A16: 46084 | B16: =A16+7 | C16: 投放完毕 | D16: 萌萌小🌧 | E16: https://www.douyin.com/note/7613031533112581883 | F16: 2026/3/4投放500元 | G16: 这次对新疆体验感很特殊，飞机上一起坐的大哥他是来工作听说我自己来跟我说这边的有趣的地方，他说在快到新疆的景色更美，靠近新疆时雪山真的很美，下飞机后打车滴滴司机里元宵快乐，欢迎来新疆过节，他看我自己来跟我说很多需要注意的事情，晚上很晚到酒店里后保洁阿姨跟我笑着那种是善意的笑，她说话像中部地区的，江西那边口音不像本地人，跟我说房间在哪里哪里，我没太热情回应，出来吃晚饭时听司机说有家挺好吃的，我就去了，后面老板看我说话有点像外地，就问我来旅游的吗，自己吃饭，我说从安徽过来的，想看看新疆的美景，他就跟我说这边很多好玩的，希望喜欢这里，他在上菜时端过来一碟我没点的，他说这是送的自己做的，马肠包马肉凉菜，后面结账时我问马肉价格这边多少他说136，怪不得天上龙肉地上马肉，今天上午我点了天润的奶制品想带回去，外卖共100多，那个外卖里送了罐干噎酸奶，下午想自驾去天山天池看夕阳可天气还是雾蒙蒙，山里估计视野不太好，这边8.9点太阳下山，我担心我车技回来不行就改去和田二街好好尝尝这边吃的，滴滴司机我问他国道和山路好不好走，他说可以走，于是我准备改计划订车出发，司机就问了我是外地哪里的我说安徽的，他说我真厉害自己敢来这么远，后来他给我送到地址时跟我说前面有点堵，让我等一会下他给我送到小吃街里，于是我下车便是美食一条路，他说新疆本地人几乎很多都走不出省，对外面的世界同样充满好奇期待，他准备等孩子暑假也去外面玩玩，买烤馕时那两个维吾尔族的男生结账我问他多少钱，他说一个馕5元，我共4个馕和2个小馕，他俩说着听不懂的话最后说23，我说好，付过去了，确定哈，他俩交流两句说对，然后我去餐厅最后尝一下这里的菜，那几道菜加烧烤共126，服务员是个同龄的少数名族女孩很好看，她一直跟我说少点一点哦，吃不完的，我说好，后面上菜时阿姨说我一个人吗，我说嗯，过一会刚刚小姑娘过来给我一碗甜的牛奶和白砂糖，她说当地的奶皮子配糖吃会好很多，单吃的话会很酸，她注意到我在外面买的奶皮子了哈哈，后面我要真空打包带走，老板娘叫两个人过来帮忙包装，我问她打包费多少，她说不用，吃完回酒店时我想明晚的航班9点，我2点退房后面去机场有点早想要么再定一晚，到前台我想了下跟前台说房间续2个小时吧，续到4点，明晚飞机9点，机场很大我提前几小时到正好不值当续订，酒店续时30一小时，一晚160多我那个房间，前台有个姐姐说不用了，我结束给个好评就好，还有没有其他的需要的，我说房间的拖鞋需要一个新的，当我回房间后发现房间在我6点走后被人又打扫了一遍，而今天下午4点阿姨过来过一次给我洗漱用品了，现在的房间里开着的窗户被关上，水多给了2瓶共4瓶，我开着的面包袋子被系好，睡衣也被叠好了#新疆 #新疆是个好地方 #乌鲁木齐 #抖音美食推荐官 #热点小助手 @抖音小助手 | H16: 199 | I16: ='详细数据'!AC24 | J16: 1870 | K16: 500 | L16: =K16/J16 | M16: 场景 | N16: 旅游出行 | P16: 1870 | Q16: =IF(J16="","",IF(J16>=500000,"S 级",IF(J16>=100000,"A 级",IF(J16>=50000,"B 级","C 级"))))
A17: 46085 | B17: =A17+7 | C17: 投放完毕 | D17: 小万不吃香菜 | E17: https://www.douyin.com/video/7613215289803536101 | F17: 2026/3/5投放500元2026/3/9投放500元 | G17: 打到了一辆超级干净的滴滴心情都变美了#打车打车 | H17: 91 | I17: ='详细数据'!AC27+'详细数据'!AC36 | J17: 3769 | K17: =500+'详细数据'!J36 | L17: =K17/J17 | M17: 车内 | N17: 车内整洁 | P17: 3769 | Q17: =IF(J17="","",IF(J17>=500000,"S 级",IF(J17>=100000,"A 级",IF(J17>=50000,"B 级","C 级"))))
A18: 46086 | B18: =A18+7 | C18: 投放完毕 | D18: 🦁🦁奔跑的蜗牛 | E18: https://www.douyin.com/note/7613350700244157626 | F18: 2026/3/5投放500元 | G18: 今天出门打车居然打到了特斯拉，北京果然藏龙卧虎啊，连特斯拉都来跑滴滴了#特斯拉 #特斯拉汽车 #北京网约车 #北京网约车司机 | H18: 155 | I18: ='详细数据'!AC29 | J18: 1556 | K18: 500 | L18: =K18/J18 | M18: 车内 | N18: 特殊车型/车衣 | P18: 1556 | Q18: =IF(J18="","",IF(J18>=500000,"S 级",IF(J18>=100000,"A 级",IF(J18>=50000,"B 级","C 级"))))
A19: 46082 | B19: =A19+7 | C19: 投放完毕 | D19: 花渐落 | E19: https://www.douyin.com/note/7612219889386191970 | F19: 2026/3/5投放500元 | G19: 郑州今后的发展会越来越好： | H19: 71 | I19: ='详细数据'!AC28 | J19: 1558 | K19: 500 | L19: =K19/J19 | M19: 无匹配类别 | N19: 无匹配类别 | P19: 1558 | Q19: =IF(J19="","",IF(J19>=500000,"S 级",IF(J19>=100000,"A 级",IF(J19>=50000,"B 级","C 级"))))
A20: 46085 | B20: =A20+7 | C20: 投放完毕 | D20: 小万不吃香菜 | E20: https://www.douyin.com/video/7613215289803536101 | F20: 2026/3/5投放500元 | G20: 打到了一辆超级干净的滴滴心情都变美了#打车打车 | H20: 106 | I20: ='详细数据'!AC30 | J20: 3485 | K20: 500 | L20: =K20/J20 | M20: 车内 | N20: 车内整洁 | P20: 3485 | Q20: =IF(J20="","",IF(J20>=500000,"S 级",IF(J20>=100000,"A 级",IF(J20>=50000,"B 级","C 级"))))
A21: 46086 | B21: =A21+7 | C21: 投放完毕 | D21: GOOD. | E21: https://www.douyin.com/note/7613787027502461352 | F21: 2026/3/9投放500元2026/3/12投放500元 | G21: 愿：平安 发财。@滴滴出行司机中心官方账号 | H21: 299 | I21: ='详细数据'!AC35+'详细数据'!AC55 | J21: 7295 | K21: ='详细数据'!J35+'详细数据'!J55 | L21: =K21/J21 | M21: 无匹配类别 | N21: 无匹配类别 | P21: 7295 | Q21: =IF(J21="","",IF(J21>=500000,"S 级",IF(J21>=100000,"A 级",IF(J21>=50000,"B 级","C 级"))))
B22: =A22+7 | C22: 无法投放 | D22: ✎﹏ ℳ伱♡吥懂💞ꦿ᭄ | E22: https://www.douyin.com/video/7613759148690695077 | F22: / | G22: 这么多年坐滴滴打车，是我遇上最好的一个滴滴司机，肯定会给你好评呀。 | H22: 147 | I22: / | J22: / | K22: / | L22: / | M22: / | P22: /
A23: 46089 | B23: =A23+7 | C23: 投放完毕 | D23: 一点也不酷啊。 | E23: https://www.douyin.com/video/7614841048691419327 | F23: 2026/3/9投放500元2026/3/12投放500元2026/3/13投放500元 | G23: 打了2个小时滴滴，取消了半天，终于打到了。氛围灯也开了，最好的安排也安排了，总裁座椅也给他调了。他常出现的地方我给你们标记出来了 | H23: 316 | I23: ='详细数据'!AC34+'详细数据'!AC54+'详细数据'!AC63 | J23: 33030 | K23: ='详细数据'!J34+'详细数据'!J54+'详细数据'!J63 | L23: =K23/J23 | M23: 产品力 | N23: 专车/豪华车 | P23: 33030 | Q23: =IF(J23="","",IF(J23>=500000,"S 级",IF(J23>=100000,"A 级",IF(J23>=50000,"B 级","C 级"))))
B24: =A24+7 | C24: 无法投放 | D24: 杨哥来了 | E24: https://www.douyin.com/note/7614679701290263147 | F24: / | G24: 雨夜武汉，一位滴滴司机，让我读懂什。雨夜守护 致敬武汉暖心司机 | H24: 3657 | I24: / | J24: / | K24: / | L24: / | M24: / | P24: /
A25: 46089 | B25: =A25+7 | C25: 投放完毕 | D25: 莫陌墨默 | E25: https://www.douyin.com/video/7614604940937363313 | F25: 2026/3/9投放500元2026/3/12投放500元2026/3/13投放499.7元 | G25: 回家路上，司机自娱自乐，一句“不会让我亲脆”让我破防，简直是氛围组，然后人生第一次跟滴滴合唱😂😂😂，憋怕我伤心 | H25: 370 | I25: ='详细数据'!AC33+'详细数据'!AC53+'详细数据'!AC62 | J25: 5009 | K25: ='详细数据'!J33+'详细数据'!J53+'详细数据'!J62 | L25: =K25/J25 | M25: 司机 | N25: 司乘互动 | P25: 5009 | Q25: =IF(J25="","",IF(J25>=500000,"S 级",IF(J25>=100000,"A 级",IF(J25>=50000,"B 级","C 级"))))
A26: 46088 | B26: =A26+7 | C26: 投放完毕 | D26: ⁺✞ʚ佐鸣重度依赖ɞ✟₊ | E26: https://www.douyin.com/note/7614491818344720739 | F26: 2026/3/9投放500元2026/3/12投放500元 | G26: 上天入地我再也找不到佐鸣这样美好的家产了。家产要永远幸福！ #佐鸣 #佐鸣永远热恋 #滴滴打车 3799！ | H26: 616 | I26: ='详细数据'!AC32+'详细数据'!AC52 | J26: 3105 | K26: ='详细数据'!J32+'详细数据'!J52 | L26: =K26/J26 | M26: 无匹配类别 | N26: 无匹配类别 | P26: 3105 | Q26: =IF(J26="","",IF(J26>=500000,"S 级",IF(J26>=100000,"A 级",IF(J26>=50000,"B 级","C 级"))))
A27: 46090 | B27: =A27+7 | C27: 投放完毕 | D27: 云子 | E27: https://www.douyin.com/video/7615259770899058779 | F27: 2026/3/10投放500元 | G27: 谢谢我的好闺蜜陪我一起闹，还好俺两个一瓶10年都没多，可以安全到家，我好幸运的就是，滴滴师傅是个女同胞，谢谢感恩遇见 | H27: 104 | I27: ='详细数据'!AC42 | J27: 708 | K27: ='详细数据'!J42 | L27: =K27/J27 | M27: 司机 | N27: 女司机 | P27: 708 | Q27: =IF(J27="","",IF(J27>=500000,"S 级",IF(J27>=100000,"A 级",IF(J27>=50000,"B 级","C 级"))))
A28: 46090 | B28: =A28+7 | C28: 投放完毕 | D28: 温暖小孩 | E28: https://www.douyin.com/note/7615023865811614964 | F28: 2026/3/10投放500元 | G28: 滴滴打到帕萨特！第一次体验直接被后排圈粉✨ | H28: 105 | I28: ='详细数据'!AC41 | J28: 924 | K28: ='详细数据'!J41 | L28: =K28/J28 | M28: 车内 | N28: 特殊车型/车衣 | P28: 924 | Q28: =IF(J28="","",IF(J28>=500000,"S 级",IF(J28>=100000,"A 级",IF(J28>=50000,"B 级","C 级"))))
A29: 46089 | B29: =A29+7 | C29: 投放完毕 | D29: 🌈✨小趙媳妇儿✨💕 | E29: https://www.douyin.com/note/7615049142386066043 | F29: 2026/3/10投放500元 | G29: 你们有没有打到过那种车内气味很重的车 打到你们会怎么做 #滴滴司机 #干净的车内环境 | H29: 82 | I29: ='详细数据'!AC40 | J29: 1027 | K29: ='详细数据'!J40 | L29: =K29/J29 | M29: 车内环境投诉 | N29: 烟味/异味 | P29: 1027 | Q29: =IF(J29="","",IF(J29>=500000,"S 级",IF(J29>=100000,"A 级",IF(J29>=50000,"B 级","C 级"))))
A30: 46089 | B30: =A30+7 | C30: 投放完毕 | D30: 小水滴💧 | E30: https://www.douyin.com/note/7614899619931912369 | F30: 2026/3/10投放500元 | G30: 这个妇女节做了一件小事：给所有载过我的女司机发祝福红包🧧 | H30: 448 | I30: ='详细数据'!AC39 | J30: 961 | K30: ='详细数据'!J39 | L30: =K30/J30 | M30: 司机 | N30: 女司机 | P30: 961 | Q30: =IF(J30="","",IF(J30>=500000,"S 级",IF(J30>=100000,"A 级",IF(J30>=50000,"B 级","C 级"))))
A31: 46090 | B31: =A31+7 | C31: 投放完毕 | D31: 玖张机 | E31: https://www.douyin.com/video/7615266309736562682 | F31: 2026/3/11投放500元 | G31: 滴滴打车好评，可以优先选择女性司机。#滴滴 #打车软件 #安全出行 #女性 #解锁新功能 | H31: 141 | I31: ='详细数据'!AC45 | J31: 514 | K31: ='详细数据'!J45 | L31: =K31/J31 | M31: 产品力 | N31: 女性友好计划 | P31: 514 | Q31: =IF(J31="","",IF(J31>=500000,"S 级",IF(J31>=100000,"A 级",IF(J31>=50000,"B 级","C 级"))))
A32: 46092 | B32: =A32+7 | C32: 投放完毕 | D32: 小辉哥 | E32: https://www.douyin.com/video/7615783338746236337 | F32: 2026/3/11投放500元2026/3/12投放500元2026/3/13投放500元2026/3/16投放500元2026/3/17投放500元 | G32: #滴滴，#出租车，朋友们，在陌生的城市，打滴滴还是方便一点！ | H32: 138 | I32: ='详细数据'!AC44+'详细数据'!AC51+'详细数据'!AC61+'详细数据'!AC68+'详细数据'!AC72 | J32: 9518 | K32: ='详细数据'!J44+'详细数据'!J51+'详细数据'!J61+'详细数据'!J68+'详细数据'!J72 | L32: =K32/J32 | M32: 场景 | N32: 旅游出行 | P32: 9518 | Q32: =IF(J32="","",IF(J32>=500000,"S 级",IF(J32>=100000,"A 级",IF(J32>=50000,"B 级","C 级"))))
A33: 46092 | B33: =A33+7 | C33: 投放完毕 | D33: 绛珠仙子成长日记 | E33: https://www.douyin.com/video/7615713873504923322 | F33: 2026/3/11投放500元2026/3/12投放500元2026/3/13投放500元2026/3/16投放500元2026/3/17投放1000元2026/3/18投放9999.79元 | G33: 5.0分的滴滴司机 师傅我听懂了 其实你在告诉我 这个世界上没有定义 只有视角不同 但我此刻有个善良的定义 那就是你的那一句 “为什么你大半夜去人民医院” 以及你的善意的开导 但我是个杠精 我天天带着答案问问题 请原谅我 谢谢你，陌生人 至少此刻你的善良给我带来了开心 我对很多东西都没有欲望 但是对善意的瞬间 充满欲望 渴求遇见它享受它 #司机师傅 #欲望 #善良 | H33: 103 | I33: ='详细数据'!AC43+'详细数据'!AC50+'详细数据'!AC60+'详细数据'!AC67+'详细数据'!AC69+'详细数据'!AC75 | J33: 50277 | K33: ='详细数据'!J43+'详细数据'!J50+'详细数据'!J60+'详细数据'!J67+'详细数据'!J69+'详细数据'!J75 | L33: =K33/J33 | M33: 司机 | N33: 司乘温暖 | P33: 50277 | Q33: =IF(J33="","",IF(J33>=500000,"S 级",IF(J33>=100000,"A 级",IF(J33>=50000,"B 级","C 级"))))
A34: 46092 | B34: =A34+7 | C34: 投放完毕 | D34: 好人好梦👑 | E34: https://www.douyin.com/note/7615950184098960602 | F34: 2026/3/12投放500元 | G34: 今天特别感谢滴滴车主这位大姐拾金不昧的精神，拾到我的皮夹克外套和钱包。特地把平台的接单取消，送到我厂里。关键是身份证，银行卡，医保卡补办太费事了。现在还是好人多。失而复得我很开心。祝好人一生平安！ | H34: 82 | I34: ='详细数据'!AC49 | J34: 1155 | K34: ='详细数据'!J49 | L34: =K34/J34 | M34: 司机 | N34: 失物返还 | P34: 1155 | Q34: =IF(J34="","",IF(J34>=500000,"S 级",IF(J34>=100000,"A 级",IF(J34>=50000,"B 级","C 级"))))
A35: 46092 | B35: =A35+7 | C35: 投放完毕 | D35: 火光 | E35: https://www.douyin.com/note/7615669310942601338 | F35: 2026/3/12投放500元 | G35: 不敢直视师傅的眼睛。#滴滴 #我爱你 | H35: 75 | I35: ='详细数据'!AC48 | J35: 759 | K35: ='详细数据'!J48 | L35: =K35/J35 | M35: 司机 | N35: 司乘互动 | P35: 759 | Q35: =IF(J35="","",IF(J35>=500000,"S 级",IF(J35>=100000,"A 级",IF(J35>=50000,"B 级","C 级"))))
A36: 46092 | B36: =A36+7 | C36: 投放完毕 | D36: 财神爷的小心肝🐉 | E36: https://www.douyin.com/note/7616010066626177211 | F36: 2026/3/12投放499.82元 | G36: 今天因为闹钟没响起晚了所以打滴滴赶去上班，像往常打车一样，我上车报了尾号便开始刷手机，正常都是一路无言。 | H36: 107 | I36: ='详细数据'!AC47 | J36: 1083 | K36: ='详细数据'!J47 | L36: =K36/J36 | M36: 场景 | N36: 通勤上下班 | P36: 1083 | Q36: =IF(J36="","",IF(J36>=500000,"S 级",IF(J36>=100000,"A 级",IF(J36>=50000,"B 级","C 级"))))
A37: 46092 | B37: =A37+7 | C37: 投放完毕 | D37: 秋日胡杨 | E37: https://www.douyin.com/note/7615977113706843382 | F37: 2026/3/12投放499.89元 | G37: 揭阳很好，下次还来 揭阳是唯一个被本地人喊"欢迎"的城市，也是唯一个不被叫"外省仔"的城市 | H37: 90 | I37: ='详细数据'!AC45 | J37: 337 | K37: ='详细数据'!J46 | L37: =K37/J37 | M37: 场景 | N37: 旅游出行 | P37: 337 | Q37: =IF(J37="","",IF(J37>=500000,"S 级",IF(J37>=100000,"A 级",IF(J37>=50000,"B 级","C 级"))))
A38: 46093 | B38: =A38+7 | C38: 投放完毕 | D38: 故宫楚楚日常 | E38: https://www.douyin.com/video/7616359394191938022 | F38: 2026/3/13投放500元 | G38: 整个北京唱歌最好听的滴滴司机被我碰到啦！#故宫楚楚 #滴滴司机 #滴滴司机唱歌 #北京生活 #北京滴滴司机 | H38: 159 | I38: ='详细数据'!AC59 | J38: 1432 | K38: ='详细数据'!J59 | L38: =K38/J38 | M38: 司机 | N38: 司乘互动 | P38: 1432 | Q38: =IF(J38="","",IF(J38>=500000,"S 级",IF(J38>=100000,"A 级",IF(J38>=50000,"B 级","C 级"))))
A39: 46093 | B39: =A39+7 | C39: 投放完毕 | D39: 看他慢慢爱 | E39: https://www.douyin.com/note/7616183547221202259 | F39: 2026/3/13投放500元 | G39: 滴滴可以设置女司机偏好啦。总算是可以小范围避免那些不稳定因素了#滴滴女司机设置 | H39: 119 | I39: ='详细数据'!AC58 | J39: 853 | K39: ='详细数据'!J58 | L39: =K39/J39 | M39: 产品力 | N39: 女性友好计划 | P39: 853 | Q39: =IF(J39="","",IF(J39>=500000,"S 级",IF(J39>=100000,"A 级",IF(J39>=50000,"B 级","C 级"))))
A40: 46093 | B40: =A40+7 | C40: 投放完毕 | D40: 幸运天使（小齐姑姑） | E40: https://www.douyin.com/note/7616286705788479977 | F40: 2026/3/13投放500元 | G40: 正月二十四，晴天，今日解锁滴滴出行，没想到这么方便，电话发出去三两分钟车马上就到，想去那去哪，遇到健谈的师傅一路上还不感觉孤单，轻松又自在，再也不用因为你不拉我出门让我等的憋气人了，哈哈。 | H40: 114 | I40: ='详细数据'!AC57 | J40: 496 | K40: ='详细数据'!J57 | L40: =K40/J40 | M40: 产品力 | N40: 叫车快 | P40: 496 | Q40: =IF(J40="","",IF(J40>=500000,"S 级",IF(J40>=100000,"A 级",IF(J40>=50000,"B 级","C 级"))))
A41: 46092 | B41: =A41+7 | C41: 投放完毕 | D41: dyy | E41: https://www.douyin.com/note/7616006793667697893 | F41: 2026/3/13投放499.93元 | G41: 打了一辆滴滴豪华车，司机穿的是衬衫马甲正装，上车会问车内温度和香薰气味是否合适，全程播放的都是高级的古典音乐，水是voss的，车里还有零食，糖果可以吃，司机师傅车开的真的很稳#滴滴豪华车 | H41: 168 | I41: ='详细数据'!AC56 | J41: 1190 | K41: ='详细数据'!J56 | L41: =K41/J41 | M41: 产品力 | N41: 专车/豪华车 | P41: 1190 | Q41: =IF(J41="","",IF(J41>=500000,"S 级",IF(J41>=100000,"A 级",IF(J41>=50000,"B 级","C 级"))))
A42: 46096 | B42: =A42+7 | C42: 投放完毕 | D42: 彭彭的由来 | E42: https://www.douyin.com/note/7617431215097004667 | F42: 2026/3/16投放500元 | G42: 今天和朋友吃完饭打车回学校，不知为何辗转了三辆车，心里烦躁得很。终于打到一辆车，车里干净又整洁。 | H42: 263 | I42: ='详细数据'!AC66 | J42: 1123 | K42: ='详细数据'!J66 | L42: =K42/J42 | M42: 车内 | N42: 车内整洁 | P42: 1123 | Q42: =IF(J42="","",IF(J42>=500000,"S 级",IF(J42>=100000,"A 级",IF(J42>=50000,"B 级","C 级"))))
A43: 46095 | B43: =A43+7 | C43: 投放完毕 | D43: 湖北.宜昌 | E43: https://www.douyin.com/video/7616911882826256890 | F43: 2026/3/16投放500元 | G43: 坐了一辆豪华滴滴，重庆司机很有礼貌，上车提示您系好安全带(后排)车上有为您备的矿泉水，下车提示祝您一路顺风旅途愉快！ | H43: 72 | I43: ='详细数据'!AC65 | J43: 1028 | K43: ='详细数据'!J65 | L43: =K43/J43 | M43: 产品力 | N43: 专车/豪华车 | P43: 1028 | Q43: =IF(J43="","",IF(J43>=500000,"S 级",IF(J43>=100000,"A 级",IF(J43>=50000,"B 级","C 级"))))
A44: 46095 | B44: =A44+7 | C44: 投放完毕 | D44: 茹ge💨 | E44: https://www.douyin.com/note/7617137673777764465 | F44: 2026/3/16投放500元 | G44: 今天把手机落在滴滴车上，很快联系上了师傅。我说麻烦他跑一趟，路费我来出，他说：“不用，看着给就好。” | H44: 110 | I44: ='详细数据'!AC64 | J44: 288 | K44: ='详细数据'!J64 | L44: =K44/J44 | M44: 司机 | N44: 失物返还 | P44: 288 | Q44: =IF(J44="","",IF(J44>=500000,"S 级",IF(J44>=100000,"A 级",IF(J44>=50000,"B 级","C 级"))))
A45: 46098 | B45: =A45+7 | C45: 投放完毕 | D45: 乌苏一姐 | E45: https://www.douyin.com/video/7617891266244423656 | F45: 2026/3/17投放500元 | G45: #滴滴打车 好好赚钱雇个司机，想谈个贴心的对象，但发现只要出钱就有人愿意服务！ | H45: 78 | I45: ='详细数据'!AC71 | J45: 200 | K45: ='详细数据'!J71 | L45: =K45/J45 | M45: 司机 | N45: 司机服务 | P45: 200 | Q45: =IF(J45="","",IF(J45>=500000,"S 级",IF(J45>=100000,"A 级",IF(J45>=50000,"B 级","C 级"))))
A46: 46097 | B46: =A46+7 | C46: 投放完毕 | D46: 71623570672 | E46: https://www.douyin.com/video/7617859050039070435 | F46: 2026/3/17投放500元 | G46: 滴滴还是太超前了 滴滴还能打倒特斯拉 | H46: 80 | I46: ='详细数据'!AC70 | J46: 276 | K46: ='详细数据'!J70 | L46: =K46/J46 | M46: 车内 | N46: 特殊车型/车衣 | P46: 276 | Q46: =IF(J46="","",IF(J46>=500000,"S 级",IF(J46>=100000,"A 级",IF(J46>=50000,"B 级","C 级"))))
A47: 46096 | B47: =A47+7 | C47: 投放完毕 | D47: 咕咕哒哒 | E47: https://www.douyin.com/note/7617498397310715327 | F47: 2026/3/18投放1000元 | G47: 第二次来柳州，东西还是一样好吃，市民还是一样热情滴滴司机、菜场老板、粉店老板、买菜阿姨、咖啡店小哥，每个人都对游客很耐心柳州值得 | H47: 75 | I47: ='详细数据'!AC74 | J47: 141 | K47: ='详细数据'!J74 | L47: =K47/J47 | M47: 场景 | N47: 旅游出行 | P47: 141 | Q47: =IF(J47="","",IF(J47>=500000,"S 级",IF(J47>=100000,"A 级",IF(J47>=50000,"B 级","C 级"))))
A48: 46098 | B48: =A48+7 | C48: 投放完毕 | D48: 🌸旧时光 | E48: https://www.douyin.com/video/7618168504240308069 | F48: 2026/3/18投放1000元 | G48: 滴滴回家，真是划算 | H48: 102 | I48: ='详细数据'!AC73 | J48: 430 | K48: ='详细数据'!J73 | L48: =K48/J48 | M48: 产品力 | N48: 价格优惠 | P48: 430 | Q48: =IF(J48="","",IF(J48>=500000,"S 级",IF(J48>=100000,"A 级",IF(J48>=50000,"B 级","C 级"))))
A49: 46100 | B49: =A49+7 | C49: 在投 | D49: 小仙仙🌈 | E49: https://www.douyin.com/video/7618960753446510009 | F49: 2026/3/20投放1000元2026/3/23投放5000元 | G49: 打了那么多次车，第一次遇到后车座提供充电线的，而且还是三插头的，给师傅点赞👍#滴滴司机 #滴滴 | H49: 261 | I49: ='详细数据'!AC79+'详细数据'!AC86 | J49: 5874 | K49: ='详细数据'!J79+'详细数据'!J86 | L49: =K49/J49 | P49: 5874 | Q49: =IF(J49="","",IF(J49>=500000,"S 级",IF(J49>=100000,"A 级",IF(J49>=50000,"B 级","C 级"))))
A50: 46098 | B50: =A50+7 | C50: 投放完毕 | D50: 🌈Lin 、 | E50: https://www.douyin.com/video/7618222573041999345 | F50: 2026/3/20投放1000元 | G50: #滴滴出行 温岭的滴滴也是让我大开眼界😂 | H50: 85 | I50: ='详细数据'!AC78 | J50: 1586 | K50: ='详细数据'!J78 | L50: =K50/J50 | M50: 车内 | N50: 特殊车型/车衣 | P50: 1586 | Q50: =IF(J50="","",IF(J50>=500000,"S 级",IF(J50>=100000,"A 级",IF(J50>=50000,"B 级","C 级"))))
A51: 46099 | B51: =A51+7 | C51: 投放完毕 | D51: 人间有情 | E51: https://www.douyin.com/video/7618525485648050938 | F51: 2026/3/20投放1000元 | G51: 城市在改变，滴滴出行，庐陵小巴也是一个选择！ | H51: 85 | I51: ='详细数据'!AC77 | J51: 1761 | K51: ='详细数据'!J77 | L51: =K51/J51 | M51: 产品力 | N51: 滴滴小巴 | P51: 1761 | Q51: =IF(J51="","",IF(J51>=500000,"S 级",IF(J51>=100000,"A 级",IF(J51>=50000,"B 级","C 级"))))
A52: 46101 | B52: =A52+7 | C52: 投放完毕 | D52: 陈黎 | E52: https://www.douyin.com/note/7619093952427614843 | F52: 2026/3/20投放1000元 | G52: 如果嵩山能发声，黄河会呐喊，那么今日的天问就是：河南人惹谁了？ | H52: 581 | I52: ='详细数据'!AC76 | J52: 2430 | K52: ='详细数据'!J76 | L52: =K52/J52 | M52: 无匹配类别 | N52: 无匹配类别 | P52: 2430 | Q52: =IF(J52="","",IF(J52>=500000,"S 级",IF(J52>=100000,"A 级",IF(J52>=50000,"B 级","C 级"))))
A53: 46100 | B53: =A53+7 | C53: 投放完毕 | D53: 高山都957 | E53: https://www.douyin.com/video/7618932945290901903 | F53: 2026/3/20投放1000元 | G53: #出差打车 第一次打高端车滴滴司机好高端啊，停车接送服务，都穿正装耶 | H53: 212 | I53: ='详细数据'!AC80 | J53: 视频下架 | K53: ='详细数据'!J80 | L53: =K53/J53 | M53: 产品力 | N53: 专车/豪华车 | P53: 视频下架
A54: 46103 | B54: =A54+7 | C54: 投放完毕 | D54: 东方先生 | E54: https://www.douyin.com/note/7619935329013573091 | F54: 2026/3/23投放1000元 | G54: 第一次遇到聋哑人滴滴司机，100元一点爱心。#北漂人民辛苦了 | H54: 235 | I54: ='详细数据'!AC84 | J54: 835 | K54: ='详细数据'!J84 | L54: =K54/J54 | M54: 司机 | N54: 特殊身份-听障司机 | P54: 835 | Q54: =IF(J54="","",IF(J54>=500000,"S 级",IF(J54>=100000,"A 级",IF(J54>=50000,"B 级","C 级"))))
A55: 46102 | B55: =A55+7 | C55: 投放完毕 | D55: 面具 | E55: https://www.douyin.com/video/7619622592362705846 | F55: 2026/3/23投放999.21元 | G55: 泾川人打车，别花冤枉钱！ | H55: 131 | I55: ='详细数据'!AC83 | J55: 1105 | K55: ='详细数据'!J83 | L55: =K55/J55 | M55: 产品力 | N55: 价格优惠 | P55: 1105 | Q55: =IF(J55="","",IF(J55>=500000,"S 级",IF(J55>=100000,"A 级",IF(J55>=50000,"B 级","C 级"))))
A56: 46101 | B56: =A56+7 | C56: 投放完毕 | D56: harrynos | E56: https://www.douyin.com/note/7619357588699109065 | F56: 2026/3/23投放999.89元 | G56: 第4集 | 济州偶来小路 亲子徒步百公里Day3。第三天走了5号线/13.4公里+6号线10.1公里 | H56: 91 | I56: ='详细数据'!AC82 | J56: 620 | K56: ='详细数据'!J82 | L56: =K56/J56 | M56: 场景 | N56: 旅游出行 | P56: 620 | Q56: =IF(J56="","",IF(J56>=500000,"S 级",IF(J56>=100000,"A 级",IF(J56>=50000,"B 级","C 级"))))
A57: 46102 | B57: =A57+7 | C57: 投放完毕 | D57: 哆啦萌萌^ | E57: https://www.douyin.com/note/7619636679322387057 | F57: 2026/3/23投放1000元2026/3/24投放5000元2026/3/27投放10000元 | G57: 因为有碰到这些人让我感觉这个国家也没有网上说的那样排华与危险 | H57: 1120 | I57: ='详细数据'!AC81+'详细数据'!AC91+'详细数据'!AC110 | J57: 131931 | K57: ='详细数据'!J81+'详细数据'!J91+'详细数据'!J110 | L57: =K57/J57 | M57: 产品力 | N57: 海外打车 | P57: 131931 | Q57: =IF(J57="","",IF(J57>=500000,"S 级",IF(J57>=100000,"A 级",IF(J57>=50000,"B 级","C 级"))))
A58: 46102 | B58: =A58+7 | C58: 投放完毕 | D58: 💐/₁₂.₁₅ ᵕ̈ xzq✨ | E58: https://www.douyin.com/note/7619605942468253051 | F58: 2026/3/23投放999.63元 | G58: 呼啦啦，已到达桐乡啦🤪🤪 第二次参加半马啦，感谢桐乡半马在8个报名之中作为第二个选择了我哈哈哈 | H58: 688 | I58: ='详细数据'!AC85 | J58: 2295 | K58: ='详细数据'!J85 | L58: =K58/J58 | M58: 场景 | N58: 马拉松/赛事 | P58: 2295 | Q58: =IF(J58="","",IF(J58>=500000,"S 级",IF(J58>=100000,"A 级",IF(J58>=50000,"B 级","C 级"))))
A59: 46102 | B59: =A59+7 | C59: 投放完毕 | D59: 扭瓶盖小能手🤨 | E59: https://www.douyin.com/video/7619392937248262208 | F59: 2026/3/23投放999.82元 | G59: 今日心情被耗到1%🧸拖着疲惫的身体打了一辆滴滴🚗拉开车门的瞬间，看到了满车玩偶——司机是一位北方的退役军人小哥哥🚕@霍拉拉 短暂的车程，在愉快的聊天中满血复活✨热爱生活的人，真的会闪闪发光💛 #治愈系 #满车玩偶 #陌生人的温暖 | H59: 160 | I59: ='详细数据'!AC89 | J59: 1359 | K59: ='详细数据'!J89 | L59: =K59/J59 | M59: 司机 | N59: 特殊身份-退伍军人 | P59: 1359 | Q59: =IF(J59="","",IF(J59>=500000,"S 级",IF(J59>=100000,"A 级",IF(J59>=50000,"B 级","C 级"))))
A60: 46101 | B60: =A60+7 | C60: 投放完毕 | D60: 🫘纸 | E60: https://www.douyin.com/note/7619346681800231592 | F60: 2026/3/23投放1000元2026/3/24投放3416.75元2026/3/27投放10000元 | G60: 第一次打滴滴司机怎么这么帅啊，无意冒犯。#滴滴司机 | H60: 304 | I60: ='详细数据'!AC88+'详细数据'!AC90+'详细数据'!AC109 | J60: 87499 | K60: ='详细数据'!J88+'详细数据'!J90+'详细数据'!J109 | L60: =K60/J60 | M60: 司机 | N60: 司乘互动 | P60: 87499 | Q60: =IF(J60="","",IF(J60>=500000,"S 级",IF(J60>=100000,"A 级",IF(J60>=50000,"B 级","C 级"))))
A61: 46104 | B61: =A61+7 | C61: 投放完毕 | D61: 贝贝公主👸 | E61: https://www.douyin.com/note/7620309274209021605 | F61: 2026/3/23投放999.78元 | G61: #特斯拉 #滴滴打车 也是坐上特斯拉了，滴滴打车，人生第一次哈哈哈哈哈哈哈哈哈 | H61: 13 | I61: ='详细数据'!AC87 | J61: 616 | K61: ='详细数据'!J87 | L61: =K61/J61 | M61: 车内 | N61: 特殊车型/车衣 | P61: 616 | Q61: =IF(J61="","",IF(J61>=500000,"S 级",IF(J61>=100000,"A 级",IF(J61>=50000,"B 级","C 级"))))
A62: 46104 | B62: =A62+7 | C62: 投放完毕 | D62: 刘量AI | E62: https://www.douyin.com/video/7620296845138728549 | F62: 2026/3/24投放1000元2026/3/27投放10000元 | G62: 什么？1句话滴滴AI就能帮你打到满意的车 #AI#AI打车#滴滴打车#AI出行#AI小滴 | H62: 2250 | I62: ='详细数据'!AC94+'详细数据'!AC108 | J62: 14833 | K62: ='详细数据'!J94+'详细数据'!J108 | L62: =K62/J62 | M62: 产品力 | N62: AI叫车/AI小滴 | P62: 14833 | Q62: =IF(J62="","",IF(J62>=500000,"S 级",IF(J62>=100000,"A 级",IF(J62>=50000,"B 级","C 级"))))
A63: 46103 | B63: =A63+7 | C63: 无法投放 | D63: choose | E63: https://www.douyin.com/note/7619916215347607450 | G63: 叫了个滴滴车 1.5元就算了，车还是宝马，司机还是1米8的帅哥 😂 | H63: 81
A64: 46104 | B64: =A64+7 | C64: 无法投放 | D64: 瓜田学姐 | E64: https://www.douyin.com/video/7620371187046075682 | G64: 曾被全网唱衰的女乘客匹配女司机功能 如今被狠狠打脸 #女司机 #出租车 #打车 #女性力量 | H64: 121879
A65: 46103 | B65: =A65+7 | C65: 投放完毕 | D65: 任我行 | E65: https://www.douyin.com/note/7619897380909579002 | F65: 2026/3/24投放1000元 | G65: 昨天坐滴滴，竟然打到了一辆汉的绝版车，大家猜猜是啥车？ | H65: 83 | I65: ='详细数据'!AC92 | J65: 1922 | K65: ='详细数据'!J92 | L65: =K65/J65 | M65: 车内 | N65: 特殊车型/车衣 | P65: 1922 | Q65: =IF(J65="","",IF(J65>=500000,"S 级",IF(J65>=100000,"A 级",IF(J65>=50000,"B 级","C 级"))))
A66: 46104 | B66: =A66+7 | C66: 投放完毕 | D66: 羽物夫妇 | E66: https://www.douyin.com/video/7620401522627016079 | F66: 2026/3/25投放1000元 | G66: 今日份快乐是滴滴给的！随手一打就是豪华车，体验感直接封神，果然生活处处有惊喜～#羽物夫妇 #共青城 #豪华车 #五星级服务 | H66: 105 | I66: ='详细数据'!AC100 | J66: 2707 | K66: ='详细数据'!J100 | L66: =K66/J66 | M66: 产品力 | N66: 专车/豪华车 | P66: 2707 | Q66: =IF(J66="","",IF(J66>=500000,"S 级",IF(J66>=100000,"A 级",IF(J66>=50000,"B 级","C 级"))))
A67: 46105 | B67: =A67+7 | C67: 投放完毕 | D67: 3uii- | E67: https://www.douyin.com/note/7620816046761141747 | F67: 2026/3/25投放1000元 | G67: 我想感谢一位桂A的刘师傅。 | H67: 167 | I67: ='详细数据'!AC99 | J67: 672 | K67: ='详细数据'!J99 | L67: =K67/J67 | M67: 司机 | N67: 司乘温暖 | P67: 672 | Q67: =IF(J67="","",IF(J67>=500000,"S 级",IF(J67>=100000,"A 级",IF(J67>=50000,"B 级","C 级"))))
A68: 46105 | B68: =A68+7 | C68: 投放完毕 | D68: 艳子 | E68: https://www.douyin.com/video/7620759348268759141 | F68: 2026/3/25投放1000元 | G68: 今天打滴滴打到一个全是帅哥的司机说是邓为，不得不说是真帅。#邓为 | H68: 126 | I68: ='详细数据'!AC98 | J68: 4645 | K68: ='详细数据'!J98 | L68: =K68/J68 | M68: 司机 | N68: 司乘互动 | P68: 4645 | Q68: =IF(J68="","",IF(J68>=500000,"S 级",IF(J68>=100000,"A 级",IF(J68>=50000,"B 级","C 级"))))
A69: 46105 | B69: =A69+7 | C69: 投放完毕 | D69: 池也white | E69: https://www.douyin.com/note/7620767030497210778 | F69: 2026/3/25投放1000元 | G69: 感谢大哥。武汉牛逼！十七公里二十三分钟就能到#武汉 #滴滴司机 #赶车 #基建狂魔 | H69: 405 | I69: ='详细数据'!AC97 | J69: 7349 | K69: ='详细数据'!J97 | L69: =K69/J69 | M69: 司机 | N69: 驾驶技术 | P69: 7349 | Q69: =IF(J69="","",IF(J69>=500000,"S 级",IF(J69>=100000,"A 级",IF(J69>=50000,"B 级","C 级"))))
A70: 46105 | B70: =A70+7 | C70: 投放完毕 | D70: 爱漂亮的沈姨 | E70: https://www.douyin.com/note/7620750244388744677 | F70: 2026/3/25投放1000元2026/3/27投放10000元 | G70: 司机师傅一句夸赞，让我更爱穿汉服了。55岁，照样敢把汉服穿出门～ | H70: 1635 | I70: ='详细数据'!AC96+'详细数据'!AC107 | J70: 31542 | K70: ='详细数据'!J96+'详细数据'!J107 | L70: =K70/J70 | M70: 司机 | N70: 司乘互动 | P70: 31542 | Q70: =IF(J70="","",IF(J70>=500000,"S 级",IF(J70>=100000,"A 级",IF(J70>=50000,"B 级","C 级"))))
A71: 46105 | B71: =A71+7 | C71: 投放完毕 | D71: 摸鱼大小姐 | E71: https://www.douyin.com/video/7620717387695869226 | F71: 2026/3/25投放1000元2026/3/27投放9999.74元 | G71: 女生之间的善意 从来不是刻意营造的模样 #女司机 #打车 #网约车 #正能量 | H71: 1039 | I71: ='详细数据'!AC95+'详细数据'!AC106 | J71: 70124 | K71: ='详细数据'!J95+'详细数据'!J106 | L71: =K71/J71 | M71: 司机 | N71: 女司机 | P71: 70124 | Q71: =IF(J71="","",IF(J71>=500000,"S 级",IF(J71>=100000,"A 级",IF(J71>=50000,"B 级","C 级"))))
A72: 46106 | B72: =A72+7 | C72: 投放完毕 | D72: wangCc⚡️ | E72: https://www.douyin.com/note/7621196315842001280 | F72: 2026/3/27投放1000元 | G72: 初到杭州人生地不熟，打了个车前往目的地 | H72: 137 | I72: ='详细数据'!AC105 | J72: 3091 | K72: ='详细数据'!J105 | L72: =K72/J72 | M72: 场景 | N72: 旅游出行 | P72: 3091 | Q72: =IF(J72="","",IF(J72>=500000,"S 级",IF(J72>=100000,"A 级",IF(J72>=50000,"B 级","C 级"))))
A73: 46106 | B73: =A73+7 | C73: 投放完毕 | D73: 是陈叁叁咩 | E73: https://www.douyin.com/note/7621099857121775019 | F73: 2026/3/27投放1000元 | G73: 谁懂打滴滴碰到了这一幕的救赎感 #可爱到爆炸💥 #滴滴司机 #车载鹦鹉 #高德打车 | H73: 516 | I73: ='详细数据'!AC104 | J73: 7509 | K73: ='详细数据'!J104 | L73: =K73/J73 | M73: 车内 | N73: 司机自发装置 | P73: 7509 | Q73: =IF(J73="","",IF(J73>=500000,"S 级",IF(J73>=100000,"A 级",IF(J73>=50000,"B 级","C 级"))))
A74: 46106 | B74: =A74+7 | C74: 投放完毕 | D74: 紫苏草 | E74: https://www.douyin.com/video/7621131594221657457 | F74: 2026/3/27投放1000元 | G74: 刮风下雨都是叫滴滴上下班，儿子说领导也是地铁上班，停车太难，路上又堵，他还说买了车天天晒太阳，天天掉价，还要停车费，各种费用，学车也要钱，还要时间，坚决不要车，所以说我家没有车，我觉得挺好，上海滴滴便宜，叫车很快接单！ | H74: 368 | I74: ='详细数据'!AC103 | J74: 1098 | K74: ='详细数据'!J103 | L74: =K74/J74 | M74: 产品力 | N74: 价格优惠 | P74: 1098 | Q74: =IF(J74="","",IF(J74>=500000,"S 级",IF(J74>=100000,"A 级",IF(J74>=50000,"B 级","C 级"))))
A75: 46107 | B75: =A75+7 | C75: 投放完毕 | D75: 已重置 | E75: https://www.douyin.com/note/7621580768725255525 | F75: 2026/3/27投放1000元2026/3/30投放10000元2026/3/31投放10000元2026/4/1投放10000元 | G75: 谁懂啊!打车遇到退役军人司机，安全感直接拉满#滴滴司机 师傅说：“以前保家卫国，现在保你平安到家~”#暖心瞬间 #退役军人 #打车奇遇 | H75: 546 | I75: ='详细数据'!AC102+'详细数据'!AC117+'详细数据'!AC122+'详细数据'!AC129 | J75: 789775 | K75: ='详细数据'!J102+'详细数据'!J117+'详细数据'!J122+'详细数据'!J129 | L75: =K75/J75 | M75: 司机 | N75: 特殊身份-退伍军人 | P75: 1355985 | Q75: =IF(J75="","",IF(J75>=500000,"S 级",IF(J75>=100000,"A 级",IF(J75>=50000,"B 级","C 级"))))
A76: 46107 | B76: =A76+7 | C76: 投放完毕 | D76: 鱼丸子的快乐星球🫧 | E76: https://www.douyin.com/note/7621539907975294329 | F76: 2026/3/27投放1000元 | G76: 谁能懂上车那一刻的惊喜感呀哈哈~ 今日份最快乐的事情莫过于~花最低的💰打到了一辆喜爱的车哈哈#滴滴出行 #打车打到特斯拉 #真实生活分享计划 #特斯拉model3 | H76: 131 | I76: ='详细数据'!AC101 | J76: 611 | K76: ='详细数据'!J101 | L76: =K76/J76 | M76: 车内 | N76: 特殊车型/车衣 | P76: 656 | Q76: =IF(J76="","",IF(J76>=500000,"S 级",IF(J76>=100000,"A 级",IF(J76>=50000,"B 级","C 级"))))
A77: 46109 | B77: =A77+7 | C77: 投放完毕 | D77: 晓雅姐 | E77: https://www.douyin.com/note/7622163930036053684 | F77: 2026/3/30投放1000元 | G77: #出行 #专车接送 今天遇到了好司机， | H77: 610 | I77: ='详细数据'!AC113 | J77: 2383 | K77: ='详细数据'!J113 | L77: =K77/J77 | M77: 产品力 | N77: 专车/豪华车 | P77: 2540 | Q77: =IF(J77="","",IF(J77>=500000,"S 级",IF(J77>=100000,"A 级",IF(J77>=50000,"B 级","C 级"))))
A78: 46108 | B78: =A78+7 | C78: 投放完毕 | D78: 无情四季豆 | E78: https://www.douyin.com/video/7621965075905249910 | F78: 2026/3/30投放1000元2026/3/31投放5000元 | G78: 真的被成都滴滴师傅的善意感动到了 | H78: 1062 | I78: ='详细数据'!AC114+'详细数据'!AC123 | J78: 27238 | K78: ='详细数据'!J114+'详细数据'!J123 | L78: =K78/J78 | M78: 司机 | N78: 司乘温暖 | P78: 30202 | Q78: =IF(J78="","",IF(J78>=500000,"S 级",IF(J78>=100000,"A 级",IF(J78>=50000,"B 级","C 级"))))
A79: 46108 | B79: =A79+7 | C79: 投放完毕 | D79: 一口甜☁️⋆ | E79: https://www.douyin.com/note/7621904670667781553 | F79: 2026/3/30投放1000元2026/3/31投放10000元2026/4/1投放10000元2026/4/2投放10000元 | G79: 打车的意外惊喜，一整车的柠檬香扑而来 | H79: 4966 | I79: ='详细数据'!AC112+'详细数据'!AC121+'详细数据'!AC128+'详细数据'!AB130 | J79: 377923 | K79: ='详细数据'!J112+'详细数据'!J121+'详细数据'!J128+'详细数据'!I130 | L79: =K79/J79 | M79: 车内 | N79: 香卡 | O79: 10000 | P79: 461464 | Q79: =IF(J79="","",IF(J79>=500000,"S 级",IF(J79>=100000,"A 级",IF(J79>=50000,"B 级","C 级"))))
A80: 46108 | B80: =A80+7 | C80: 投放完毕 | D80: 丸o.Q | E80: https://www.douyin.com/note/7621941211725617849 | F80: 2026/3/30投放1000元2026/3/31投放5000元 | G80: 滴滴公交 拯救不会骑车的大学生！#厉害了我的车 #每天必打开的软件 #每天冷知识 #还有这种操作 #滴滴公交车 | H80: 2975 | I80: ='详细数据'!AC111+'详细数据'!AC120 | J80: 15820 | K80: ='详细数据'!J111+'详细数据'!J120 | L80: =K80/J80 | M80: 产品力 | N80: 网约公交 | P80: 17200 | Q80: =IF(J80="","",IF(J80>=500000,"S 级",IF(J80>=100000,"A 级",IF(J80>=50000,"B 级","C 级"))))
A81: 46110 | B81: =A81+7 | C81: 投放完毕 | D81: 王多鱼🐟（文哥） | E81: https://www.douyin.com/video/7622625731391179151 | F81: 2026/3/30投放1000元 | G81: 体验一下网约公交 | H81: 34 | I81: ='详细数据'!AC115 | J81: 1843 | K81: ='详细数据'!J115 | L81: =K81/J81 | M81: 产品力 | N81: 网约公交 | P81: 1854 | Q81: =IF(J81="","",IF(J81>=500000,"S 级",IF(J81>=100000,"A 级",IF(J81>=50000,"B 级","C 级"))))
A82: 46110 | B82: =A82+7 | C82: 投放完毕 | D82: 隆A📸客LianA | E82: https://www.douyin.com/video/7622531685897224689 | F82: 2026/3/30投放1000元 | G82: 天等至南宁 超大滴滴巴士，每天只有两台车在跑三趟？🤔#广西超大运输集团 #客运 #文明出行 | H82: 88 | I82: ='详细数据'!AC116 | J82: 288 | K82: ='详细数据'!J116 | L82: =K82/J82 | M82: 产品力 | N82: 站点巴士 | P82: 310 | Q82: =IF(J82="","",IF(J82>=500000,"S 级",IF(J82>=100000,"A 级",IF(J82>=50000,"B 级","C 级"))))
A83: 46111 | B83: =A83+7 | C83: 投放完毕 | D83: 傻二哥 | E83: https://www.douyin.com/note/7622970947830529457 | F83: 2026/3/31投放1000元 | G83: 深圳爱心接力！志愿者极速奔跑+滴滴积极相助，遗失手机发车前1分钟物归原主，旅客泪目致谢。 | H83: 187 | I83: ='详细数据'!AC119 | J83: 566 | K83: ='详细数据'!J119 | L83: =K83/J83 | M83: 司机 | N83: 失物返还 | P83: 609 | Q83: =IF(J83="","",IF(J83>=500000,"S 级",IF(J83>=100000,"A 级",IF(J83>=50000,"B 级","C 级"))))
A84: 46111 | B84: =A84+7 | C84: 投放完毕 | D84: Guci. | E84: https://www.douyin.com/note/7623066471988239337 | F84: 2026/3/31投放1000元2026/4/1投放5000元2026/4/2投放5000元 | G84: 谁懂啊!打车遇到，退役军人司机安全感直接拉满#滴滴司机 师傅说：“以前保家卫国，现在保你平安到家#退役军人 #暖心瞬间 #打车奇遇 | H84: 264 | I84: ='详细数据'!AC118+'详细数据'!AB127+'详细数据'!AC131 | J84: 121178 | K84: ='详细数据'!J118+'详细数据'!I127+'详细数据'!J131 | L84: =K84/J84 | M84: 司机 | N84: 特殊身份-退伍军人 | O84: 5000 | P84: 121317 | Q84: =IF(J84="","",IF(J84>=500000,"S 级",IF(J84>=100000,"A 级",IF(J84>=50000,"B 级","C 级"))))
A85: 46111 | B85: =A85+7 | C85: 投放完毕 | D85: 沐沐小食光 | E85: https://www.douyin.com/video/7623026166921225970 | F85: 2026/4/1投放1000元 | G85: 这滴滴车也太干净了吧！一点异味都没有关键是这车跑了十几万公里了，还能保持的这么干净我一个女人自己的车都没法比，惭愧啊#靠谱男司机 #杭州滴滴 #打车 #滴滴司机 | H85: 156 | I85: ='详细数据'!AC126 | J85: 2790 | K85: ='详细数据'!J126 | L85: =K85/J85 | M85: 车内 | N85: 车内整洁 | P85: 2908 | Q85: =IF(J85="","",IF(J85>=500000,"S 级",IF(J85>=100000,"A 级",IF(J85>=50000,"B 级","C 级"))))
A86: 46112 | B86: =A86+7 | C86: 投放完毕 | D86: AO王的偏爱²⁰²⁶ | E86: https://www.douyin.com/video/7623358535632128435 | F86: 2026/4/1投放1000元 | G86: #大巴车 | H86: 136 | I86: ='详细数据'!AC125 | J86: 3438 | K86: ='详细数据'!J125 | L86: =K86/J86 | M86: 产品力 | N86: 站点巴士 | P86: 4163 | Q86: =IF(J86="","",IF(J86>=500000,"S 级",IF(J86>=100000,"A 级",IF(J86>=50000,"B 级","C 级"))))
A87: 46112 | B87: =A87+7 | C87: 投放完毕 | D87: 早早早早睡 | E87: https://www.douyin.com/note/7623367834466321253 | F87: 2026/4/1投放1000元 | G87: 打到这种滴滴网约车 扑面而来的安全感#退役军人 #滴滴司机 #致敬 #滴滴司机 | H87: 79 | I87: ='详细数据'!AC124 | J87: 286 | K87: ='详细数据'!J124 | L87: =K87/J87 | M87: 司机 | N87: 特殊身份-退伍军人 | P87: 306 | Q87: =IF(J87="","",IF(J87>=500000,"S 级",IF(J87>=100000,"A 级",IF(J87>=50000,"B 级","C 级"))))
A88: 46112 | B88: =A88+7 | C88: 投放完毕 | D88: 不羁的风 | E88: https://www.douyin.com/note/7623407790573423066 | F88: 2026/4/2投放1000元 | G88: 上海今天的雨很大不仅打湿了我的双眸还把这座魔幻城市冲刷得焕然一新通过抖音平台实名表扬这位滴滴司机 | H88: 75 | I88: ='详细数据'!AC133 | J88: 533 | K88: ='详细数据'!J133 | L88: =K88/J88 | M88: 司机 | N88: 司机服务 | P88: 535 | Q88: =IF(J88="","",IF(J88>=500000,"S 级",IF(J88>=100000,"A 级",IF(J88>=50000,"B 级","C 级"))))

Sheet 4月加热汇总
A1: 发布日期 | B1: 投放截止日期 | C1: 状态 | D1: 达人名称 | E1: 链接 | F1: 投放记录 xx日投放xx元 | G1: 标题 | H1: 投前互动量 | I1: 投放互动量 | J1: 投放后点赞量 | K1: 投放后收藏量 | L1: 投放后评论量 | M1: 投放后转发量 | N1: 总互动量 | O1: 总投放金额 | P1: 综合cpe *投入/笔记外层互动数据 | Q1: 一级分类 | R1: 二级分类 | S1: 备注 | T1: 爆款定级
A2: 汇总 | H2: - | I2: - | N2: =SUM(N3:N98) | O2: =SUM(O3:O98) | P2: =O2/N2
A3: 46113 | B3: =A3+7 | C3: 投放完毕 | D3: 养一只蒙丢丢 | E3: https://www.douyin.com/video/7623768838857578048 | F3: 2026/4/2投放1000元 | G3: 北京的滴滴司机也太好了吧🤗，滴滴快车享受专车都享受不了的待遇，快下车了看我们都没拿，然后他抓了四个🍊送到了我们手里边#抖加小助手 #抖音热门 #抖音热门小助手 | H3: 99 | I3: ='详细数据'!AC132 | J3: 3830 | K3: 35 | L3: 49 | M3: 174 | N3: =SUM(J3:M3) | O3: ='详细数据'!J132 | P3: =O3/N3 | Q3: 司机 | R3: 司乘温暖 | T3: =IF(N3="","",IF(N3>=500000,"S 级",IF(N3>=100000,"A 级",IF(N3>=50000,"B 级","C 级"))))
A4: 46114 | B4: =A4+7 | C4: 投放完毕 | D4: 晓雅姐 | E4: https://www.douyin.com/note/7624113880570299215 | F4: 2026/4/3投放1000元 | G4: #出行 #专车接送 乘坐这样的专车出行，怎么会有司乘矛盾呢。 | H4: 81 | I4: ='详细数据'!AC134 | J4: 1407 | K4: 39 | L4: 56 | M4: 3 | N4: =SUM(J4:M4) | O4: ='详细数据'!J133 | P4: =O4/N4 | Q4: 产品力 | R4: 专车/豪华车 | T4: =IF(N4="","",IF(N4>=500000,"S 级",IF(N4>=100000,"A 级",IF(N4>=50000,"B 级","C 级"))))
A5: 46116 | B5: =A5+7 | C5: 投放完毕 | D5: Maisy | E5: https://www.douyin.com/video/7624862115832787121 | F5: 2026/4/7投放1000元2026/4/8投放5000元 | G5: 大雨着急去和朋友吃饭被困在公司于是滴滴师傅把车停在最近的停车场带伞来接我 路上跟我描述车况并一直道歉 从前这样的事情只有父亲做过 相同的还有那把倾斜的伞和淋湿的衣服#雨 #沈阳美食 #滴滴司机 #服务业 | H5: 474 | I5: ='详细数据'!AC139 | J5: 24000 | K5: 347 | L5: 1815 | M5: 410 | N5: =SUM(J5:M5) | O5: ='详细数据'!J134+'详细数据'!J141 | P5: =O5/N5 | Q5: 司机 | R5: 司乘温暖 | T5: =IF(N5="","",IF(N5>=500000,"S 级",IF(N5>=100000,"A 级",IF(N5>=50000,"B 级","C 级"))))
A6: 46115 | B6: =A6+7 | C6: 投放完毕 | D6: 真褒义词！ | E6: https://www.douyin.com/video/7624320840444438116 | F6: 2026/4/7投放1000元 | G6: 重庆新华网你好事做尽！！！！也是在滴滴上自己点歌了#重庆 #张云雷 #滴滴出行 | H6: 90 | I6: ='详细数据'!AC138 | J6: 1666 | K6: 52 | L6: 35 | M6: 10 | N6: =SUM(J6:M6) | O6: ='详细数据'!J135 | P6: =O6/N6 | Q6: 车内 | R6: 司机自发装置 | T6: =IF(N6="","",IF(N6>=500000,"S 级",IF(N6>=100000,"A 级",IF(N6>=50000,"B 级","C 级"))))
A7: 46117 | B7: =A7+7 | C7: 投放完毕 | D7: 茉 | E7: https://www.douyin.com/note/7625245014687938233 | F7: 2026/4/7投放1000元 | G7: 女性主义。今天经历了很多幸福的事情。第一件事：今天第一次启用了刷到的“滴滴女性友好计划”，即优先推荐女司机。 | H7: 189 | I7: ='详细数据'!AC137 | J7: 1963 | K7: 37 | L7: 15 | M7: 21 | N7: =SUM(J7:M7) | O7: ='详细数据'!J136 | P7: =O7/N7 | Q7: 产品力 | R7: 女性友好计划 | T7: =IF(N7="","",IF(N7>=500000,"S 级",IF(N7>=100000,"A 级",IF(N7>=50000,"B 级","C 级"))))
A8: 46117 | B8: =A8+7 | C8: 投放完毕 | D8: ￴￴ ￴￴陈伟 | E8: https://www.douyin.com/note/7624963816623740027 | F8: 2026/4/7投放1000元2026/4/8投放10000元2026/4/9投放5000元2026/4/10投放5000元 | G8: 那天我打了个滴滴 和往常一样开了车门要准备上车 可那天我一打开车门映入眼帘看到司机车上贴满了各国的钞票 和各国的祝福语 | H8: 88 | I8: ='详细数据'!AC136+'详细数据'!AC145+'详细数据'!AC149 | J8: 287000 | K8: 5917 | L8: 637 | M8: 24000 | N8: =SUM(J8:M8) | O8: ='详细数据'!J137+'详细数据'!J140+'详细数据'!J145+'详细数据'!J149 | P8: =O8/N8 | Q8: 车内 | R8: 司机自发装置 | T8: =IF(N8="","",IF(N8>=500000,"S 级",IF(N8>=100000,"A 级",IF(N8>=50000,"B 级","C 级"))))
A9: 46117 | B9: =A9+7 | C9: 投放完毕 | D9: 牙抖音不抖🪥 | E9: https://www.douyin.com/video/7625090564824947065 | F9: 2026/4/7投放1000元 | G9: 长见识了，才知道还有滴滴公交车3块钱一个人#滴滴公交车 # | H9: 35 | I9: ='详细数据'!AC135 | J9: 2298 | K9: 51 | L9: 84 | M9: 107 | N9: =SUM(J9:M9) | O9: ='详细数据'!J138 | P9: =O9/N9 | Q9: 产品力 | R9: 网约公交 | T9: =IF(N9="","",IF(N9>=500000,"S 级",IF(N9>=100000,"A 级",IF(N9>=50000,"B 级","C 级"))))
A10: 46119 | B10: =A10+7 | C10: 投放完毕 | D10: 纯爷们 | E10: https://www.douyin.com/note/7625760714330410816 | F10: 2026/4/8投放835.21元 | G10: 昨天肚子疼了一天，从早上九点多到夜里十一点多，实在忍不住了，去了医院，结果说是急性阑尾炎。 | H10: 81 | I10: ='详细数据'!AC143 | J10: 图文下线 | N10: =SUM(J10:M10) | O10: ='详细数据'!J143 | P10: =O10/N10 | Q10: 场景 | R10: 医院/就医 | T10: =IF(N10="","",IF(N10>=500000,"S 级",IF(N10>=100000,"A 级",IF(N10>=50000,"B 级","C 级"))))
A11: 46119 | B11: =A11+7 | C11: 在投 | D11: 哎呦～wei♞🌽 | E11: https://www.douyin.com/note/7625846621917471208 | F11: 2026/4/8投放1000元 | G11: 兖州真的是一个很有爱的城市，滴滴师傅都好有礼貌，也很有爱心 | H11: 87 | I11: ='详细数据'!AC142 | J11: 542 | K11: 34 | L11: 12 | M11: 3 | N11: =SUM(J11:M11) | O11: ='详细数据'!J142 | P11: =O11/N11 | Q11: 司机 | R11: 司机服务 | T11: =IF(N11="","",IF(N11>=500000,"S 级",IF(N11>=100000,"A 级",IF(N11>=50000,"B 级","C 级"))))
A12: 46120 | B12: =A12+7 | C12: 投放完毕 | D12: 晓雅姐 | E12: https://www.douyin.com/note/7626240521292568483 | F12: 2026/4/9投放1000元 | G12: #出行 #专车接送 稳稳的好评给这司机，上车没有多久就很困睡着了 | H12: 132 | I12: ='详细数据'!AC144 | J12: 2000 | K12: 37 | L12: 87 | M12: 12 | N12: =SUM(J12:M12) | O12: ='详细数据'!J144 | P12: =O12/N12 | Q12: 产品力 | R12: 专车/豪华车 | T12: =IF(N12="","",IF(N12>=500000,"S 级",IF(N12>=100000,"A 级",IF(N12>=50000,"B 级","C 级"))))
A13: 46120 | B13: =A13+7 | C13: 投放完毕 | D13: 朵朵妹妹 | E13: https://www.douyin.com/video/7626383694223907429 | F13: 2026/4/10投放1000元 | G13: 这次体验感真的超好，坐到了极氪009，晕车的我突然不晕了，司机亲自开门，车上再也没有异味，都是香香的，有吃有喝 | H13: 96 | I13: ='详细数据'!AC148 | J13: 2089 | K13: 54 | L13: 177 | M13: 75 | N13: =SUM(J13:M13) | O13: ='详细数据'!J148 | P13: =O13/N13 | Q13: 车内 | R13: 特殊车型/车衣 | T13: =IF(N13="","",IF(N13>=500000,"S 级",IF(N13>=100000,"A 级",IF(N13>=50000,"B 级","C 级"))))
A14: 46121 | B14: =A14+7 | C14: 投放完毕 | D14: 善缘 | E14: https://www.douyin.com/note/7626557894406165434 | F14: 2026/4/10投放1000元 | G14: 这两天被太多温柔善意包裹着 | H14: 101 | I14: ='详细数据'!AC147 | J14: 1848 | K14: 66 | L14: 121 | M14: 3 | N14: =SUM(J14:M14) | O14: ='详细数据'!J147 | P14: =O14/N14 | Q14: 司机 | R14: 司乘温暖 | T14: =IF(N14="","",IF(N14>=500000,"S 级",IF(N14>=100000,"A 级",IF(N14>=50000,"B 级","C 级"))))
A15: 46121 | B15: =A15+7 | C15: 投放完毕 | D15: 薇薇安的闪电侠 | E15: https://www.douyin.com/video/7626715483103183604 | F15: 2026/4/10投放1000元 | G15: 第一次打到播放音乐的滴滴打车，还是我喜欢的音乐，并且还不臭的车，必须给司机大哥发个红包表示感谢一下，希望司机不要嫌弃太少哈 #滴滴打车 | H15: 83 | I15: ='详细数据'!AC146 | J15: 3338 | K15: 82 | L15: 244 | M15: 28 | N15: =SUM(J15:M15) | O15: ='详细数据'!J146 | P15: =O15/N15 | Q15: 车内 | R15: 司机自发装置 | T15: =IF(N15="","",IF(N15>=500000,"S 级",IF(N15>=100000,"A 级",IF(N15>=50000,"B 级","C 级"))))
A16: 46123 | B16: =A16+7 | C16: 投放完毕 | D16: Y悟空 | E16: https://www.douyin.com/video/7627467421783603045 | F16: 2026/4/13投放1000元2026/4/14投放5000元2026/4/15投放10000元 | G16: #潮玩驾驶 #车载搭子 #滴滴司机 | H16: 367 | I16: ='详细数据'!AC153+'详细数据'!AC154+'详细数据'!AC158 | J16: 131000 | K16: 2525 | L16: 1003 | M16: 32000 | N16: =SUM(J16:M16) | O16: ='详细数据'!J153+'详细数据'!J154+'详细数据'!J158 | P16: =O16/N16 | Q16: 车内 | R16: 司机自发装置 | T16: =IF(N16="","",IF(N16>=500000,"S 级",IF(N16>=100000,"A 级",IF(N16>=50000,"B 级","C 级"))))
A17: 46122 | B17: =A17+7 | C17: 投放完毕 | D17: 人间小迷糊 | E17: https://www.douyin.com/note/7626984999901013113 | F17: 2026/4/13投放1000元 | G17: 今天的滴滴司机应该是一个灵魂很有趣的人呢👍多么可可爱爱ෆ╹ .̮ ╹ෆ的人，才能配出这么有趣的文字~ | H17: 74 | I17: ='详细数据'!AC152 | J17: 272 | K17: 21 | L17: 14 | M17: 16 | N17: =SUM(J17:M17) | O17: ='详细数据'!J152 | P17: =O17/N17 | Q17: 车内 | R17: 留言本 | T17: =IF(N17="","",IF(N17>=500000,"S 级",IF(N17>=100000,"A 级",IF(N17>=50000,"B 级","C 级"))))
A18: 46123 | B18: =A18+7 | C18: 无法投放 | D18: 黄山竹 | E18: https://www.douyin.com/note/7627440028503106771 | G18: 方便市民出行 | H18: 64
A19: 46124 | B19: =A19+7 | C19: 投放完毕 | D19: beo_mmunga_ | E19: https://www.douyin.com/video/7627890045047581027 | F19: 2026/4/13投放598.97元 | G19: 遇到了这辈子最合拍的滴滴师傅😂😂#滴滴司机 #心软的神 #k歌之王 | H19: 79 | I19: ='详细数据'!AC150 | J19: 视频下线 | N19: =SUM(J19:M19) | O19: ='详细数据'!J150 | P19: =O19/N19 | Q19: 司机 | R19: 司乘互动 | T19: =IF(N19="","",IF(N19>=500000,"S 级",IF(N19>=100000,"A 级",IF(N19>=50000,"B 级","C 级"))))
A20: 46125 | B20: =A20+7 | C20: 投放完毕 | D20: CHN | E20: https://www.douyin.com/video/7628055768176180586 | F20: 2026/4/14投放1000元 | G20: 滴滴真的什么车都能打到！曾经的豪华电车，有幸优享到了，车还是很不错的，尤其劳斯莱斯的开门！ #高合hiphix #滴滴 #新能源汽车 | H20: 128 | I20: ='详细数据'!AC156 | J20: 2013 | K20: 64 | L20: 72 | M20: 60 | N20: =SUM(J20:M20) | O20: ='详细数据'!J156 | P20: =O20/N20 | Q20: 车内 | R20: 特殊车型/车衣 | T20: =IF(N20="","",IF(N20>=500000,"S 级",IF(N20>=100000,"A 级",IF(N20>=50000,"B 级","C 级"))))
A21: 46124 | B21: =A21+7 | C21: 投放完毕 | D21: ☎️@永欢生态农场 | E21: https://www.douyin.com/video/7627656361078613477 | F21: 2026/4/14投放1000元 | G21: 打个滴滴司机师傅都是个美女，现在行业那么卷了吗？ | H21: 82 | I21: ='详细数据'!AC155 | J21: 2941 | K21: 57 | L21: 111 | M21: 24 | N21: =SUM(J21:M21) | O21: ='详细数据'!J155 | P21: =O21/N21 | Q21: 司机 | R21: 女司机 | T21: =IF(N21="","",IF(N21>=500000,"S 级",IF(N21>=100000,"A 级",IF(N21>=50000,"B 级","C 级"))))
A22: 46126 | B22: =A22+7 | C22: 投放完毕 | D22: 茉香·姜婷婷 | E22: https://www.douyin.com/video/7628568501427008241 | F22: 2026/4/15投放1000元 | G22: 我们不是他人口中的“小店小厂”，当我们集结成为匠心联盟，蚂蚁军团可食象。 | H22: 184 | I22: ='详细数据'!AC159 | J22: 1108 | K22: 71 | L22: 49 | M22: 21 | N22: =SUM(J22:M22) | O22: ='详细数据'!J159 | P22: =O22/N22 | Q22: 无匹配类别 | R22: 无匹配类别 | T22: =IF(N22="","",IF(N22>=500000,"S 级",IF(N22>=100000,"A 级",IF(N22>=50000,"B 级","C 级"))))
A23: 46126 | B23: =A23+7 | C23: 投放完毕 | D23: 保山小韩 | E23: https://www.douyin.com/video/7628593020561465713 | F23: 2026/4/15投放1000元 | G23: 这是我坐过最暖心的滴滴车，人都会疲惫，会黯淡，但也会因为某个瞬间重新爱上生活#滴滴车内的小细节#云南保山#治愈世界治愈你 | H23: 242 | I23: ='详细数据'!AC157 | J23: 3088 | K23: 43 | L23: 84 | M23: 525 | N23: =SUM(J23:M23) | O23: ='详细数据'!J157 | P23: =O23/N23 | Q23: 车内 | R23: 司机自发装置 | T23: =IF(N23="","",IF(N23>=500000,"S 级",IF(N23>=100000,"A 级",IF(N23>=50000,"B 级","C 级"))))
A24: 46125 | B24: =A24+7 | C24: 投放完毕 | D24: 恭喜啊小富婆 | E24: https://www.douyin.com/video/7628175992222109553 | F24: 2026/4/16投放1000元 | G24: 隔一天洗一次！干一行爱一行，一行白鹭上青天！ #滴滴司机 #日常vlog #搞笑 #搞笑视频 #出门必备 | H24: 72 | I24: ='详细数据'!AC161 | J24: 1737 | K24: 27 | L24: 50 | M24: 6 | N24: =SUM(J24:M24) | O24: ='详细数据'!J161 | P24: =O24/N24 | Q24: 无匹配类别 | R24: 无匹配类别 | T24: =IF(N24="","",IF(N24>=500000,"S 级",IF(N24>=100000,"A 级",IF(N24>=50000,"B 级","C 级"))))
A25: 46128 | B25: =A25+7 | C25: 投放完毕 | D25: 汪涛和导盲犬叮当 | E25: https://www.douyin.com/video/7629141999672840169 | F25: 2026/4/16投放1000元2026/4/17投放5000元 | G25: 带导盲犬叮当在福州坐滴滴，被一位暖心交警狠狠治愈。 带着导盲犬叮当在福州路边等候滴滴，因视线不便，我只能将手机贴在耳边听单，加上排队车辆较多，在路口徘徊等待了很久。 | H25: 347 | I25: ='详细数据'!AC160+'详细数据'!AC163 | J25: 19000 | K25: 297 | L25: 115 | M25: 91 | N25: =SUM(J25:M25) | O25: ='详细数据'!J160+'详细数据'!J163 | P25: =O25/N25 | Q25: 司机 | R25: 司乘温暖 | T25: =IF(N25="","",IF(N25>=500000,"S 级",IF(N25>=100000,"A 级",IF(N25>=50000,"B 级","C 级"))))
A26: 46127 | B26: =A26+7 | C26: 投放完毕 | D26: 兵哥跑车 | E26: https://www.douyin.com/video/7628928486560089529 | F26: 2026/4/17投放1000元 | G26: 滴滴香卡来啦#滴滴北京限定香卡 #把北京景点挂到车上 | H26: 929 | I26: ='详细数据'!AC162 | J26: 1439 | K26: 59 | L26: 33 | M26: 3 | N26: =SUM(J26:M26) | O26: ='详细数据'!J162 | P26: =O26/N26 | Q26: 车内 | R26: 香卡 | T26: =IF(N26="","",IF(N26>=500000,"S 级",IF(N26>=100000,"A 级",IF(N26>=50000,"B 级","C 级"))))
A27: 46131 | B27: =A27+7 | C27: 投放完毕 | D27: 桃子欧尼 | E27: https://www.douyin.com/note/7630389147651540148 | F27: 2026/4/20投放1000元 | G27: 加班的坏心情得到了治愈～#打车奇遇 #退役军人 #滴滴司机 #致敬 #dou上热门 | H27: 112 | I27: ='详细数据'!AC171 | J27: 2872 | K27: 15 | L27: 29 | M27: 57 | N27: =SUM(J27:M27) | O27: ='详细数据'!J171 | P27: =O27/N27 | Q27: 司机 | R27: 特殊身份-退伍军人 | T27: =IF(N27="","",IF(N27>=500000,"S 级",IF(N27>=100000,"A 级",IF(N27>=50000,"B 级","C 级"))))
A28: 46131 | B28: =A28+7 | C28: 投放完毕 | D28: 🧀 | E28: https://www.douyin.com/note/7630280919329366708 | F28: 2026/4/20投放1000元 | G28: 第一次打到聋哑人司机的车，上车习惯性报了手机尾号，没注意到提示牌 习惯性跟司机打招呼 没理我 当我抬头的时候司机拿着提示牌给我看 这才明白他是 | H28: 448 | I28: ='详细数据'!AC170 | J28: 1421 | K28: 14 | L28: 19 | M28: 8 | N28: =SUM(J28:M28) | O28: ='详细数据'!J170 | P28: =O28/N28 | Q28: 司机 | R28: 特殊身份-听障司机 | T28: =IF(N28="","",IF(N28>=500000,"S 级",IF(N28>=100000,"A 级",IF(N28>=50000,"B 级","C 级"))))
A29: 46131 | B29: =A29+7 | C29: 投放完毕 | D29: 佩琪 | E29: https://www.douyin.com/video/7630163601161398178 | F29: 2026/4/20投放1000元 | G29: #滴滴司机 今天遇到一个57岁还在开滴滴的叔叔，他说他要挣钱，他儿子开了一个装修公司在亏钱，他希望可以帮他一把，看见他跟我父亲的年龄差不多大，莫名有一股亲切 | H29: 259 | I29: ='详细数据'!AC166 | J29: 1086 | K29: 28 | L29: 68 | M29: 11 | N29: =SUM(J29:M29) | O29: ='详细数据'!J166 | P29: =O29/N29 | Q29: 司机 | R29: 司乘互动 | T29: =IF(N29="","",IF(N29>=500000,"S 级",IF(N29>=100000,"A 级",IF(N29>=50000,"B 级","C 级"))))
A30: 46130 | B30: =A30+7 | C30: 在投 | D30: 知青 | E30: https://www.douyin.com/video/7629911775865505906 | F30: 2026/4/20投放1000元 | G30: 上午去南昌汉代海昏候博物馆参观，我乘坐滴滴网约车，有幸遇上一个即开车技术好，又是南昌通的师傅，让我一路开心。#南昌交通 #司机 #夫妻日常 #海昏侯博物馆 | H30: 92 | I30: ='详细数据'!AC169 | J30: 857 | K30: 63 | L30: 42 | M30: 2 | N30: =SUM(J30:M30) | O30: ='详细数据'!J169 | P30: =O30/N30 | Q30: 场景 | R30: 旅游出行 | T30: =IF(N30="","",IF(N30>=500000,"S 级",IF(N30>=100000,"A 级",IF(N30>=50000,"B 级","C 级"))))
A31: 46130 | B31: =A31+7 | C31: 投放完毕 | D31: 汪涛和导盲犬叮当 | E31: https://www.douyin.com/video/7630071089049654198 | F31: 2026/4/20投放1000元 | G31: 带叮当在福州坐滴滴遇到一位热心司机，一路交谈满是温暖！ 带着导盲犬叮当出行，在福州偶遇一位暖心滴滴司机。一路交谈满是善意，司机细心询问导盲犬的相关事宜 | H31: 202 | I31: ='详细数据'!AC168 | J31: 464 | K31: 32 | L31: 28 | M31: 7 | N31: =SUM(J31:M31) | O31: ='详细数据'!J168 | P31: =O31/N31 | Q31: 司机 | R31: 司机服务 | T31: =IF(N31="","",IF(N31>=500000,"S 级",IF(N31>=100000,"A 级",IF(N31>=50000,"B 级","C 级"))))
A32: 46131 | B32: =A32+7 | C32: 投放完毕 | D32: 英 | E32: https://www.douyin.com/video/7630474109919557051 | F32: 2026/4/20投放1000元 | G32: 2026.4.19日，今天从峨眉坐滴滴巴士来成都，就是为了明天带妈妈到华西看病。提前一天过来，就是为了省钱、省时间、少折腾。 | H32: 7 | I32: ='详细数据'!AC167 | J32: 230 | K32: 27 | L32: 12 | M32: 2 | N32: =SUM(J32:M32) | O32: ='详细数据'!J167 | P32: =O32/N32 | Q32: 场景 | R32: 医院/就医 | T32: =IF(N32="","",IF(N32>=500000,"S 级",IF(N32>=100000,"A 级",IF(N32>=50000,"B 级","C 级"))))
A33: 46131 | B33: =A33+7 | C33: 投放完毕 | D33: 飘雪 | E33: https://www.douyin.com/video/7630433467185514597 | F33: 2026/4/20投放1000元 | G33: #滴滴站点巴士 #成都到广元39.9 | H33: 46 | I33: ='详细数据'!AC165 | J33: 253 | K33: 18 | L33: 13 | M33: 2 | N33: =SUM(J33:M33) | O33: ='详细数据'!J165 | P33: =O33/N33 | Q33: 产品力 | R33: 站点巴士 | T33: =IF(N33="","",IF(N33>=500000,"S 级",IF(N33>=100000,"A 级",IF(N33>=50000,"B 级","C 级"))))
A34: 46129 | B34: =A34+7 | C34: 无法投放 | D34: 楚楚爱济宁 | E34: https://www.douyin.com/video/7629612388421693945 | G34: 滴滴站点巴士 🚌 它来啦～#嘉祥 #济宁 #滴滴站点巴士 #方便又实用 #出行 | H34: 950 | N34: =SUM(J34:M34) | P34: =O34/N34
A35: 46128 | B35: =A35+7 | C35: 投放完毕 | D35: 悠悠的视界 | E35: https://www.douyin.com/video/7629126711086685289 | F35: 2026/4/20投放1000元 | G35: 武汉人去黄石也太方便了吧，黄石首条滴滴站点巴士线路要来了，黄石往返武汉线路将于4月16日正式通车，往返双向车票黄石至武昌线路限时体验价14.9元起#黄石到武汉 #滴滴站点巴士 #黄石出行 #武汉通勤 #城际出行 | H35: 2031 | I35: ='详细数据'!AC164 | J35: 970 | K35: 280 | L35: 171 | M35: 1006 | N35: =SUM(J35:M35) | O35: ='详细数据'!J164 | P35: =O35/N35 | Q35: 产品力 | R35: 站点巴士 | T35: =IF(N35="","",IF(N35>=500000,"S 级",IF(N35>=100000,"A 级",IF(N35>=50000,"B 级","C 级"))))
A36: 46127 | B36: =A36+7 | C36: 无法投放 | D36: 叶同学 | E36: https://www.douyin.com/video/7628801934065316517 | G36: 厦门龙海往返出行的神仙级路线开了！滴巴上线啦！提前购票只要9.9，真的很划算#龙海厦门 #龙海巴士 #漳州交通 #跨城上班 #周末回家省钱攻略 | H36: 2636 | N36: =SUM(J36:M36) | P36: =O36/N36
A37: 46132 | B37: =A37+7 | C37: 投放完毕 | D37: 年年 | E37: https://www.douyin.com/video/7630833058359450441 | F37: 2026/4/22投放1000元 | G37: 岳阳的滴滴司机这么有节目的吗？！听爽了！！#GAI #功夫胖 #山歌王 | H37: 82 | I37: ='详细数据'!AC174 | J37: 1266 | K37: 47 | L37: 53 | M37: 95 | N37: =SUM(J37:M37) | O37: ='详细数据'!J174 | P37: =O37/N37 | Q37: 司机 | R37: 司乘互动 | T37: =IF(N37="","",IF(N37>=500000,"S 级",IF(N37>=100000,"A 级",IF(N37>=50000,"B 级","C 级"))))
A38: 46133 | B38: =A38+7 | C38: 投放完毕 | D38: 余梦似海 | E38: https://www.douyin.com/video/7631145389820062201 | F38: 2026/4/22投放1000元 | G38: 姐妹们！高德打车跟滴滴打车是有区别的你们知道吗？高德打车是出租车公司直接给你选择路线，就是大家都懂的，绕圈子路线，他不是按照最近路线给你选，滴滴打车是可以自己选路线的，我分享出来让不懂的姐妹打车出租车意避坑##出行 #出租车 #高德打车 #注意避坑#记录真实生活 | H38: 101 | I38: ='详细数据'!AC173 | J38: 330 | K38: 42 | L38: 73 | M38: 4 | N38: =SUM(J38:M38) | O38: ='详细数据'!J173 | P38: =O38/N38 | Q38: 无匹配类别 | R38: 无匹配类别 | T38: =IF(N38="","",IF(N38>=500000,"S 级",IF(N38>=100000,"A 级",IF(N38>=50000,"B 级","C 级"))))
A39: 46133 | B39: =A39+7 | C39: 投放完毕 | D39: 养森不能碰—第11年 | E39: https://www.douyin.com/video/7631151287887270757 | F39: 2026/4/22投放1000元 | G39: #记录我的生活 又回老家彭山了 | H39: 112 | I39: ='详细数据'!AC172 | J39: 685 | K39: 40 | L39: 60 | M39: 179 | N39: =SUM(J39:M39) | O39: ='详细数据'!J172 | P39: =O39/N39 | Q39: 场景 | R39: 跨城出行 | T39: =IF(N39="","",IF(N39>=500000,"S 级",IF(N39>=100000,"A 级",IF(N39>=50000,"B 级","C 级"))))
A40: 46133 | B40: =A40+7 | C40: 投放完毕 | D40: 清泉~漂荷 | E40: https://www.douyin.com/video/7631159721408326771 | F40: 2026/4/23投放1000元 | G40: 🚗这滴滴师傅也太会了吧！导航屏前插满鲜花💐瞬间治愈所有疲惫～生活美学不分职业！#车载小确幸 #美来自生活 | H40: 83 | I40: ='详细数据'!AC178 | J40: 1552 | K40: 63 | L40: 60 | M40: 10 | N40: =SUM(J40:M40) | O40: ='详细数据'!J178 | P40: =O40/N40 | Q40: 车内 | R40: 司机自发装置 | T40: =IF(N40="","",IF(N40>=500000,"S 级",IF(N40>=100000,"A 级",IF(N40>=50000,"B 级","C 级"))))
A41: 46133 | B41: =A41+7 | C41: 投放完毕 | D41: 夏天 | E41: https://www.douyin.com/video/7631062852215782976 | F41: 2026/4/23投放1000元 | G41: 打了个滴滴车回家路上看到一个老公公滑倒了，车都已经开过去了我跟司机说我要去帮他，司机也挺热心的，就立马路边停车跟着我一起过去了，下雨天太滑了他骑电动车滑倒了，脸朝地满脸都是血，一个人失魂落魄的趴在地上的几分钟，也不知道他在想什么，不知道是不是也会想年轻时候意气风发的模样，也不知道其他路过的人为啥都没有去帮助他，帮他叫了110和120，后来又帮忙把他扶起来了，后来警察来了我们也走了，不知道他是谁的老公，谁的爸爸，那一瞬间感觉有点心酸，人都是会老的，今天又做了一件好事，感觉很开心，想起前几年也救过一个中年人，发了抖音视频还小火了一下，相信做的好事都会有福报的，希望抖音也多宣传这种正能量#救人 #老人 | H41: 80 | I41: ='详细数据'!AC177 | J41: 2401 | K41: 53 | L41: 26 | M41: 11 | N41: =SUM(J41:M41) | O41: ='详细数据'!J177 | P41: =O41/N41 | Q41: 司机 | R41: 司乘温暖 | T41: =IF(N41="","",IF(N41>=500000,"S 级",IF(N41>=100000,"A 级",IF(N41>=50000,"B 级","C 级"))))
A42: 46134 | B42: =A42+7 | C42: 投放完毕 | D42: 妙童 | E42: https://www.douyin.com/video/7631406422018455730 | F42: 2026/4/23投放1000元 | G42: 西安滴滴上大分，车内卫生，司机形象，司机服务，司机素养真是给西安贴金！西装，白手套，矿泉水，卫生纸，给你挑最短的路线跑，很温暖！👍#西安 #西安滴滴 | H42: 505 | I42: ='详细数据'!AC176 | J42: 1072 | K42: 39 | L42: 726 | M42: 26 | N42: =SUM(J42:M42) | O42: ='详细数据'!J176 | P42: =O42/N42 | Q42: 产品力 | R42: 专车/豪华车 | T42: =IF(N42="","",IF(N42>=500000,"S 级",IF(N42>=100000,"A 级",IF(N42>=50000,"B 级","C 级"))))
A43: 46133 | B43: =A43+7 | C43: 在投 | D43: 篠濲裲 | E43: https://www.douyin.com/note/7631161091032347131 | F43: 2026/4/23投放1000元 | G43: 作为一个在南昌的外地人，经常刷到网上吐槽超雄司机，就让我来说说昨天晚上有幸打到的这位滴滴车司机师傅吧 | H43: 85 | I43: ='详细数据'!AC175 | J43: 1037 | K43: 29 | L43: 42 | M43: 11 | N43: =SUM(J43:M43) | O43: ='详细数据'!J175 | P43: =O43/N43 | Q43: 司机 | R43: 司机服务 | T43: =IF(N43="","",IF(N43>=500000,"S 级",IF(N43>=100000,"A 级",IF(N43>=50000,"B 级","C 级"))))
A44: 46135 | B44: =A44+7 | C44: 投放完毕 | D44: 垚外婆爱生活 | E44: https://www.douyin.com/video/7631754234015477361 | F44: 2026/4/24投放1000元 | G44: 谁懂啊！早晨打车送外孙上学偶遇到退役军人司机，安全感直接拉满。师傅对着孩子说：“以前叔叔保家卫国，现在保你平安到学校～”#滴滴司机#退役军人#暖心瞬间#打车奇遇 | H44: 99 | I44: ='详细数据'!AC180 | J44: 200 | K44: 10 | L44: 71 | M44: 0 | N44: =SUM(J44:M44) | O44: ='详细数据'!J180 | P44: =O44/N44 | Q44: 司机 | R44: 特殊身份-退伍军人 | T44: =IF(N44="","",IF(N44>=500000,"S 级",IF(N44>=100000,"A 级",IF(N44>=50000,"B 级","C 级"))))
A45: 46135 | B45: =A45+7 | C45: 无法投放 | D45: 请叫我女王大人🥕 | E45: https://www.douyin.com/video/7631803624960610230 | G45: 体验今天刚上线的滴滴公交#公共交通绿色出行 #滴滴公交 #电动车交通 | H45: 845
A46: 46135 | B46: =A46+7 | C46: 无法投放 | D46: 沉积岩✨ | E46: https://www.douyin.com/video/7631919828249700068 | G46: 打车碰到的特别有趣而且经历丰富的司机师傅我不行了。#车内搞笑对话 #滴滴司机 #吃货日常分享 | H46: 122
A47: 46138 | B47: =A47+7 | C47: 无法投放 | D47: 🌹ꦿꦼ҉陈蒙💞꯭࿚纪恋༊⁵²⁰ | E47: https://www.douyin.com/video/7632912964463542479 | G47: #滴滴，都说滴滴司机服务态度不好，车又臭臭的，看看这师傅，给司机师傅值得点赞、 | H47: 109
A48: 46138 | B48: =A48+7 | C48: 投放完毕 | D48: Celestial Canvas | E48: https://www.douyin.com/video/7632889897694619264 | F48: 2026/4/27投放1000元 | G48: 花2美元坐豪华电动车，被按摩座椅直接惊到，直呼中国滴滴太香！#老外看中国 #中国新能源汽车出行 #中国发展正能量 #美国人在中国真实体验 #英语听力 | H48: 672 | I48: ='详细数据'!AC186 | J48: 2681 | K48: 53 | L48: 50 | M48: 25 | N48: =SUM(J48:M48) | O48: ='详细数据'!J186 | P48: =O48/N48 | Q48: 产品力 | R48: 专车/豪华车 | T48: =IF(N48="","",IF(N48>=500000,"S 级",IF(N48>=100000,"A 级",IF(N48>=50000,"B 级","C 级"))))
A49: 46137 | B49: =A49+7 | C49: 投放完毕 | D49: 暴雨 | E49: https://www.douyin.com/note/7632617218002329514 | F49: 2026/4/27投放1000元2026/4/28投放509.78元 | G49: 对我们女司机就是这样细心，外面飘的柳絮要开窗通风，还贴心的弄上了车窗网。车里也没有异味，也不会开车抽烟啥的#滴滴司机 #女司机 #柳絮 | H49: 523 | I49: ='详细数据'!AC185+'详细数据'!AC187 | J49: 13000 | K49: 51 | L49: 62 | M49: 95 | N49: =SUM(J49:M49) | O49: ='详细数据'!J185+'详细数据'!J187 | P49: =O49/N49 | Q49: 司机 | R49: 女司机 | T49: =IF(N49="","",IF(N49>=500000,"S 级",IF(N49>=100000,"A 级",IF(N49>=50000,"B 级","C 级"))))
A50: 46137 | B50: =A50+7 | C50: 投放完毕 | D50: 🐳小🐬 | E50: https://www.douyin.com/video/7632511512201008505 | F50: 2026/4/27投放1000元 | G50: 都说东北人疼孩子，这下见识到了 打了个滴滴，是个东北司机，接单后先是帮我们放行李，说“早上挺冷的，抱着孩子赶紧上车”，然后在车上把导航放一边，特意给孩子打开动画片，又怕孩子听不见，还把声音放到最大，东北人疼孩子，具像化了👍🤣#上热门 #东北人疼孩子 #滴滴司机 | H50: 138 | I50: ='详细数据'!AC184 | J50: 812 | K50: 27 | L50: 25 | M50: 5 | N50: =SUM(J50:M50) | O50: ='详细数据'!J184 | P50: =O50/N50 | Q50: 司机 | R50: 司乘温暖 | T50: =IF(N50="","",IF(N50>=500000,"S 级",IF(N50>=100000,"A 级",IF(N50>=50000,"B 级","C 级"))))
A51: 46137 | B51: =A51+7 | C51: 投放完毕 | D51: 小夭 | E51: https://www.douyin.com/video/7632465056047360442 | F51: 2026/4/27投放1000元 | G51: 预约的6.35的车，早上6点就到了，师傅说他没事，就等着我，让我慢慢收拾，足足等了我快40分钟。滴滴师傅太不容易了，开着30多万的车接送乘客，勤劳工作，兢兢业业，在此也祝愿所有辛苦坚持工作，肩负家庭重担的平凡的我们，平安，幸福！#滴滴司机 #辛勤劳动者 | H51: 151 | I51: ='详细数据'!AC183 | J51: 1279 | K51: 58 | L51: 53 | M51: 2 | N51: =SUM(J51:M51) | O51: ='详细数据'!J183 | P51: =O51/N51 | Q51: 司机 | R51: 司机服务 | T51: =IF(N51="","",IF(N51>=500000,"S 级",IF(N51>=100000,"A 级",IF(N51>=50000,"B 级","C 级"))))
A52: 46135 | B52: =A52+7 | C52: 投放完毕 | D52: CS第一深情798 | E52: https://www.douyin.com/video/7631938177683662579 | F52: 2026/4/27投放1000元 | G52: #常熟网约公共 特地去试乘了一下。蛮不错！！！ | H52: 117 | I52: ='详细数据'!AC182 | J52: 644 | K52: 50 | L52: 22 | M52: 123 | N52: =SUM(J52:M52) | O52: ='详细数据'!J182 | P52: =O52/N52 | Q52: 产品力 | R52: 网约公交 | T52: =IF(N52="","",IF(N52>=500000,"S 级",IF(N52>=100000,"A 级",IF(N52>=50000,"B 级","C 级"))))
A53: 46135 | B53: =A53+7 | C53: 投放完毕 | D53: 狼道大狮 | E53: https://www.douyin.com/video/7631754660667995892 | F53: 2026/4/27投放1000元 | G53: 打卡春天里的第一趟网约公交车！#网约公交车 #常熟公交 #常熟 | H53: 2594 | I53: ='详细数据'!AC181 | J53: 2420 | K53: 92 | L53: 346 | M53: 1201 | N53: =SUM(J53:M53) | O53: ='详细数据'!J181 | P53: =O53/N53 | Q53: 产品力 | R53: 网约公交 | T53: =IF(N53="","",IF(N53>=500000,"S 级",IF(N53>=100000,"A 级",IF(N53>=50000,"B 级","C 级"))))
A54: 46139 | B54: =A54+7 | C54: 投放完毕 | D54: 悦己 | E54: https://www.douyin.com/video/7633260661108049226 | F54: 2026/4/28投放108.64元 | G54: 原本28-29号的行程，今早翻看通知发现是今天中午就要到场。距离发车仅剩一小时，脑子里瞬间理清所需物品，几分钟快速收拾完毕，从容叫车出发。 | H54: 75 | I54: ='详细数据'!AC188 | J54: 402 | K54: 11 | L54: 16 | M54: 0 | N54: =SUM(J54:M54) | O54: ='详细数据'!J188 | P54: =O54/N54 | Q54: 场景 | R54: 通勤上下班 | T54: =IF(N54="","",IF(N54>=500000,"S 级",IF(N54>=100000,"A 级",IF(N54>=50000,"B 级","C 级"))))
A55: 46140 | B55: =A55+7 | C55: 投放完毕 | D55: 娇娇与@导盲犬二锦锦的日 | E55: https://www.douyin.com/video/7633750886359587048 | F55: 2026/4/29投放115.64元 | G55: 烟台滴滴出行师傅和芝罘湾码头工作人员太好了，鼓励看不见的我们 #多出来走走 #感谢工作人员你们辛苦了 | H55: 810 | I55: ='详细数据'!AC192 | J55: 2258 | K55: 64 | L55: 667 | M55: 118 | N55: =SUM(J55:M55) | O55: ='详细数据'!J192 | P55: =O55/N55 | Q55: 司机 | R55: 司机服务 | T55: =IF(N55="","",IF(N55>=500000,"S 级",IF(N55>=100000,"A 级",IF(N55>=50000,"B 级","C 级"))))
A56: 46140 | B56: =A56+7 | C56: 投放完毕 | D56: 梦姐 | E56: https://www.douyin.com/video/7633786629181727609 | F56: 2026/4/29投放112.4元 | G56: 今天坐出租车想唱歌，问师傅能否拍个抖音记录美好生活，师傅 #出租车司机 #即兴唱歌 #随拍 | H56: 1251 | I56: ='详细数据'!AC191 | J56: 3228 | K56: 231 | L56: 175 | M56: 38 | N56: =SUM(J56:M56) | O56: ='详细数据'!J191 | P56: =O56/N56 | Q56: 无匹配类别 | R56: 无匹配类别 | T56: =IF(N56="","",IF(N56>=500000,"S 级",IF(N56>=100000,"A 级",IF(N56>=50000,"B 级","C 级"))))
A57: 46138 | B57: =A57+7 | C57: 投放完毕 | D57: 海韵 | E57: https://www.douyin.com/video/7633007885915943606 | F57: 2026/4/29投放117.24元 | G57: 这歌的小调调带勾勾儿，滴滴小哥儿的车摆件也挺搭！～ | H57: 81 | I57: ='详细数据'!AC190 | J57: 326 | K57: 13 | L57: 76 | M57: 0 | N57: =SUM(J57:M57) | O57: ='详细数据'!J190 | P57: =O57/N57 | Q57: 车内 | R57: 司机自发装置 | T57: =IF(N57="","",IF(N57>=500000,"S 级",IF(N57>=100000,"A 级",IF(N57>=50000,"B 级","C 级"))))
A58: 46138 | B58: =A58+7 | C58: 投放完毕 | D58: 林强 | E58: https://www.douyin.com/video/7632969984486313061 | F58: 2026/4/29投放116.67元 | G58: 滴滴网约车这哥们的车贴很有味道，直击人心，引人共鸣。所有的一切都瞬间被治愈了哈哈 | H58: 71 | I58: ='详细数据'!AC189 | J58: 361 | K58: 13 | L58: 17 | M58: 0 | N58: =SUM(J58:M58) | O58: ='详细数据'!J189 | P58: =O58/N58 | Q58: 车内 | R58: 司机自发装置 | T58: =IF(N58="","",IF(N58>=500000,"S 级",IF(N58>=100000,"A 级",IF(N58>=50000,"B 级","C 级"))))
A59: 46141 | B59: =A59+7 | C59: 投放完毕 | D59: 范思哲 | E59: https://www.douyin.com/note/7634085219296901353 | F59: 2026/4/30投放1000元 | G59: 劫后余生。4.28 小记昨天在这大山里发烧38.5，附近还没有车 | H59: 125 | I59: ='详细数据'!AC197 | J59: 2878 | K59: 48 | L59: 11 | M59: 32 | N59: =SUM(J59:M59) | O59: ='详细数据'!J197 | P59: =O59/N59 | Q59: 场景 | R59: 医院/就医 | T59: =IF(N59="","",IF(N59>=500000,"S 级",IF(N59>=100000,"A 级",IF(N59>=50000,"B 级","C 级"))))
A60: 46141 | B60: =A60+7 | C60: 投放完毕 | D60: 小珍珠AH | E60: https://www.douyin.com/video/7634061256496521851 | F60: 2026/4/30投放1000元 | G60: 第一视角带大家乘坐蚌埠市区到滕湖机场的大巴#机场最新消息 #蚌埠 #蚌埠机场 #滕湖机场 #滕湖 | H60: 1523 | I60: ='详细数据'!AC196 | J60: 2155 | K60: 201 | L60: 94 | M60: 1111 | N60: =SUM(J60:M60) | O60: ='详细数据'!J196 | P60: =O60/N60 | Q60: 场景 | R60: 机场/高铁接送 | T60: =IF(N60="","",IF(N60>=500000,"S 级",IF(N60>=100000,"A 级",IF(N60>=50000,"B 级","C 级"))))
A61: 46141 | B61: =A61+7 | C61: 投放完毕 | D61: 芋泥啵啵 | E61: https://www.douyin.com/note/7634169978048694630 | F61: 2026/4/30投放1000元 | G61: 我出门喜欢打专车的原因：专车司机穿戴整洁，文明礼貌，车里干干净净，没有异味 | H61: 198 | I61: ='详细数据'!AC195 | J61: 12000 | K61: 184 | L61: 309 | M61: 425 | N61: =SUM(J61:M61) | O61: ='详细数据'!J195 | P61: =O61/N61 | Q61: 产品力 | R61: 专车/豪华车 | T61: =IF(N61="","",IF(N61>=500000,"S 级",IF(N61>=100000,"A 级",IF(N61>=50000,"B 级","C 级"))))
A62: 46141 | B62: =A62+7 | C62: 投放完毕 | D62: 多肉小城日记 | E62: https://www.douyin.com/video/7633992971189784147 | F62: 2026/4/30投放1000元 | G62: 如果你在马鞍山打到这辆车，记得拿小礼物哟#滴滴打车 #滴滴司机 #网约车 #马鞍山 #宁马城际 | H62: 79 | I62: ='详细数据'!AC193 | J62: 1132 | K62: 44 | L62: 31 | M62: 41 | N62: =SUM(J62:M62) | O62: ='详细数据'!J193 | P62: =O62/N62 | Q62: 车内 | R62: 司机自发装置 | T62: =IF(N62="","",IF(N62>=500000,"S 级",IF(N62>=100000,"A 级",IF(N62>=50000,"B 级","C 级"))))
A63: 46141 | B63: =A63+7 | C63: 投放完毕 | D63: 阿喆爱生活 | E63: https://www.douyin.com/video/7634026065808580795 | F63: 2026/4/30投放1000元 | G63: 这个滴滴司机服务可以#滴滴 | H63: 75 | I63: ='详细数据'!AC194 | J63: 1978 | K63: 41 | L63: 58 | M63: 3 | N63: =SUM(J63:M63) | O63: ='详细数据'!J194 | P63: =O63/N63 | Q63: 司机 | R63: 司机服务 | T63: =IF(N63="","",IF(N63>=500000,"S 级",IF(N63>=100000,"A 级",IF(N63>=50000,"B 级","C 级"))))

Sheet 5月加热汇总
A1: 发布日期 | B1: 投放截止日期 | C1: 状态 | D1: 达人名称 | E1: 链接 | F1: 投放记录 xx日投放xx元 | G1: 标题 | H1: 投前互动量 | I1: 投放互动量 | J1: 投放后点赞量 | K1: 投放后收藏量 | L1: 投放后评论量 | M1: 投放后转发量 | N1: 总互动量 | O1: 总投放金额 | P1: 综合cpe *投入/笔记外层互动数据 | Q1: 一级分类 | R1: 二级分类 | S1: 备注 | T1: 爆款定级
A2: 汇总 | H2: - | I2: - | N2: =SUM(N3:N70) | O2: =SUM(O3:O70) | P2: =O2/N2
A3: 46147 | B3: =A3+7 | C3: 投放完毕 | D3: 吴安芝 | E3: https://www.douyin.com/note/7636204932429437370 | F3: 2026/5/6投放1000元2026/5/7投放5000元 | G3: 我评论了@浮生 的作品：想起我之前夏天和朋友打车，朋友用的某地图打的一口价的车，司机就说，一口价的车没有空调服务司机还振振有词。我在某滴上打车，特惠也好特价也好，都有空调 | H3: 76 | I3: ='详细数据'!AC204+'详细数据'!AC206 | J3: 30000 | K3: 2718 | L3: 983 | M3: 379 | N3: =SUM(J3:M3) | O3: ='详细数据'!J204+'详细数据'!J206 | P3: =O3/N3 | Q3: 无匹配类别 | R3: 无匹配类别 | T3: =IF(N3="","",IF(N3>=500000,"S 级",IF(N3>=100000,"A 级",IF(N3>=50000,"B 级","C 级"))))
A4: 46146 | B4: =A4+7 | C4: 投放完毕 | D4: 秋恋雪 | E4: https://www.douyin.com/video/7636020034524274043 | F4: 2026/5/6投放1000元 | G4: 吹着长安街的晚风，邂逅天安门的夜色。遇到超暖心的滴滴师傅，细心放缓车速，成全每一份想定格盛世风景的心意。平凡人，最动人的温柔。#吃喝玩乐分享计划 #天安门 #北京夜景 #视觉冲击旅行 #视觉盛宴城市记忆 | H4: 131 | I4: ='详细数据'!AC203 | J4: 2440 | K4: 47 | L4: 225 | M4: 4 | N4: =SUM(J4:M4) | O4: ='详细数据'!J203 | P4: =O4/N4 | Q4: 产品力 | R4: 价格优惠 | T4: =IF(N4="","",IF(N4>=500000,"S 级",IF(N4>=100000,"A 级",IF(N4>=50000,"B 级","C 级"))))
A5: 46146 | B5: =A5+7 | C5: 投放完毕 | D5: 马超Aster | E5: https://www.douyin.com/video/7636040612411755802 | F5: 2026/5/6投放1000元2026/5/7投放5000元2026/5/8投放5000元 | G5: 负债百万的滴滴司机告诉我，要好好爱自己 #滴滴司机 #爱情 #爱自己 #生活 #陌生人的温暖 | H5: 16600 | I5: ='详细数据'!AC202+'详细数据'!AC205+'详细数据'!AC209 | J5: 96000 | K5: 23000 | L5: 3860 | M5: 20000 | N5: =SUM(J5:M5) | O5: ='详细数据'!J202+'详细数据'!J205+'详细数据'!J209 | P5: =O5/N5 | Q5: 司机 | R5: 司乘温暖 | T5: =IF(N5="","",IF(N5>=500000,"S 级",IF(N5>=100000,"A 级",IF(N5>=50000,"B 级","C 级"))))
A6: 46145 | B6: =A6+7 | C6: 投放完毕 | D6: 寻找薇薇安·迈尔🎈 | E6: https://www.douyin.com/note/7635545727879850313 | F6: 2026/5/6投放1000元 | G6: 滴滴的后座上，藏着一个被羽绒服裹得严严实实的小朋友。 | H6: 86 | I6: ='详细数据'!AC201 | J6: 949 | K6: 11 | L6: 19 | M6: 14 | N6: =SUM(J6:M6) | O6: ='详细数据'!J201 | P6: =O6/N6 | Q6: 司机 | R6: 司乘互动 | T6: =IF(N6="","",IF(N6>=500000,"S 级",IF(N6>=100000,"A 级",IF(N6>=50000,"B 级","C 级"))))
A7: 46146 | B7: =A7+7 | C7: 投放完毕 | D7: 爱吃鱼的猫猫 | E7: https://www.douyin.com/note/7635922915368283775 | F7: 2026/5/6投放1000元 | G7: 常熟市区新推出的滴滴公交，体验了一把。3元/人，随叫随到。#常熟#公交出行绿色低碳 #公交乘车体验 #公共交通 | H7: 16 | I7: ='详细数据'!AC200 | J7: 747 | K7: 31 | L7: 41 | M7: 10 | N7: =SUM(J7:M7) | O7: ='详细数据'!J200 | P7: =O7/N7 | Q7: 场景 | R7: 家庭出行/带娃 | T7: =IF(N7="","",IF(N7>=500000,"S 级",IF(N7>=100000,"A 级",IF(N7>=50000,"B 级","C 级"))))
A8: 46145 | B8: =A8+7 | C8: 投放完毕 | D8: Daniel_花木吴彦祖 | E8: https://www.douyin.com/video/7635684064943428729 | F8: 2026/5/6投放1000元 | G8: #公共交通 #巴士 人多出行的正确打开方式哦 | H8: 12 | I8: ='详细数据'!AC199 | J8: 1152 | K8: 36 | L8: 138 | M8: 13 | N8: =SUM(J8:M8) | O8: ='详细数据'!J199 | P8: =O8/N8 | Q8: 产品力 | R8: 网约公交 | T8: =IF(N8="","",IF(N8>=500000,"S 级",IF(N8>=100000,"A 级",IF(N8>=50000,"B 级","C 级"))))
A9: 46148 | B9: =A9+7 | C9: 无法投放 | D9: 古城金街艾美女鞋馆主理人（夏款 | E9: https://www.douyin.com/video/7636439919821352357 | F9: 2026/5/6投放1000元 | G9: 今天因为我一个错误的决定，让我的宝贝儿子受累了，五一小长假结束，今天儿子返校去南昌坐高铁，本来他打算下午去名优特汽车站坐客车去南昌，然后我说帮他叫江南出行的车子，这种车子坐着舒服一些 | H9: 138 | Q9: 产品力 | R9: 站点巴士
A10: 46146 | B10: =A10+7 | C10: 投放完毕 | D10: 常熟热心姚阿姨 | E10: https://www.douyin.com/video/7636034872154967707 | F10: 2026/5/6投放1000元 | G10: 滴滴小公交小可爱送我回家啦 | H10: 7 | I10: ='详细数据'!AC198 | J10: 423 | K10: 13 | L10: 8 | M10: 9 | N10: =SUM(J10:M10) | O10: ='详细数据'!J198 | P10: =O10/N10 | Q10: 场景 | R10: 跨城出行 | T10: =IF(N10="","",IF(N10>=500000,"S 级",IF(N10>=100000,"A 级",IF(N10>=50000,"B 级","C 级"))))
A11: 46149 | B11: =A11+7 | C11: 投放完毕 | D11: 萬家幺女万和香 | E11: https://www.douyin.com/video/7636826521273382309 | F11: 2026/5/7投放1000元 | G11: 今天坐滴滴车，师傅问我在哪里下单？我说在微信里面，他说怎么坐车的全部都是美女坐我的车？我说那你走桃花运了，他说美女，你气质太好，我说你也长得很帅，到底是他犯花痴，还是我犯花痴？都夸对方长得帅，其实夸对方帅也是一种礼貌 | H11: 108 | I11: ='详细数据'!AC208 | J11: 259 | K11: 11 | L11: 12 | M11: 17 | N11: =SUM(J11:M11) | O11: ='详细数据'!J208 | P11: =O11/N11 | Q11: 产品力 | R11: 滴滴小巴 | T11: =IF(N11="","",IF(N11>=500000,"S 级",IF(N11>=100000,"A 级",IF(N11>=50000,"B 级","C 级"))))
A12: 46149 | B12: =A12+7 | C12: 投放完毕 | D12: 克莱因蓝 | E12: https://www.douyin.com/video/7637044455720278251 | F12: 2026/5/7投放1000元 | G12: 现在滴滴瞬间都这么有品吗！#打车#出租车司机 | H12: 2 | I12: ='详细数据'!AC207 | J12: 768 | K12: 65 | L12: 10 | M12: 17 | N12: =SUM(J12:M12) | O12: ='详细数据'!J207 | P12: =O12/N12 | Q12: 司机 | R12: 司乘互动 | T12: =IF(N12="","",IF(N12>=500000,"S 级",IF(N12>=100000,"A 级",IF(N12>=50000,"B 级","C 级"))))
A13: 46148 | B13: =A13+7 | C13: 投放完毕 | D13: 吉玺 | E13: https://www.douyin.com/video/7636643841961216127 | F13: 2026/5/8投放1000元 | G13: 家长是孩子的首任老师。现在只要有人对我们释放善意，孩子都会有感恩之心。比如昨天的滴滴司机，态度友善，还一路畅聊临下车我习惯性说了一声：“谢谢”！师傅立马说：期待下次还接你的订单，慢走！孩儿在旁边说：妈妈，给师傅一个好评吧，好评多了他的订单会多。 | H13: 72 | I13: ='详细数据'!AC210 | J13: 778 | K13: 28 | L13: 31 | M13: 5 | N13: =SUM(J13:M13) | O13: ='详细数据'!J210 | P13: =O13/N13 | Q13: 车内 | R13: 司机自发装置 | T13: =IF(N13="","",IF(N13>=500000,"S 级",IF(N13>=100000,"A 级",IF(N13>=50000,"B 级","C 级"))))
A14: 46150 | B14: =A14+7 | C14: 投放完毕 | D14: 弦外故事 | E14: https://www.douyin.com/video/7637394139268615462 | F14: 2026/5/9投放1000元 | G14: 刷爆朋友圈！谁能猜到网约车后座是歌神陈奕迅打车偶遇歌迷沉浸式听歌Eason忍不住开口跟唱恶搞司机网友：滴滴现在还缺人么？ #陈奕迅 #唱歌 #明星 #删了她 | H14: 98 | I14: ='详细数据'!AC211 | J14: 468 | K14: 27 | L14: 28 | M14: 34 | N14: =SUM(J14:M14) | O14: ='详细数据'!J211 | P14: =O14/N14 | Q14: 司机 | R14: 司机服务 | T14: =IF(N14="","",IF(N14>=500000,"S 级",IF(N14>=100000,"A 级",IF(N14>=50000,"B 级","C 级"))))
A15: 46151 | B15: =A15+7 | C15: 无法投放 | D15: 豫S✨老梅👵🌟💫 | E15: https://www.douyin.com/video/7637703323614063275 | G15: 滴滴出行 喜欢打女司机的车 | H15: 119 | Q15: 司机 | R15: 司乘互动
A16: 46152 | B16: =A16+7 | C16: 投放完毕 | D16: 漫寻星📸. | E16: https://www.douyin.com/video/7637869144147080817 | F16: 2026/5/11投放1000元 | G16: 常熟这个不起眼的小城市，却有着网约公交😍不仅覆盖了部分公交线网空白，还方便了市民出行，别看车小，却总能跑出最快的时速，试运营期间，只需3元/人次，就能开启这段美妙旅程，非常有性价比🤓#公交车 #公交迷 #公共交通 #城市公交 #网约公交 | H16: 88 | I16: ='详细数据'!AC212 | J16: 2765 | K16: 57 | L16: 17 | M16: 52 | N16: =SUM(J16:M16) | O16: ='详细数据'!J212 | P16: =O16/N16 | Q16: 司机 | R16: 女司机 | T16: =IF(N16="","",IF(N16>=500000,"S 级",IF(N16>=100000,"A 级",IF(N16>=50000,"B 级","C 级"))))
A17: 46154 | B17: =A17+7 | C17: 无法投放 | D17: 蘅若 | E17: https://www.douyin.com/note/7638835615421411577 | G17: 是不是南方的滴滴司机都帮忙拿行李呀，莫名的感觉很好 | H17: 130 | Q17: 产品力 | R17: 网约公交
A18: 46153 | B18: =A18+7 | C18: 投放完毕 | D18: 徐伟华 | E18: https://www.douyin.com/note/7638470477203931643 | F18: 2026/5/13投放1000元 | G18: 出发啦！今天滴滴车司机是我的老乡，车内非常整洁！给他点赞！ | H18: 73 | I18: ='详细数据'!AC213 | J18: 102 | K18: 5 | L18: 10 | M18: 5 | N18: =SUM(J18:M18) | O18: ='详细数据'!J213 | P18: =O18/N18 | Q18: 司机 | R18: 司机服务 | T18: =IF(N18="","",IF(N18>=500000,"S 级",IF(N18>=100000,"A 级",IF(N18>=50000,"B 级","C 级"))))
A19: 46155 | B19: =A19+7 | C19: 投放完毕 | D19: 宋疯恩🐌🦋 | E19: https://www.douyin.com/note/7639298762268064241 | F19: 2026/5/15投放1000元 | G19: 我只敢在这个车里全程专心看手机 并且心里不会对路况感到担惊害怕#滴滴专车 | H19: 142 | I19: ='详细数据'!AC221 | J19: 1061 | K19: 14 | L19: 148 | M19: 10 | N19: =SUM(J19:M19) | O19: ='详细数据'!J221 | P19: =O19/N19 | Q19: 车内 | R19: 车内整洁 | T19: =IF(N19="","",IF(N19>=500000,"S 级",IF(N19>=100000,"A 级",IF(N19>=50000,"B 级","C 级"))))
A20: 46155 | B20: =A20+7 | C20: 投放完毕 | D20: 小六liu | E20: https://www.douyin.com/note/7639360447649575034 | F20: 2026/5/15投放1000元 | G20: 我将拥护滴滴打车#如何选择真正的靠谱平台 #女性安全 #滴滴出行 | H20: 248 | I20: ='详细数据'!AC220 | J20: 931 | K20: 22 | L20: 348 | M20: 77 | N20: =SUM(J20:M20) | O20: ='详细数据'!J220 | P20: =O20/N20 | Q20: 产品力 | R20: 专车/豪华车 | T20: =IF(N20="","",IF(N20>=500000,"S 级",IF(N20>=100000,"A 级",IF(N20>=50000,"B 级","C 级"))))
A21: 46156 | B21: =A21+7 | C21: 投放完毕 | D21: 美美姐🇨🇳🇭🇰 | E21: https://www.douyin.com/note/7639587991471701105 | F21: 2026/5/15投放1000元 | G21: 5月12晚上我们在聚会回家叫的滴滴下车时把手机忘在了车上，回到家后大概半二十分钟左右发现手机不在， | H21: 88 | I21: ='详细数据'!AC219 | J21: 291 | K21: 6 | L21: 7 | M21: 7 | N21: =SUM(J21:M21) | O21: ='详细数据'!J219 | P21: =O21/N21 | Q21: 产品力 | R21: 女性友好计划 | T21: =IF(N21="","",IF(N21>=500000,"S 级",IF(N21>=100000,"A 级",IF(N21>=50000,"B 级","C 级"))))
A22: 46154 | B22: =A22+7 | C22: 投放完毕 | D22: 骑境•路飞 | E22: https://www.douyin.com/note/7638908016368917681 | F22: 2026/5/15投放1000元 | G22: 外胎爆了怎么办？ #扎胎了怎么办 #货拉拉 | H22: 74 | I22: ='详细数据'!AC215 | J22: 880 | K22: 19 | L22: 42 | M22: 3 | N22: =SUM(J22:M22) | O22: ='详细数据'!J215 | P22: =O22/N22 | Q22: 司机 | R22: 失物返还 | T22: =IF(N22="","",IF(N22>=500000,"S 级",IF(N22>=100000,"A 级",IF(N22>=50000,"B 级","C 级"))))
A23: 46156 | B23: =A23+7 | C23: 投放完毕 | D23: 婷宝儿💖 | E23: https://www.douyin.com/video/7639539369804821434 | F23: 2026/5/15投放1000元 | G23: 平时上班打了这么多滴滴，第一次遇到这么干净又帅气的司机！坐起心情都要舒畅些 | H23: 149 | I23: ='详细数据'!AC218 | J23: 342 | K23: 31 | L23: 19 | M23: 16 | N23: =SUM(J23:M23) | O23: ='详细数据'!J218 | P23: =O23/N23 | Q23: 无匹配类别 | R23: 无匹配类别 | T23: =IF(N23="","",IF(N23>=500000,"S 级",IF(N23>=100000,"A 级",IF(N23>=50000,"B 级","C 级"))))
A24: 46156 | B24: =A24+7 | C24: 投放完毕 | D24: 幕兮彤 | E24: https://www.douyin.com/note/7639700717046112383 | F24: 2026/5/15投放1000元 | G24: 好可爱#拼车趣事 #滴滴司机 | H24: 87 | I24: ='详细数据'!AC217 | J24: 421 | K24: 4 | L24: 7 | M24: 12 | N24: =SUM(J24:M24) | O24: ='详细数据'!J217 | P24: =O24/N24 | Q24: 司机 | R24: 司机服务 | T24: =IF(N24="","",IF(N24>=500000,"S 级",IF(N24>=100000,"A 级",IF(N24>=50000,"B 级","C 级"))))
A25: 46156 | B25: =A25+7 | C25: 投放完毕 | D25: 不吃韭菜~ | E25: https://www.douyin.com/note/7639772595369289381 | F25: 2026/5/15投放1000元 | G25: 第一次打到聋哑司机的车 | H25: 188 | I25: ='详细数据'!AC216 | J25: 3951 | K25: 56 | L25: 69 | M25: 38 | N25: =SUM(J25:M25) | O25: ='详细数据'!J216 | P25: =O25/N25 | Q25: 产品力 | R25: 拼车 | T25: =IF(N25="","",IF(N25>=500000,"S 级",IF(N25>=100000,"A 级",IF(N25>=50000,"B 级","C 级"))))
A26: 46157 | B26: =A26+7 | C26: 投放完毕 | D26: 艾米 | E26: https://www.douyin.com/note/7640081270203342562 | F26: 2026/5/18投放1000元 | G26: 咱也赶个时髦，头一次搭滴滴，还是个美女 | H26: 111 | I26: ='详细数据'!AC226 | J26: 669 | K26: 28 | L26: 41 | M26: 26 | N26: =SUM(J26:M26) | O26: ='详细数据'!J226 | P26: =O26/N26 | Q26: 司机 | R26: 特殊身份-听障司机 | T26: =IF(N26="","",IF(N26>=500000,"S 级",IF(N26>=100000,"A 级",IF(N26>=50000,"B 级","C 级"))))
A27: 46158 | B27: =A27+7 | C27: 投放完毕 | D27: 逢时春迟月 | E27: https://www.douyin.com/note/7640285558464104890 | F27: 2026/5/18投放1000元2026/5/19投放5000元 | G27: #特斯拉 上班打车打到特斯拉车主，开始以为我眼花了，我上车之后问叔叔，你 | H27: 3430 | I27: ='详细数据'!AC225+'详细数据'!AC227 | J27: 18000 | K27: 264 | L27: 3065 | M27: 1114 | N27: =SUM(J27:M27) | O27: ='详细数据'!J225+'详细数据'!J227 | P27: =O27/N27 | Q27: 司机 | R27: 女司机 | T27: =IF(N27="","",IF(N27>=500000,"S 级",IF(N27>=100000,"A 级",IF(N27>=50000,"B 级","C 级"))))
A28: 46157 | B28: =A28+7 | C28: 投放完毕 | D28: 小贝勒爷 | E28: https://www.douyin.com/note/7640097613844477669 | F28: 2026/5/18投放1000元 | G28: 敬礼～安全感爆棚。打到中共党员师傅的车🚗安 | H28: 742 | I28: ='详细数据'!AC224 | J28: 1075 | K28: 45 | L28: 176 | M28: 258 | N28: =SUM(J28:M28) | O28: ='详细数据'!J224 | P28: =O28/N28 | Q28: 车内 | R28: 特殊车型/车衣 | T28: =IF(N28="","",IF(N28>=500000,"S 级",IF(N28>=100000,"A 级",IF(N28>=50000,"B 级","C 级"))))
A29: 46159 | B29: =A29+7 | C29: 投放完毕 | D29: FM101.6小仙 | E29: https://www.douyin.com/video/7640775971604485993 | F29: 2026/5/18投放1000元 | G29: 和奶奶出门叫了个滴滴、师傅很热情，长得也挺帅，一路上聊的也挺嗨，结果奶奶拉着脸开始教育我，说我不要忘了自己结婚了，有老公还这样，说我不考虑孩子 | H29: 481 | I29: ='详细数据'!AC223 | J29: 1357 | K29: 30 | L29: 59 | M29: 491 | N29: =SUM(J29:M29) | O29: ='详细数据'!J223 | P29: =O29/N29 | Q29: 司机 | R29: 司机服务 | T29: =IF(N29="","",IF(N29>=500000,"S 级",IF(N29>=100000,"A 级",IF(N29>=50000,"B 级","C 级"))))
A30: 46159 | B30: =A30+7 | C30: 投放完毕 | D30: 十亿少男的梦94 | E30: https://www.douyin.com/video/7640834357934858225 | F30: 2026/5/18投放1000元 | G30: 宝宝巴士🚌 #新能源城市公交 #网约公交车谁懂啊！坐网约公交🚍有种坐宝宝巴士的快乐🎉 | H30: 48 | I30: ='详细数据'!AC222 | J30: 1045 | K30: 51 | L30: 47 | M30: 61 | N30: =SUM(J30:M30) | O30: ='详细数据'!J222 | P30: =O30/N30 | Q30: 场景 | R30: 带长辈出行 | T30: =IF(N30="","",IF(N30>=500000,"S 级",IF(N30>=100000,"A 级",IF(N30>=50000,"B 级","C 级"))))
A31: 46160 | B31: =A31+7 | C31: 投放完毕 | D31: 沧桑大叔 | E31: https://www.douyin.com/video/7641120212301335651 | F31: 2026/5/19投放1000元 | G31: 【鲁BA29065】人啊一生能遇多少善良的人？感谢临沂好大哥滴滴出行夜班司机冒雨上百里地从胶州给我送回失物！！！#感谢好人一生平安 #两个龙虾🦞店为丁大哥终身免费吃#青岛好司机鲁BA29065 | H31: 198 | I31: ='详细数据'!AC232 | J31: 1330 | K31: 33 | L31: 80 | M31: 6 | N31: =SUM(J31:M31) | O31: ='详细数据'!J232 | P31: =O31/N31 | Q31: 产品力 | R31: 网约公交 | T31: =IF(N31="","",IF(N31>=500000,"S 级",IF(N31>=100000,"A 级",IF(N31>=50000,"B 级","C 级"))))
A32: 46160 | B32: =A32+7 | C32: 投放完毕 | D32: 吃完芒果早点睡觉 | E32: https://www.douyin.com/note/7640942718125977999 | F32: 2026/5/19投放1000元 | G32: “人们常以缘分深厚作为亲近的借口，而以无缘，作为了却情谊的假辞而已，或许有一天真到了无路可去无法可解的地步， | H32: 95 | I32: ='详细数据'!AC231 | J32: 1662 | K32: 29 | L32: 100 | M32: 38 | N32: =SUM(J32:M32) | O32: ='详细数据'!J231 | P32: =O32/N32 | Q32: 司机 | R32: 失物返还 | T32: =IF(N32="","",IF(N32>=500000,"S 级",IF(N32>=100000,"A 级",IF(N32>=50000,"B 级","C 级"))))
A33: 46160 | B33: =A33+7 | C33: 投放完毕 | D33: 丹哥🌈 | E33: https://www.douyin.com/video/7640897437604151503 | F33: 2026/5/19投放1000元 | G33: 久了没打车，滴滴都是宝马#滴滴出行 | H33: 77 | I33: ='详细数据'!AC230 | J33: 143 | K33: 4 | L33: 65 | M33: 7 | N33: =SUM(J33:M33) | O33: ='详细数据'!J230 | P33: =O33/N33 | Q33: 无匹配类别 | R33: 无匹配类别 | T33: =IF(N33="","",IF(N33>=500000,"S 级",IF(N33>=100000,"A 级",IF(N33>=50000,"B 级","C 级"))))
A34: 46159 | B34: =A34+7 | C34: 投放完毕 | D34: 晓雅姐 | E34: https://www.douyin.com/note/7640813564869112942 | F34: 2026/5/19投放1000元 | G34: 遇到好的司机真的是一种幸运，说话语气温和给人一种温暖，穿戴整齐干净 | H34: 198 | I34: ='详细数据'!AC229 | J34: 1331 | K34: 29 | L34: 68 | M34: 12 | N34: =SUM(J34:M34) | O34: ='详细数据'!J229 | P34: =O34/N34 | Q34: 车内 | R34: 特殊车型/车衣 | T34: =IF(N34="","",IF(N34>=500000,"S 级",IF(N34>=100000,"A 级",IF(N34>=50000,"B 级","C 级"))))
A35: 46160 | B35: =A35+7 | C35: 投放完毕 | D35: 物是人非yaa(没回复就 | E35: https://www.douyin.com/note/7641163045289481322 | F35: 2026/5/19投放1000元 | G35: #北川地震遗址2026年5月18日，绵阳安州区，天气暖和也不闷热。打了一辆滴滴 | H35: 88 | I35: ='详细数据'!AC228 | J35: 1591 | K35: 47 | L35: 43 | M35: 19 | N35: =SUM(J35:M35) | O35: ='详细数据'!J228 | P35: =O35/N35 | Q35: 司机 | R35: 司机服务 | T35: =IF(N35="","",IF(N35>=500000,"S 级",IF(N35>=100000,"A 级",IF(N35>=50000,"B 级","C 级"))))
A36: 46162 | B36: =A36+7 | C36: 投放完毕 | D36: 晓雅姐 | E36: https://www.douyin.com/note/7641875385806374833 | F36: 2026/5/22投放1000元 | G36: #专车接送 #出行 普通的520的下午，普通的小雅女士穿了很喜欢的牛仔鱼尾裙，化了个淡妆 | H36: 84 | I36: ='详细数据'!AC239 | J36: 191 | K36: 10 | L36: 16 | M36: 4 | N36: =SUM(J36:M36) | O36: ='详细数据'!J239 | P36: =O36/N36 | Q36: 场景 | R36: 旅游出行 | T36: =IF(N36="","",IF(N36>=500000,"S 级",IF(N36>=100000,"A 级",IF(N36>=50000,"B 级","C 级"))))
A37: 46162 | B37: =A37+7 | C37: 投放完毕 | D37: 安安💓 | E37: https://www.douyin.com/video/7641882679970377957 | F37: 2026/5/22投放1000元 | G37: 今天回一趟汕尾，坐滴滴车都感觉滴滴很高档，这辈子没有坐过，，， | H37: 75 | I37: ='详细数据'!AC238 | J37: 421 | K37: 5 | L37: 21 | M37: 1 | N37: =SUM(J37:M37) | O37: ='详细数据'!J238 | P37: =O37/N37 | Q37: 产品力 | R37: 专车/豪华车 | T37: =IF(N37="","",IF(N37>=500000,"S 级",IF(N37>=100000,"A 级",IF(N37>=50000,"B 级","C 级"))))
A38: 46162 | B38: =A38+7 | C38: 投放完毕 | D38: SSKYLAR | E38: https://www.douyin.com/note/7641993475752266235 | F38: 2026/5/22投放1000元 | G38: 上班楠 #原相机乘乘的 今天的开心是因为滴滴司机巨帅啊啊啊啊啊啊啊啊那我自己自拍这么多张沙意思？ | H38: 109 | I38: ='详细数据'!AC237 | J38: 766 | K38: 13 | L38: 38 | M38: 21 | N38: =SUM(J38:M38) | O38: ='详细数据'!J237 | P38: =O38/N38 | Q38: 产品力 | R38: 专车/豪华车 | T38: =IF(N38="","",IF(N38>=500000,"S 级",IF(N38>=100000,"A 级",IF(N38>=50000,"B 级","C 级"))))
A39: 46162 | B39: =A39+7 | C39: 投放完毕 | D39: @五月💘🌹 | E39: https://www.douyin.com/video/7641921320654050427 | F39: 2026/5/22投放1000元 | G39: 滴滴车司机清唱的真好听😄#520 | H39: 167 | I39: ='详细数据'!AC236 | J39: 370 | K39: 8 | L39: 11 | M39: 4 | N39: =SUM(J39:M39) | O39: ='详细数据'!J236 | P39: =O39/N39 | Q39: 司机 | R39: 司乘互动 | T39: =IF(N39="","",IF(N39>=500000,"S 级",IF(N39>=100000,"A 级",IF(N39>=50000,"B 级","C 级"))))
A40: 46162 | B40: =A40+7 | C40: 投放完毕 | D40: 小绿绿绿📸 | E40: https://www.douyin.com/video/7641922307711110454 | F40: 2026/5/22投放1000元2026/5/26投放30000元 | G40: 有一种爱叫妈妈永远在#亲情#家的味道#人间观察计划 | H40: 78302 | I40: ='详细数据'!AC235+'详细数据'!AC242 | J40: 232000 | K40: 16000 | L40: 9946 | M40: 16000 | N40: =SUM(J40:M40) | O40: ='详细数据'!J235+'详细数据'!J242 | P40: =O40/N40 | Q40: 司机 | R40: 司乘互动 | T40: =IF(N40="","",IF(N40>=500000,"S 级",IF(N40>=100000,"A 级",IF(N40>=50000,"B 级","C 级"))))
A41: 46162 | B41: =A41+7 | C41: 投放完毕 | D41: 温良人间 | E41: https://www.douyin.com/video/7641872986798179494 | F41: 2026/5/22投放1000元 | G41: 滴滴上叫了个车，等了13分钟才到，我都准备投诉了。｜温良人间 滴滴上叫了个车，13分钟才到。车窗降下来，副驾驶有人。一抬头，座椅后贴着一张纸。30年，她在他身边，他心里踏实。#人间真实 #夫妻相守 #暖心瞬间 #网约车司机 #温良人间 | H41: 717 | I41: ='详细数据'!AC234 | J41: 1257 | K41: 13 | L41: 29 | M41: 17 | N41: =SUM(J41:M41) | O41: ='详细数据'!J234 | P41: =O41/N41 | Q41: 司机 | R41: 司乘温暖 | T41: =IF(N41="","",IF(N41>=500000,"S 级",IF(N41>=100000,"A 级",IF(N41>=50000,"B 级","C 级"))))
A42: 46161 | B42: =A42+7 | C42: 投放完毕 | D42: 冥币生产厂家～赵姐 | E42: https://www.douyin.com/video/7641439405101877689 | F42: 2026/5/22投放1000元 | G42: 姐妹看看这是哪😃猜对有奖哈😂温馨提示：此路段比较拥挤，不适合开车，滴滴出行比较方便，并且还能趁等车的时间抖音臭美🤣😂#我不尴尬尴尬的就是别人 🥱😳 | H42: 224 | I42: ='详细数据'!AC233 | J42: 1006 | K42: 33 | L42: 92 | M42: 5 | N42: =SUM(J42:M42) | O42: ='详细数据'!J233 | P42: =O42/N42 | Q42: 场景 | R42: 通勤上下班 | T42: =IF(N42="","",IF(N42>=500000,"S 级",IF(N42>=100000,"A 级",IF(N42>=50000,"B 级","C 级"))))
A43: 46164 | B43: =A43+7 | C43: 投放完毕 | D43: 顾秋的枫 | E43: https://www.douyin.com/video/7642542991392131697 | F43: 2026/5/22投放1000元 | G43: 打车打到了辆很有意思的滴滴 | H43: 202 | I43: ='详细数据'!AC241 | J43: 359 | K43: 10 | L43: 23 | M43: 158 | N43: =SUM(J43:M43) | O43: ='详细数据'!J241 | P43: =O43/N43 | Q43: 车内 | R43: 特殊车型/车衣 | T43: =IF(N43="","",IF(N43>=500000,"S 级",IF(N43>=100000,"A 级",IF(N43>=50000,"B 级","C 级"))))
A44: 46165 | B44: =A44+7 | C44: 投放完毕 | D44: 娜妮妮 | E44: https://www.douyin.com/video/7642987403964425702 | F44: 2026/5/26投放1000元 | G44: 手机失而复得，谢谢超光速滴滴侠，匆忙的路程变得温暖。生活的每一环都值得记录#好人好事 #滴滴小哥 #好司机 | H44: 113 | I44: ='详细数据'!AC240 | J44: 323 | K44: 9 | L44: 137 | M44: 2 | N44: =SUM(J44:M44) | O44: ='详细数据'!J240 | P44: =O44/N44 | Q44: 司机 | R44: 司乘互动 | T44: =IF(N44="","",IF(N44>=500000,"S 级",IF(N44>=100000,"A 级",IF(N44>=50000,"B 级","C 级"))))
A45: 46167 | B45: =A45+7 | C45: 投放完毕 | D45: 晶ᰔᩚ晶 | E45: https://www.douyin.com/note/7643698260415278282 | F45: 2026/5/26投放1000元 | G45: 今天中午和爸爸从医院打车回家，因为拿的东西比较多，我想着打两辆车，这些行李和轮椅和凳子一车，我和爸爸在重新打个车，怕一个车进不去，然后滴滴司机师傅 | H45: 1283 | I45: ='详细数据'!AC243 | J45: 1443 | K45: 33 | L45: 330 | M45: 31 | N45: =SUM(J45:M45) | O45: ='详细数据'!J243 | P45: =O45/N45 | Q45: 司机 | R45: 司乘互动 | T45: =IF(N45="","",IF(N45>=500000,"S 级",IF(N45>=100000,"A 级",IF(N45>=50000,"B 级","C 级"))))
A46: 46170 | B46: =A46+7 | C46: 投放完毕 | D46: 小洸茫 | E46: https://www.douyin.com/note/7644783522482479781 | F46: 2026/5/29投放1000元 | G46: 今日份小惊喜，打到一个特价车就算了，一看还是#小米su7 最好看的颜色，上车一看还是个美女司机，一路心情都变好啦！#打车#滴滴出行 #打车 | H46: 111 | I46: ='详细数据'!AC245 | J46: 1561 | K46: 49 | L46: 38 | M46: 66 | N46: =SUM(J46:M46) | O46: ='详细数据'!J245 | P46: =O46/N46 | Q46: 司机 | R46: 女司机 | T46: =IF(N46="","",IF(N46>=500000,"S 级",IF(N46>=100000,"A 级",IF(N46>=50000,"B 级","C 级"))))
A47: 46170 | B47: =A47+7 | C47: 投放完毕 | D47: 天才楠 | E47: https://www.douyin.com/note/7644884486891055345 | F47: 2026/5/29投放1000元 | G47: 一个普通的清晨，着急赶飞机打了一辆车。这是我第一次被一个滴滴师傅激励到。车里非常干净，没有异味。手边放着鲜绿的盆栽，还有两盒小零食。副驾驶的前方粘着整齐成排小玩具。纸巾在专属的包厢里，包厢上贴着两面红旗。我前 | H47: 159 | I47: ='详细数据'!AC244 | J47: 2215 | K47: 27 | L47: 33 | M47: 32 | N47: =SUM(J47:M47) | O47: ='详细数据'!J244 | P47: =O47/N47 | Q47: 车内 | R47: 车内整洁 | T47: =IF(N47="","",IF(N47>=500000,"S 级",IF(N47>=100000,"A 级",IF(N47>=50000,"B 级","C 级"))))
A48: 46171 | B48: =A48+7 | C48: 投放完毕 | D48: SUXINTANG | E48: https://www.douyin.com/note/7645240445212140901 | F48: 2026/6/1投放200元 | G48: 今天和姐妹准备打车出去时，看到这个，真的🥹#滴滴出行 #上热搜 #girlshelpgirls #女性安全 #正能量 | H48: 231 | I48: ='详细数据'!AC248 | J48: 242 | K48: 6 | L48: 18 | M48: 15 | N48: =SUM(J48:M48) | O48: ='详细数据'!J248 | P48: =O48/N48 | Q48: 产品力 | R48: 女性友好计划 | T48: =IF(N48="","",IF(N48>=500000,"S 级",IF(N48>=100000,"A 级",IF(N48>=50000,"B 级","C 级"))))
A49: 46172 | B49: =A49+7 | C49: 在投 | D49: @FM986 | E49: https://www.douyin.com/user/MS4wLjABAAAAHiNlZYZTggesEkYjsQOZAMiIoZx92Px0Ly_6HDjpSMc?from_tab_name=main&modal_id=7645700319447662666&vid=7645700319447662666 | F49: 2026/6/1投放200元2026/6/2投放10000元2026/6/3投放10000元2026/6/4投放10000元 | G49: #热门 关于我们一家子打了一辆#网约公交车 | H49: 146000 | I49: ='详细数据'!AC247+'详细数据'!AC249+'详细数据'!AC251+'详细数据'!AC257 | J49: 207000 | K49: 8157 | L49: 19000 | M49: 335000 | N49: =SUM(J49:M49) | O49: ='详细数据'!J247+'详细数据'!J249+'详细数据'!J251+'详细数据'!J257 | P49: =O49/N49 | Q49: 产品力 | R49: 网约公交 | T49: =IF(N49="","",IF(N49>=500000,"S 级",IF(N49>=100000,"A 级",IF(N49>=50000,"B 级","C 级"))))
A50: 46172 | B50: =A50+7 | C50: 投放完毕 | D50: @我是一个大天才 | E50: https://www.douyin.com/user/MS4wLjABAAAA_7cgS9jyMObeRftEnQsxCj3kgz23c5BEfSOrqxibHa0?from_tab_name=main&modal_id=7645601096832956904&vid=7645601096832956904 | F50: 2026/6/1投放200元 | G50: #网约公交车 真是太方便啦！比打车还合适哈哈，车里空调足足的😂 | H50: 1595 | I50: ='详细数据'!AC246 | J50: 854 | K50: 86 | L50: 350 | M50: 1001 | N50: =SUM(J50:M50) | O50: ='详细数据'!J246 | P50: =O50/N50 | Q50: 产品力 | R50: 网约公交 | T50: =IF(N50="","",IF(N50>=500000,"S 级",IF(N50>=100000,"A 级",IF(N50>=50000,"B 级","C 级"))))

Sheet 6月加热汇总
A1: 发布日期 | B1: 投放截止日期 | C1: 状态 | D1: 达人名称 | E1: 链接 | F1: 投放记录 xx日投放xx元 | G1: 标题 | H1: 投前互动量 | I1: 投放互动量 | J1: 投放后点赞量 | K1: 投放后收藏量 | L1: 投放后评论量 | M1: 投放后转发量 | N1: 总互动量 | O1: 总投放金额 | P1: 综合cpe *投入/笔记外层互动数据 | Q1: 一级分类 | R1: 二级分类
A2: 汇总 | H2: - | I2: - | N2: =SUM(N3:N70) | O2: =SUM(O3:O70) | P2: =O2/N2
A3: 46173 | B3: =A3+7 | C3: 投放完毕 | D3: 月嫂 苗苗 拒绝连赞 | E3: https://www.douyin.com/video/7645956165910827377 | F3: 2026/6/2投放1000元 | G3: 滴滴打车平台真给力还是女司机漂亮美女车坐着舒服出发上班去了#车外风景 | H3: 80 | I3: ='详细数据'!AC250 | J3: 554 | K3: 8 | L3: 34 | M3: 2 | N3: =SUM(J3:M3) | O3: ='详细数据'!J250 | P3: =O3/N3 | Q3: 司机 | R3: 女司机
A4: 46175 | B4: =A4+7 | C4: 投放完毕 | D4: 小幸运888 | E4: https://www.douyin.com/note/7646727972648596218 | F4: 2026/6/3投放1000元2026/6/4投放5000元 | G4: 凌晨两点，那个沉默的司机救了我一命 | H4: 2597 | I4: ='详细数据'!AC253+'详细数据'!AC258 | J4: 16000 | K4: 1311 | L4: 444 | M4: 231 | N4: =SUM(J4:M4) | O4: ='详细数据'!J253+'详细数据'!J258 | P4: =O4/N4 | Q4: 司机 | R4: 司乘温暖
A5: 46175 | B5: =A5+7 | C5: 投放完毕 | D5: 天天有钱花女士 | E5: https://www.douyin.com/note/7646701552317873787 | F5: 2026/6/3投放1000元 | G5: 滴滴打车。肯定是特别勤快又负责任的滴滴司机，接到我订单就立马过来了，结果我一看他衣服都穿反了😁，我该怎么不失礼貌又委婉的提醒他啊！在线等挺急的…#在线等 | H5: 95 | I5: ='详细数据'!AC254 | J5: 392 | K5: 19 | L5: 100 | M5: 15 | N5: =SUM(J5:M5) | O5: ='详细数据'!J254 | P5: =O5/N5 | Q5: 司机 | R5: 司乘互动
A6: 46175 | B6: =A6+7 | C6: 无法投放 | D6: 蛋炒西红柿加番茄酱(求关注 | E6: https://www.douyin.com/note/7646632021980156346 | G6: 滴滴小程序和软件是都可以选择女司机的!#滴滴司机 #滴滴 #女性 #女性智慧 #女性成长 | H6: 521 | Q6: 产品力 | R6: 女性友好计划
A7: 46177 | B7: =A7+7 | C7: 投放完毕 | D7: 七里 | E7: https://www.douyin.com/video/7647214379003431907 | F7: 2026/6/4投放1000元 | G7: 前几天从医院出来，打车回家。上车以后才发现司机不会说话，是一位听障朋友。更要命的是，我还把上车地点定错了。我手忙脚乱地比划着请他先靠边停，又掏出手机打字给他看，他始终很耐心，没有半点不耐烦。重新设好目的地后，车子稳稳地开了一路。 | H7: 219 | I7: ='详细数据'!AC256 | J7: 2173 | K7: 21 | L7: 18 | M7: 9 | N7: =SUM(J7:M7) | O7: ='详细数据'!J256 | P7: =O7/N7 | Q7: 司机 | R7: 特殊身份-听障司机
A8: 46175 | B8: =A8+7 | C8: 投放完毕 | D8: @悠游自在 | E8: https://www.douyin.com/user/MS4wLjABAAAAJT00acZ9BEt6-OB1zk6oV1GFf2azeh_kQhjcxcwY0X8k-_kXcxTTL2JwWJUF35x1?from_tab_name=main&modal_id=7646742373196733811 | F8: 2026/6/4投放1000元 | G8: 退休低成本快乐 #退休日常生活记录 #网约 #一日游玩 | H8: 171 | I8: ='详细数据'!AC255 | J8: 1016 | K8: 48 | L8: 125 | M8: 31 | N8: =SUM(J8:M8) | O8: ='详细数据'!J255 | P8: =O8/N8 | Q8: 产品力 | R8: 网约公交
A9: 46177 | B9: =A9+7 | C9: 投放完毕 | D9: @LiLi_ | E9: https://www.douyin.com/user/MS4wLjABAAAAuZvZ6VAA6cysm3VWXGSfj4yJnWGSOUFbZFAky1iC_1Q?from_tab_name=main&modal_id=7647513382476541541&vid=7647513382476541541 | F9: 2026/6/5投放1000元 | G9: 今天趁着好天气、打了一次滴滴公交车🚌还是很方便哒 #滴滴公交 #来晒一下手机实拍画质 | H9: 52 | I9: ='详细数据'!AC259 | J9: 383 | K9: 11 | L9: 31 | M9: 14 | N9: =SUM(J9:M9) | O9: ='详细数据'!J259 | P9: =O9/N9 | Q9: 产品力 | R9: 网约公交
A10: 46179 | B10: =A10+7 | C10: 投放完毕 | D10: 汪涛和导盲犬叮当 | E10: https://www.douyin.com/video/7648092654844692970 | F10: 2026/6/8投放1000元 | G10: 同时带两条导盲犬上车，偶遇热情大连司机，小小车程满是温暖 在大连旅顺行程结束，我带着导盲犬叮当和另一个盲人伙伴以及另一条导盲犬椰果和他的家人结伴，从酒店打滴滴前往附近地铁站。临走和同行的视障朋友挥手告别，相聚时间很短，下次见面不知什么时候，心里很舍不得。 路上碰到一位热心的滴滴司机，上车主动搀扶我们，帮忙把行李放进后备箱。开车途中，师傅不停夸赞两只导盲犬乖巧听话。闲聊时师傅说，之前一直以为培育一只导盲犬需要200万。 我们跟师傅解释，一只导盲犬选育、长年训练、考核上岗，整体成本在20万左右，师傅听完才了解实情。 到地铁站下车，师傅又贴心把行李从后备箱拿出来。 一趟短短的车程，实实在在感受到大连人的热心和善心，谢谢这位暖心司机，为大连点赞。 #导盲犬叮当 #滴滴出行 #大连 #无障碍出行 #青年创作者计划 | H10: 164 | I10: ='详细数据'!AC261 | J10: 1414 | K10: 48 | L10: 33 | M10: 5 | N10: =SUM(J10:M10) | O10: ='详细数据'!J261 | P10: =O10/N10 | Q10: 司机 | R10: 司乘互动
A11: 46178 | B11: =A11+7 | C11: 投放完毕 | D11: ❤️心安੭ﾞ | E11: https://www.douyin.com/note/7647815865568169295 | F11: 2026/6/8投放1000元 | G11: 9237极速赶车第一人 3点26的高铁3点02上的滴滴 司机帮我赶路程3点22下的滴滴到检票口已经停止检票了，怎么检票口的妹妹说还可以进 一路呼呲带喘的赶到了月台 此刻 高铁马上到金华了 我下车了 | H11: 267 | I11: ='详细数据'!AC260 | J11: 1742 | K11: 42 | L11: 47 | M11: 4 | N11: =SUM(J11:M11) | O11: ='详细数据'!J260 | P11: =O11/N11 | Q11: 司机 | R11: 司乘互动
A12: 46177 | B12: =A12+7 | C12: 投放完毕 | D12: 电气昊子 | E12: https://www.douyin.com/video/7647506813403365321 | F12: 2026/6/9投放3000元2026/6/10投放5000元 | G12: 算了，哈尔滨夏天14度的含金量，跟你们说不清楚#哈尔滨 #晚霞 #城市的夜晚 #城市风景 #城市建设 | I12: ='详细数据'!AC263+'详细数据'!AC265 | J12: 23000 | K12: 768 | L12: 842 | M12: 5532 | N12: =SUM(J12:M12) | O12: ='详细数据'!J263+'详细数据'!J265 | P12: =O12/N12 | Q12: 产品力 | R12: 网约公交
A13: 46181 | B13: =A13+7 | C13: 投放完毕 | D13: ​车厘子的子 | E13: https://www.douyin.com/video/7648887011160830180 | F13: 2026/6/9投放500元 | G13: 来大连这几天给我的感受就是“大连 你美” | I13: ='详细数据'!AC262 | J13: 562 | K13: 50 | L13: 29 | M13: 137 | N13: =SUM(J13:M13) | O13: ='详细数据'!J262 | P13: =O13/N13 | Q13: 产品力 | R13: 滴滴专车
A14: 46181 | B14: =A14+7 | C14: 投放完毕 | D14: 小小麻～🥕 | E14: https://www.douyin.com/video/7648840710867964325 | F14: 2026/6/10投放1000元 | G14: 苏州站赶高铁 苏州站9:54的车，9:17才上车，滴滴出行写的预计36分钟。跟师傅一说赶高铁，师傅就起飞了...全程DJ嘿喂狗嘿喂狗，最后9:44到苏州站了。22公里，36分钟的车程，27分钟就到了，提前了10分钟！！天上飞机，地上苏E！！#车上的那些事儿 #天上飞机地上苏e | H14: 759 | I14: ='详细数据'!AC264 | J14: 1236 | K14: 33 | L14: 420 | M14: 141 | N14: =SUM(J14:M14) | O14: ='详细数据'!J264 | P14: =O14/N14 | Q14: 司机 | R14: 驾驶技术
A15: 46179 | B15: =A15+7 | C15: 投放完毕 | D15: 苏二小姐 | E15: https://www.douyin.com/video/7648121194428425573 | F15: 2026/6/10投放1000元 | G15: #滴滴公交车 #公交网约车 网约公交车来了🎈 | H15: 1739 | I15: ='详细数据'!AC269 | J15: 2496 | K15: 95 | L15: 275 | M15: 879 | N15: =SUM(J15:M15) | O15: ='详细数据'!J269 | P15: =O15/N15 | Q15: 产品力 | R15: 网约公交
A16: 46180 | B16: =A16+7 | C16: 投放完毕 | D16: 大鹏嘚吧嘚 | E16: https://www.douyin.com/video/7648609080373822586 | F16: 2026/6/10投放1000元 | G16: 空调嘎嘎凉快，只需三块#网约公交车 #天津公交 | H16: 4091 | I16: ='详细数据'!AC268 | J16: 3271 | K16: 224 | L16: 667 | M16: 2321 | N16: =SUM(J16:M16) | O16: ='详细数据'!J268 | P16: =O16/N16 | Q16: 产品力 | R16: 网约公交
A17: 46181 | B17: =A17+7 | C17: 投放完毕 | D17: 🐳洁 | E17: https://www.douyin.com/video/7648943448107741682 | F17: 2026/6/10投放1000元 | G17: 体验济南网约公交车🚌体验感很好 #济南网约公交 #公共交通 #公共交通绿色出行 我也体验了一把网约公交的快乐，全程只需3元钱，送到指定位置，这趟车我包车啦哈哈😃绿色出行的快乐 | H17: 741 | I17: ='详细数据'!AC267 | J17: 1033 | K17: 71 | L17: 150 | M17: 529 | N17: =SUM(J17:M17) | O17: ='详细数据'!J267 | P17: =O17/N17 | Q17: 产品力 | R17: 网约公交
A18: 46182 | B18: =A18+7 | C18: 在投 | D18: 夏荷 | E18: https://www.douyin.com/note/7649063213564689138 | F18: 2026/6/10投放1000元 | G18: #湖大到家里的温暖滴滴之旅。今天上午从湖大打车回家，遇到一位超贴心的美女师傅！ | H18: 73 | I18: ='详细数据'!AC266 | J18: 326 | K18: 18 | L18: 7 | M18: 5 | N18: =SUM(J18:M18) | O18: ='详细数据'!J266 | P18: =O18/N18 | Q18: 司机 | R18: 女司机
A19: 46187 | B19: =A19+7 | D19: 高鹰汤哥🐉 | E19: https://www.douyin.com/video/7651087551021976177 | G19: #演唱会的正确打开方式 还好美好占据了世界的大多数！演唱会结束，上万人的打车现场，我们已经打了一个小时的滴滴，加价都没打到，让我们遇见了一位好心的南京滴滴大哥买免费到我们到酒店，送到酒店我们问师傅多少钱，滴滴大哥说：我们不谈钱，只说缘。被感动到了！南京^_^下次我们还来！ | H19: 433
A20: 46188 | B20: =A20+7 | D20: 开往拉萨的小火车🚄 | E20: https://www.douyin.com/video/7651235777007377787 | G20: 带娃体验天津网约公交✨ 今天带小朋友去坐了天津的滴滴网约公交车，小家伙全程新奇得不行，眼睛都亮了，一直手舞足蹈的，特别开心～想坐的有什么不明白的可以评论区咨询我哦，今天都跟司机师傅聊明白的啦😊 | H20: 45

Sheet 详细数据
A1: 订单号 | B1: 订单类型 | C1: 作者名称 | D1: 视频标题 | E1: 视频链接 | F1: 下单时间 | G1: 状态 | H1: 订单金额（元） | I1: 预算（元） | J1: 消耗（元） | K1: 投放目标 | L1: 转化量 | M1: 转化成本 | N1: 直播间展示量 | O1: 新增观众量 | P1: 新增粉丝量 | Q1: 直播评论量 | R1: 视频播放量 | S1: 5秒完播率 | T1: 视频点赞量 | U1: 视频评论量 | V1: 视频分享量 | W1: 主页浏览量 | X1: 粉丝量 | Y1: 付费金额 | Z1: 预计投放时长 | AA1: 定向详情 | AC1: 总互动
A2: 1858553019316387 | B2: 普通订单 | C2: 酸奶吐司 | D2: 广州的滴滴车也太可爱了吧！坐得心情都美美的#广州 #广州滴滴 | E2: https://www.douyin.com/video/7612207816275352497 | F2: 46083.851 | G2: 投放完成 | H2: 500 | I2: 500 | J2: 500 | K2: 点赞评论量 | L2: 30072 | M2: 16.63 | R2: 30072 | S2: 未获得授权 | T2: 2695 | U2: 10 | V2: 405 | W2: 40 | X2: 4 | Z2: 6.0 小时 | AA2: 系统智能投放 | AC2: =SUM(T2:V2)
A3: 1858553070969904 | B3: 普通订单 | C3: 尚雅求真 | D3: “滴滴”赞 ——写在滴滴打车两年之际 （2026年2月28日） 滴滴， 无处不有处处有； 滴滴， 无时不有时时有。 滴滴， 给不车者插上翅膀； 滴滴， 让不车族便利出行。 滴滴， 让我退而不休； 滴滴， 让我视野开阔。 滴滴， 让我天天穿梭灞桥未央之间； 滴滴， 让我日日架起两地教育桥梁。 滴滴， 也让我认识了诸多司机朋友； 滴滴， 更让我了解了许多人间冷暖。 滴滴师傅的“豁达”， 让我身心愉悦； 滴滴师傅的“坚韧”， 让我倍感钦佩。 滴滴， 车车干净， 人人礼貌， 让我欣喜； 滴滴， 一会儿“78”， 一会儿“33”， 也让困惑。 愿滴滴管理日益科学！ 为滴滴司机点赞加油！ | E3: https://www.douyin.com/video/7611743676641705295 | F3: 46083.851 | G3: 投放完成 | H3: 500 | I3: 500 | J3: 500 | K3: 点赞评论量 | L3: 26860 | M3: 18.62 | R3: 26860 | S3: 未获得授权 | T3: 1082 | U3: 12 | V3: 0 | W3: 51 | X3: 10 | Z3: 6.0 小时 | AA3: 系统智能投放 | AC3: =SUM(T3:V3)
A4: 1858553087987723 | B4: 普通订单 | C4: Mr 钟又离 | D4: 太酷了 男滴滴司机的公主车： 啥样生活都是经营出来的不是吗#温暖治愈 #人间烟火#滴滴司机 #非标准人生#清醒的选负责到底 | E4: https://www.douyin.com/video/7612244922887857787 | F4: 46083.851 | G4: 投放完成 | H4: 500 | I4: 500 | J4: 500 | K4: 点赞评论量 | L4: 26306 | M4: 19.01 | R4: 26306 | S4: 未获得授权 | T4: 1404 | U4: 14 | V4: 9 | W4: 43 | X4: 11 | Z4: 6.0 小时 | AA4: 系统智能投放 | AC4: =SUM(T4:V4)
A5: 1858553133359451 | B5: 普通订单 | C5: 白开水泡茶 | D5: 武汉下雨天，我打了辆滴滴准备回学校。车正常停在路口，我刚要上车，手里装东西的纸袋子突然破了，东西撒了一地。我赶紧跟司机师傅说清楚情况，问他车上有没有袋子借我用一下。他二话不说，直接拿了个黑色塑料袋给我，那个袋子是真结实，我用过最好用的黑袋子！更贴心的是，他还跟我说：“一个怕又破了，我给你两个套着用。”本来就是件小麻烦，被师傅这么一弄，瞬间觉得特别暖心。陌生人的这份细心，真的让人心里特别舒服。 我再也不用写“发烧后妈妈背我去医院”的作文了。 我再也不用写“下雨天妈妈给我送伞”的作文了。 我再也不用写“我不会做题，老师耐心教我”的作文了。 我再也不用写“我摔倒了，同学扶我起来”的作文了。 我再也不用写“妈妈深夜给我盖被子”的作文了。 我再也不用写“我生病了，爸爸连夜带我看病”的作文了。 那些小时候最常见、最经典的模仿感恩作文，我终于不用再写啦！我有自己的感恩作文了！ | E5: https://www.douyin.com/note/7612110532075037129 | F5: 46083.851 | G5: 投放完成 | H5: 500 | I5: 500 | J5: 500 | K5: 点赞评论量 | L5: 44155 | M5: 11.32 | R5: 44155 | S5: 未获得授权 | T5: 1266 | U5: 7 | V5: 7 | W5: 1001 | X5: 5 | Z5: 6.0 小时 | AA5: 系统智能投放 | AC5: =SUM(T5:V5)
A6: 1858553164085371 | B6: 普通订单 | C6: 清风✨ | D6: 小同志，磁场又弱了吧，是时候充电了 #天安门 #士兵突击 #滴滴司机 感谢北京的滴滴师傅，放慢车速让我们看天安门夜景 | E6: https://www.douyin.com/video/7612087271226903844 | F6: 46083.852 | G6: 投放完成 | H6: 500 | I6: 500 | J6: 500 | K6: 点赞评论量 | L6: 27016 | M6: 18.51 | R6: 27016 | S6: 未获得授权 | T6: 2808 | U6: 15 | V6: 48 | W6: 56 | X6: 2 | Z6: 6.0 小时 | AA6: 系统智能投放 | AC6: =SUM(T6:V6)
A7: 1858553189305434 | B7: 普通订单 | C7: 北辰 | D7: 爱心：爱的传递。这是我遇见的最暖心的滴滴司机师傅，太原的成师傅，车牌号晋AAA1715。车费只有9.4元，但是我享受的确是专车的待遇，甚至比专车还好。上车、下车成师傅都很热心的帮我搬行李，我的行李很重，但是成师傅一点也不介意。上车后，车上很干净，而且车上备有充电器，小垃圾桶，防晕车的塑料袋，一次性口罩，一次性雨衣，防止血糖低的糖，还有速效救心丸。我和成师傅说，你是我遇见最贴心的司机师傅，没有之一。成师傅说，希望能尽自己所能，帮助更多的人。给太原成师傅点赞，希望以后还能坐到您的车。 | E7: https://www.douyin.com/note/7611832044951303909 | F7: 46083.852 | G7: 投放完成 | H7: 500 | I7: 500 | J7: 500 | K7: 点赞评论量 | L7: 28147 | M7: 17.76 | R7: 28147 | S7: 未获得授权 | T7: 1058 | U7: 13 | V7: 2 | W7: 233 | X7: 13 | Z7: 6.0 小时 | AA7: 系统智能投放 | AC7: =SUM(T7:V7)
A8: 1858553218214055 | B8: 普通订单 | C8: 一生有你 | D8: 人生第一次打到滴滴女司机，技术稳得一批，完全不输男司机👍 | E8: https://www.douyin.com/note/7611432494563328113 | F8: 46083.853 | G8: 投放完成 | H8: 500 | I8: 500 | J8: 500 | K8: 点赞评论量 | L8: 27088 | M8: 18.46 | R8: 27088 | S8: 未获得授权 | T8: 1257 | U8: 31 | V8: 4 | W8: 208 | X8: 11 | Z8: 6.0 小时 | AA8: 系统智能投放 | AC8: =SUM(T8:V8)
A9: 1858553250777130 | B9: 普通订单 | C9: Saffron | D9: 下班遇到了一位温暖的滴滴司机，椅背贴了一张纸条，口袋里放了两本小册子，两支笔和一面镜子，出于好奇心翻开册子却得到了最温暖的慰藉。司机师傅说这是他很早就想做的事情，希望他的工作也能给每一位归家或旅途中的乘客带来温暖和治愈。看着每一个陌生人的留言感觉上班的疲惫和焦虑一扫而空，我原本寻思那些个互联网上所谓的世界美好的宣言都是空谈，但是到此时此刻一时一景一心境，一花一景一世界才得以具像化。感恩遇见这位温暖的师傅，也感谢每一位留言的陌生人给我带来的幸福感。愿无论是深陷囹圄还是已经拥抱幸福的你们未来的每一天都平安喜乐，万事顺遂！ | E9: https://www.douyin.com/note/7611499522330631857 | F9: 46083.853 | G9: 投放完成 | H9: 500 | I9: 500 | J9: 500 | K9: 点赞评论量 | L9: 24300 | M9: 20.58 | R9: 24300 | S9: 未获得授权 | T9: 1280 | U9: 12 | V9: 9 | W9: 50 | X9: 13 | Z9: 6.0 小时 | AA9: 系统智能投放 | AC9: =SUM(T9:V9)
A10: 1858553275253808 | B10: 普通订单 | C10: 康老师（武汉少儿阅读） | D10: 武汉有滴滴公交啦！学名响应式公交，武汉公交APP或者小程序就可以一键预约，3分钟之内来接你，有100多个站点，覆盖医院，学校，商场非常方便，既有网约车🚗的便捷又有公交车🚌的实惠！ #mini公交车 #武汉 #武汉公交 #出行新方式 #公共交通 | E10: https://www.douyin.com/video/7611192244423229139 | F10: 46083.853 | G10: 投放完成 | H10: 500 | I10: 500 | J10: 500 | K10: 点赞评论量 | L10: 26682 | M10: 18.74 | R10: 26682 | S10: 未获得授权 | T10: 1120 | U10: 15 | V10: 10 | W10: 31 | X10: 15 | Z10: 6.0 小时 | AA10: 系统智能投放 | AC10: =SUM(T10:V10)
A11: 1858623530447112 | B11: 普通订单 | C11: Saffron | D11: 下班遇到了一位温暖的滴滴司机，椅背贴了一张纸条，口袋里放了两本小册子，两支笔和一面镜子，出于好奇心翻开册子却得到了最温暖的慰藉。司机师傅说这是他很早就想做的事情，希望他的工作也能给每一位归家或旅途中的乘客带来温暖和治愈。看着每一个陌生人的留言感觉上班的疲惫和焦虑一扫而空，我原本寻思那些个互联网上所谓的世界美好的宣言都是空谈，但是到此时此刻一时一景一心境，一花一景一世界才得以具像化。感恩遇见这位温暖的师傅，也感谢每一位留言的陌生人给我带来的幸福感。愿无论是深陷囹圄还是已经拥抱幸福的你们未来的每一天都平安喜乐，万事顺遂！ | E11: https://www.douyin.com/note/7611499522330631857 | F11: 46084.628 | G11: 投放完成 | H11: 1000 | I11: 1000 | J11: 1000 | K11: 点赞评论量 | L11: 55366 | M11: 18.06 | R11: 55366 | S11: 未获得授权 | T11: 3541 | U11: 15 | V11: 19 | W11: 137 | X11: 25 | Z11: 6.0 小时 | AA11: 系统智能投放 | AC11: =SUM(T11:V11)
A12: 1858623420580004 | B12: 普通订单 | C12: 清风✨ | D12: 小同志，磁场又弱了吧，是时候充电了 #天安门 #士兵突击 #滴滴司机 感谢北京的滴滴师傅，放慢车速让我们看天安门夜景 | E12: https://www.douyin.com/video/7612087271226903844 | F12: 46084.628 | G12: 投放完成 | H12: 1000 | I12: 1000 | J12: 1000 | K12: 点赞评论量 | L12: 54301 | M12: 18.42 | R12: 54301 | S12: 未获得授权 | T12: 10803 | U12: 49 | V12: 211 | W12: 127 | X12: 7 | Z12: 6.0 小时 | AA12: 系统智能投放 | AC12: =SUM(T12:V12)
A13: 1858623383990304 | B13: 普通订单 | C13: 白开水泡茶 | D13: 武汉下雨天，我打了辆滴滴准备回学校。车正常停在路口，我刚要上车，手里装东西的纸袋子突然破了，东西撒了一地。我赶紧跟司机师傅说清楚情况，问他车上有没有袋子借我用一下。他二话不说，直接拿了个黑色塑料袋给我，那个袋子是真结实，我用过最好用的黑袋子！更贴心的是，他还跟我说：“一个怕又破了，我给你两个套着用。”本来就是件小麻烦，被师傅这么一弄，瞬间觉得特别暖心。陌生人的这份细心，真的让人心里特别舒服。 我再也不用写“发烧后妈妈背我去医院”的作文了。 我再也不用写“下雨天妈妈给我送伞”的作文了。 我再也不用写“我不会做题，老师耐心教我”的作文了。 我再也不用写“我摔倒了，同学扶我起来”的作文了。 我再也不用写“妈妈深夜给我盖被子”的作文了。 我再也不用写“我生病了，爸爸连夜带我看病”的作文了。 那些小时候最常见、最经典的模仿感恩作文，我终于不用再写啦！我有自己的感恩作文了！ | E13: https://www.douyin.com/note/7612110532075037129 | F13: 46084.627 | G13: 投放完成 | H13: 1000 | I13: 1000 | J13: 1000 | K13: 点赞评论量 | L13: 73591 | M13: 13.59 | R13: 73591 | S13: 未获得授权 | T13: 3458 | U13: 12 | V13: 42 | W13: 1474 | X13: 25 | Z13: 6.0 小时 | AA13: 系统智能投放 | AC13: =SUM(T13:V13)
... A25: 1858703019220299 | B25: 普通订单 | C25: 一場、流★雨 | D25: 这辈子第一次坐RR，居然是在滴滴订单里😂😂 | E25: https://www.douyin.com/video/7612918993481033330 | F25: 46085.506 | G25: 投放完成 | H25: 500 | I25: 500 | J25: 500 | K25: 点赞评论量 | L25: 28758 | M25: 17.39 | R25: 28758 | S25: 未获得授权 | T25: 1900 | U25: 100 | V25: 10 | W25: 183 | X25: 28 | Z25: 6.0 小时 | AA25: 系统智能投放 | AC25: =SUM(T25:V25)
A26: 1858814215910416 | B26: 普通订单 | C26: 酸奶吐司 | D26: 广州的滴滴车也太可爱了吧！坐得心情都美美的#广州 #广州滴滴 | E26: https://www.douyin.com/video/7612207816275352497 | F26: 46086.733 | G26: 投放完成 | H26: 500 | I26: 500 | J26: 500 | K26: 点赞评论量 | L26: 34069 | M26: 14.68 | O26: =L226 | R26: 34069 | S26: 未获得授权 | T26: 7952 | U26: 20 | V26: 2135 | W26: 90 | X26: 1 | Z26: 6.0 小时 | AA26: 系统智能投放 | AC26: =SUM(T26:V26)
A27: 1858813788456169 | B27: 普通订单 | C27: 小万不吃香菜 | D27: 打到了一辆超级干净的滴滴 心情都变美了 #打车打车 | E27: https://www.douyin.com/video/7613215289803536101 | F27: 46086.728 | G27: 投放完成 | H27: 500 | I27: 500 | J27: 500 | K27: 点赞评论量 | L27: 31063 | M27: 16.1 | R27: 31063 | S27: 未获得授权 | T27: 1689 | U27: 22 | V27: 3 | W27: 136 | X27: 4 | Z27: 6.0 小时 | AA27: 系统智能投放 | AC27: =SUM(T27:V27)
A28: 1858813611580496 | B28: 普通订单 | C28: 花渐落 | D28: 郑州今后的发展会越来越好：今天打出租车，司机服务态度超好，情绪价值给的满满，贴心热情。很多时候，出租车司机是咱河南给外地游客的第一张名片，整体素质上去了，咱河南的声誉会越来越好，良性循环😀 前年一下高铁，打车滴滴，司机师傅也是自豪地给我们介绍河南的美食景点，总想给初到者第一个好印象，所以我赌大郑州大河南会越来越好👍 | E28: https://www.douyin.com/note/7612219889386191970 | F28: 46086.726 | G28: 投放完成 | H28: 500 | I28: 500 | J28: 500 | K28: 点赞评论量 | L28: 31088 | M28: 16.08 | R28: 31088 | S28: 未获得授权 | T28: 1393 | U28: 32 | V28: 4 | W28: 29 | X28: 5 | Z28: 6.0 小时 | AA28: 系统智能投放 | AC28: =SUM(T28:V28)
A29: 1858813542416464 | B29: 普通订单 | C29: 🦁 🦁 奔跑的蜗牛 | D29: 今天出门打车居然打到了特斯拉，北京果然藏龙卧虎啊，连特斯拉都来跑滴滴了#特斯拉 #特斯拉汽车 #北京网约车 #北京网约车司机 | E29: https://www.douyin.com/note/7613350700244157626 | F29: 46086.726 | G29: 投放完成 | H29: 500 | I29: 500 | J29: 500 | K29: 点赞评论量 | L29: 28114 | M29: 17.78 | R29: 28114 | S29: 未获得授权 | T29: 1173 | U29: 62 | V29: 9 | W29: 50 | X29: 9 | Z29: 6.0 小时 | AA29: 系统智能投放 | AC29: =SUM(T29:V29)
A30: 1858813482534972 | B30: 普通订单 | C30: 小万不吃香菜 | D30: 打到了一辆超级干净的滴滴 心情都变美了 #打车打车 | E30: https://www.douyin.com/video/7613215289803536101 | F30: 46086.725 | G30: 投放完成 | H30: 500 | I30: 500 | J30: 500 | K30: 点赞评论量 | L30: 32169 | M30: 15.54 | R30: 32169 | S30: 未获得授权 | T30: 1498 | U30: 27 | V30: 19 | W30: 115 | X30: 5 | Z30: 6.0 小时 | AA30: 系统智能投放 | AC30: =SUM(T30:V30)
A31: 1858813425318154 | B31: 普通订单 | C31: 清风✨ | D31: 小同志，磁场又弱了吧，是时候充电了 #天安门 #士兵突击 #滴滴司机 感谢北京的滴滴师傅，放慢车速让我们看天安门夜景 | E31: https://www.douyin.com/video/7612087271226903844 | F31: 46086.724 | G31: 投放完成 | H31: 500 | I31: 500 | J31: 500 | K31: 点赞评论量 | L31: 27036 | M31: 18.49 | R31: 27036 | S31: 未获得授权 | T31: 6097 | U31: 22 | V31: 137 | W31: 83 | X31: 0 | Z31: 6.0 小时 | AA31: 系统智能投放 | AC31: =SUM(T31:V31)
A32: 1859164681319671 | B32: 普通订单 | C32: ⁺✞ʚ佐鸣重度依赖ɞ✟₊ | D32: 上天入地我再也找不到佐鸣这样美好的家产了。家产要永远幸福！ #佐鸣 #佐鸣永远热恋 #滴滴打车 3799！（拍照已取得司机同意 ）我真的没想到能在3月7号打到3799的车！真的很高兴很高兴，希望下一次还能再打到这辆车！（无恶意纯属同人女的兴奋！大哥人特别好啊，同意我拍照了！） | E32: https://www.douyin.com/note/7614491818344720739 | F32: 46090.602 | G32: 投放完成 | H32: 500 | I32: 500 | J32: 500 | K32: 点赞评论量 | L32: 25964 | M32: 19.26 | R32: 25964 | S32: 未获得授权 | T32: 1574 | U32: 11 | V32: 1 | W32: 27 | X32: 3 | Z32: 6.0 小时 | AA32: 系统智能投放 | AC32: =SUM(T32:V32)
A33: 1859164650458329 | B33: 普通订单 | C33: 莫陌墨默 | D33: 你们遇过有趣的司机吗？回家路上，司机自娱自乐，一句“不会让我亲脆”让我破防，简直是氛围组，然后人生第一次跟滴滴合唱😂😂😂，憋怕我伤心#网约车 #网约车那些事 | E33: https://www.douyin.com/video/7614604940937363313 | F33: 46090.601 | G33: 投放完成 | H33: 500 | I33: 500 | J33: 500 | K33: 点赞评论量 | L33: 26800 | M33: 18.66 | R33: 26800 | S33: 未获得授权 | T33: 1618 | U33: 26 | V33: 6 | W33: 32 | X33: 37 | Z33: 6.0 小时 | AA33: 系统智能投放 | AC33: =SUM(T33:V33)
A34: 1859164467267692 | B34: 普通订单 | C34: 一点也不酷啊。 | D34: 打了2个小时滴滴，取消了半天，终于打到了。氛围灯也开了，最好的安排也安排了，总裁座椅也给他调了。他常出现的地方我给你们标记出来了 #洛阳胡师傅 #滴滴迈巴赫 #洛阳胡师傅路人视角 | E34: https://www.douyin.com/video/7614841048691419327 | F34: 46090.599 | G34: 投放完成 | H34: 500 | I34: 500 | J34: 500 | K34: 点赞评论量 | L34: 34757 | M34: 14.39 | R34: 34757 | S34: 未获得授权 | T34: 4640 | U34: 35 | V34: 814 | W34: 460 | X34: 1 | Z34: 6.0 小时 | AA34: 系统智能投放 | AC34: =SUM(T34:V34)
A35: 1859164399541248 | B35: 普通订单 | C35: GOOD. | D35: 愿：平安 发财。@滴滴出行司机中心官方账号 | E35: https://www.douyin.com/note/7613787027502461352 | F35: 46090.599 | G35: 投放完成 | H35: 500 | I35: 500 | J35: 500 | K35: 点赞评论量 | L35: 29713 | M35: 16.83 | R35: 29713 | S35: 未获得授权 | T35: 2965 | U35: 5 | V35: 35 | W35: 87 | X35: 4 | Z35: 6.0 小时 | AA35: 系统智能投放 | AC35: =SUM(T35:V35)
A36: 1859164326170953 | B36: 普通订单 | C36: 小万不吃香菜 | D36: 打到了一辆超级干净的滴滴 心情都变美了 #打车打车 | E36: https://www.douyin.com/video/7613215289803536101 | F36: 46090.598 | G36: 投放完成 | H36: 500 | I36: 500 | J36: 500 | K36: 点赞评论量 | L36: 38997 | M36: 12.82 | R36: 38997 | S36: 未获得授权 | T36: 216 | U36: 24 | V36: 3 | W36: 219 | X36: 3 | Z36: 6.0 小时 | AA36: 系统智能投放 | AC36: =SUM(T36:V36)
A37: 1859164253674539 | B37: 普通订单 | C37: 清风✨ | D37: 小同志，磁场又弱了吧，是时候充电了 #天安门 #士兵突击 #滴滴司机 感谢北京的滴滴师傅，放慢车速让我们看天安门夜景 | E37: https://www.douyin.com/video/7612087271226903844 | F37: 46090.597 | G37: 投放完成 | H37: 500 | I37: 500 | J37: 500 | K37: 点赞评论量 | L37: 27401 | M37: 18.25 | R37: 27401 | S37: 未获得授权 | T37: 8001 | U37: 6 | V37: 54 | W37: 55 | X37: 1 | Z37: 6.0 小时 | AA37: 系统智能投放 | AC37: =SUM(T37:V37)
A38: 1859166378451241 | B38: 普通订单 | C38: 酸奶吐司 | D38: 广州的滴滴车也太可爱了吧！坐得心情都美美的#广州 #广州滴滴 | E38: https://www.douyin.com/video/7612207816275352497 | F38: 46090.62 | G38: 投放完成 | H38: 500 | I38: 500 | J38: 500 | K38: 点赞评论量 | L38: 55976 | M38: 8.93 | R38: 55976 | S38: 未获得授权 | T38: 5067 | U38: 43 | V38: 5724 | W38: 148 | X38: 7 | Z38: 6.0 小时 | AA38: 系统智能投放 | AC38: =SUM(T38:V38)
... A69: 1859901239659895 | B69: 普通订单 | C69: 绛珠仙子成长日记 | D69: 5.0分的滴滴司机 师傅我听懂了 其实你在告诉我 这个世界上没有定义 只有视角不同 但我此刻有个善良的定义 那就是你的那一句 “为什么你大半夜去人民医院” 以及你的善意的开导 但我是个杠精 我天天带着答案问问题 请原谅我 谢谢你，陌生人 至少此刻你的善良给我带来了开心 我对很多东西都没有欲望 但是对善意的瞬间 充满欲望 渴求遇见它享受它 #司机师傅 #欲望 #善良 | E69: https://www.douyin.com/video/7615713873504923322 | F69: 46098.732 | G69: 投放完成 | H69: 1000 | I69: 1000 | J69: 1000 | K69: 点赞评论量 | L69: 56126 | M69: 17.82 | R69: 56126 | S69: 未获得授权 | T69: 15953 | U69: 120 | V69: 303 | W69: 1328 | X69: 13 | Z69: 6.0 小时 | AA69: 系统智能投放 | AC69: =SUM(T69:V69)
A70: 1859901205033108 | B70: 普通订单 | C70: 71623570672 | D70: 滴滴还是太超前了 滴滴还能打倒特斯拉 | E70: https://www.douyin.com/video/7617859050039070435 | F70: 46098.732 | G70: 投放完成 | H70: 500 | I70: 500 | J70: 500 | K70: 点赞评论量 | L70: 30522 | M70: 16.38 | R70: 30522 | S70: 未获得授权 | T70: 69 | U70: 47 | V70: 4 | W70: 104 | X70: 3 | Z70: 6.0 小时 | AA70: 系统智能投放 | AC70: =SUM(T70:V70)
A71: 1859901165763728 | B71: 普通订单 | C71: 乌苏一姐 | D71: #滴滴打车 好好赚钱雇个司机，想谈个贴心的对象，但发现只要出钱就有人愿意服务！ | E71: https://www.douyin.com/video/7617891266244423656 | F71: 46098.731 | G71: 投放完成 | H71: 500 | I71: 500 | J71: 500 | K71: 点赞评论量 | L71: 33765 | M71: 14.81 | R71: 33765 | S71: 未获得授权 | T71: 74 | U71: 17 | V71: 0 | W71: 121 | X71: 1 | Z71: 6.0 小时 | AA71: 系统智能投放 | AC71: =SUM(T71:V71)
A72: 1859901063522320 | B72: 普通订单 | C72: 小辉哥 | D72: #滴滴，#出租车，朋友们，在陌生的城市，打滴滴还是方便一点！ | E72: https://www.douyin.com/video/7615783338746236337 | F72: 46098.73 | G72: 投放完成 | H72: 500 | I72: 500 | J72: 500 | K72: 点赞评论量 | L72: 45286 | M72: 11.04 | R72: 45286 | S72: 未获得授权 | T72: 1666 | U72: 106 | V72: 19 | W72: 39 | X72: 8 | Z72: 6.0 小时 | AA72: 系统智能投放 | AC72: =SUM(T72:V72)
A73: 1859988009337927 | B73: 普通订单 | C73: 🌸旧时光 | D73: 滴滴回家，真是划算 | E73: https://www.douyin.com/video/7618168504240308069 | F73: 46099.69 | G73: 投放结束 | H73: 1000 | I73: 1000 | J73: 999.99 | K73: 点赞评论量 | L73: 94555 | M73: 10.58 | R73: 94555 | S73: 未获得授权 | T73: 267 | U73: 6 | V73: 0 | W73: 356 | X73: 10 | Z73: 6.0 小时 | AA73: 系统智能投放 | AC73: =SUM(T73:V73)
A74: 1859987937856762 | B74: 普通订单 | C74: 咕咕哒哒 | D74: 第二次来柳州，东西还是一样好吃，市民还是一样热情 滴滴司机、菜场老板、粉店老板、买菜阿姨、咖啡店小哥，每个人都对游客很耐心 柳州值得~ #柳州 #原相机live证明我来过 #柳州旅游攻略 #广西dou是好风光 #花开了 | E74: https://www.douyin.com/video/7617498397310715327 | F74: 46099.689 | G74: 投放完成 | H74: 1000 | I74: 1000 | J74: 1000 | K74: 点赞评论量 | L74: 56873 | M74: 17.58 | R74: 56873 | S74: 未获得授权 | T74: 50 | U74: 4 | V74: 11 | W74: 687 | X74: 9 | Z74: 6.0 小时 | AA74: 系统智能投放 | AC74: =SUM(T74:V74)
A75: 1859994047358116 | B75: 普通订单 | C75: 绛珠仙子成长日记 | D75: 5.0分的滴滴司机 师傅我听懂了 其实你在告诉我 这个世界上没有定义 只有视角不同 但我此刻有个善良的定义 那就是你的那一句 “为什么你大半夜去人民医院” 以及你的善意的开导 但我是个杠精 我天天带着答案问问题 请原谅我 谢谢你，陌生人 至少此刻你的善良给我带来了开心 我对很多东西都没有欲望 但是对善意的瞬间 充满欲望 渴求遇见它享受它 #司机师傅 #欲望 #善良 | E75: https://www.douyin.com/video/7615713873504923322 | F75: 46099.756 | G75: 投放结束 | H75: 10000 | I75: 10000 | J75: 9999.79 | K75: 点赞评论量 | L75: 600443 | M75: 16.65 | R75: 600443 | S75: 未获得授权 | T75: 5163 | U75: 2123 | V75: 604 | W75: 9146 | X75: 102 | Z75: 6.0 小时 | AA75: 系统智能投放 | AC75: =SUM(T75:V75)
A76: 1860161746037928 | B76: 普通订单 | C76: 陈黎 | D76: 如果嵩山能发声，黄河会呐喊，那么今日的天问就是：河南人惹谁了？ 河南，古老的中原文化，殷墟文化，甲骨文遗址，到后来的黄河口决堤，这片土地承载着多少中华儿女的爱与痛？ 转发一篇旧文： 昨天我打了个滴滴出去办事。 十几公里路程，但那时段是上班早高峰，又飘着雨，女司机抱歉地说：肯定堵得厉害，急着赶么？要不从哪里绕一下，那样就是会多花钱。 我说不急，慢慢开，你觉得怎么合适就怎么走。 可能她较少遇到这样佛系的乘客，她在反光镜中眼含感激地看我一下：谢谢您的信任啊。 常州土著讲普通话总有地方口音，她明显不是本地人。她说她是河南商丘人，机缘巧合来常州二十年了。 我开玩笑：河南人不容易，在其他省份扎根，需要付出很多才能获得认可。尤其是江南的几个城市，的确排外。 这几句话听了她几近哽咽：哎，刚开始来常州，完全不被待见，人们叫我，都是河南佬，仿佛我没名字一样。这称呼不是亲热，就是赤裸裸的歧视。我们那地方是国家级贫困县，偶尔工友聊天，他们会不怀好意问：你们吃饭不用碗吧，都是用砵头？你们拉屎用土坷垃擦屁股？你们生了女儿都卖掉？生不出儿子不罢休？兄弟三人共娶一个老婆？那生出的孩子是谁的搞得清么？你们那里人怎么都爱骗人？总部驻马店离开你家远么？每次听到这些我都很难受，是啊，咱穷，给人瞧不起，可出生没法选择，只能自己争点气，勤奋一点，真诚一点，无法力挽狂澜整个河南人的面貌，但做好自己，总是能够的。这么多年，我真的是尽心尽力地打造一个河南人的形象，我希望我是个体体面面的，自立自强的，不骗不诈的河南人。好在，现在这种情况得到了极大改善，常州是一个非常美好的城市，它海纳百川地包容了河南曾经的贫瘠落后，河南也欣慰地矗立了诸如胖东来这样靠真诚与用心打造起来的标杆企业，我们都在进步，都在发展，都在向美好的未来挺进。 她很会表达，嗓音悦耳，措词严谨，每句话，饱含感情又掷地有声。她说她有幸嫁给了常州人，丈夫是常州农村的，当年也是家贫才娶了她这个外乡人，但婆家人都很好，对她好，一家人凭借着努力，在市区买了房子，孩子在市一中读高二。 车子路过市一中门口，堵得一动不动，她骄傲地指向校园：那幢楼的四楼边上一个教室，就是我儿子的班级，他叫李苏豫，一米八五了，成绩很好，两年后，我想他会考上985或者211的。那时候我就会去河南老家办场酒，我不收礼金，就图个与亲朋好友分享喜悦。 我要下车了，还在下着雨，她松了安全带，走出驾位，在雨中眼含热泪看着我，她个子不高，但面容清秀，应该比我小十来岁。我说：苏豫妈妈，祝福你，祝福你们全家，祝福河南。来，拥抱一下。 她趴我肩头，抽泣：姐姐，常州有几万辆滴滴车，再遇到的可能性很小，但我仍是希望下回再次见到你。 未来迢远，每时每刻都有人在挥手道别，遇见的时候，但愿我们都能成为彼此的一束光。 | E76: https://www.douyin.com/note/7619093952427614843 | F76: 46101.608 | G76: 投放完成 | H76: 1000 | I76: 1000 | J76: 1000 | K76: 点赞评论量 | L76: 91833 | M76: 10.89 | R76: 91833 | S76: 未获得授权 | T76: 1143 | U76: 84 | V76: 14 | W76: 221 | X76: 12 | Z76: 6.0 小时 | AA76: 系统智能投放 | AC76: =SUM(T76:V76)
A77: 1860161689670871 | B77: 普通订单 | C77: 人间有情 | D77: 城市在改变，滴滴出行，庐陵小巴也是一个选择！ | E77: https://www.douyin.com/video/7618525485648050938 | F77: 46101.607 | G77: 投放完成 | H77: 1000 | I77: 1000 | J77: 1000 | K77: 点赞评论量 | L77: 70826 | M77: 14.12 | R77: 70826 | S77: 未获得授权 | T77: 1501 | U77: 55 | V77: 31 | W77: 45 | X77: 13 | Z77: 6.0 小时 | AA77: 系统智能投放 | AC77: =SUM(T77:V77)
A78: 1860161627157692 | B78: 普通订单 | C78: 🌈Lin 、 | D78: #滴滴出行 温岭的滴滴也是让我大开眼界😂 | E78: https://www.douyin.com/video/7618222573041999345 | F78: 46101.606 | G78: 投放完成 | H78: 1000 | I78: 1000 | J78: 1000 | K78: 点赞评论量 | L78: 63044 | M78: 15.86 | R78: 63044 | S78: 未获得授权 | T78: 1345 | U78: 11 | V78: 26 | W78: 66 | X78: 7 | Z78: 6.0 小时 | AA78: 系统智能投放 | AC78: =SUM(T78:V78)
A79: 1860161560385815 | B79: 普通订单 | C79: 小仙仙🌈 | D79: 打了那么多次车，第一次遇到后车座提供充电线的，而且还是三插头的，给师傅点赞👍#滴滴司机 #滴滴 | E79: https://www.douyin.com/video/7618960753446510009 | F79: 46101.606 | G79: 投放完成 | H79: 1000 | I79: 1000 | J79: 1000 | K79: 点赞评论量 | L79: 88997 | M79: 11.24 | R79: 88997 | S79: 未获得授权 | T79: 3262 | U79: 48 | V79: 47 | W79: 82 | X79: 3 | Z79: 6.0 小时 | AA79: 系统智能投放 | AC79: =SUM(T79:V79)
A80: 1860162109148176 | B80: 普通订单 | C80: 高山都957 | D80: #出差打车 第一次打高端车 滴滴司机好高端啊，停车接送服务，都穿正装耶 | E80: https://www.douyin.com/video/7618932945290901903 | F80: 46101.611 | G80: 投放完成 | H80: 1000 | I80: 1000 | J80: 1000 | K80: 点赞评论量 | L80: 64773 | M80: 15.44 | R80: 64773 | S80: 未获得授权 | T80: 4549 | U80: 341 | V80: 85 | W80: 1854 | X80: 34 | Z80: 6.0 小时 | AA80: 系统智能投放 | AC80: =SUM(T80:V80)
A81: 1860440139040020 | B81: 普通订单 | C81: 哆啦萌萌^ | D81: 因为有碰到这些人让我感觉这个国家也没有网上说的那样排华与危险 当时一个人落地手机没有信号 我就在机场找了一个当地的姐姐问哪里搞流量卡 她也不知道 但她很热情的帮我问了机场的工作人员并且把我带到了那个地方 晚上走在路上会有人主动过来提醒我们遇到摩托车要小心 要把包包背在前面 还有滴滴司机 我并不知道榴莲是禁止带上车的 🤣但那个司机人也特别好 把车窗打开了也没有把我们赶下车 第二天打车也是 我只是顺口说我手机快没有电了 司机很热情的把他的充电宝借给我 还不停的找线让我妈妈也能充上电 🥹 就算是逛夜市因为不小心踩到他们的脚说了句sorry 他们也会热情的回应thankyou 虽然我英语没有那么好 但是服务员都会耐心的打开翻译和我沟通 在这里我遇到的华人都充满善意 非常感叹自己能够这么幸运 碰到的都是很好的人#马来西亚 #吉隆坡#原相机 #旅游 #留学 | E81: https://www.douyin.com/video/7619636679322387057 | F81: 46104.681 | G81: 投放完成 | H81: 1000 | I81: 1000 | J81: 1000 | K81: 点赞评论量 | L81: 52011 | M81: 19.23 | R81: 52011 | S81: 未获得授权 | T81: 4559 | U81: 1 | V81: 97 | W81: 330 | X81: 9 | Z81: 6.0 小时 | AA81: 系统智能投放 | AC81: =SUM(T81:V81)
A82: 1860440084341209 | B82: 普通订单 | C82: harrynos | D82: 济州偶来小路 亲子徒步百公里Day3。第三天走了5号线/13.4公里+6号线10.1公里 到6号线的终点、同时也是7号线的起点住酒店 因为我们中午才出发，一直都在赶路，体验感其实并不是很好， 所以如果要两条线连走，建议尽量还是早一点出发，用时至少8小时 ——5号线—— 前一晚在1号线露营，起床收拾好后出发已经是9点 坐201路公交车到5号线起点，车程1个半小时左右 吃完午饭11点30才从5号线起点出发，一开始都是沿着海岸线的公路徒步 1.2km-3km是爬一座小山，爬升不是很多，但有一段要走海边的礁石 出去后又是公路，经过一片很大的山茶花园，中间章附近有一颗很大的橘子树很出片 ——6号线—— 5号线的终点也是6号线的起点，是一个淡水海水的交汇处著名景点，峡谷的小河里有不少人在划皮划艇 这个点还是比较热闹的，当地人很多，也有不少便利店可以补给 6号线的前半段也比较好走，一直都是沿海公路 夕阳下、海岸边的油菜花也是个很独特的景观 6公里不到经过一个射箭场后就进入正房瀑布的景区 讲道理也是一个比较出名的景点，可以我们到的时候天已经黑了，只能听到瀑布的声音，什么都没有看到有点可惜 正房瀑布的爬升还是比较狠的，也可能是因为当天走了快20公里已经累的不行了 7.4公里后到达爬升的顶点海螺城堡，也是6号线中间章的位置 小孩哥到这已经走崩溃了，所以盖完章决定最后的2公里直接科技徒步 第一次在韩国用滴滴打车，还挺方便的 三个人坐在马路边等车的样子看起来真的太凄惨了。 ——晚饭及住宿—— 我们住的酒店是西归浦大酒店（Hotel the Grang Seogwipo），正好就在7号线游客中心的隔壁，还是挺方便的，价格也还可以400多一晚。 到酒店放完行李，9点才出去吃饭，但是好多店都打烊不接单了，最终找到了一家中国人开的韩国烤肉店，太离谱了。。。哦，对了，这天是国内的大年夜。。。太惨了 下期更汉拿山的单日徒步。#户外徒步记录 #创作者中心 #创作灵感 #亲子徒步 #偶来小路 | E82: https://www.douyin.com/note/7619357588699109065 | F82: 46104.68 | G82: 投放结束 | H82: 1000 | I82: 1000 | J82: 999.89 | K82: 点赞评论量 | L82: 86300 | M82: 11.59 | R82: 86300 | S82: 未获得授权 | T82: 490 | U82: 11 | V82: 3 | W82: 75 | X82: 12 | Z82: 6.0 小时 | AA82: 系统智能投放 | AC82: =SUM(T82:V82)
A83: 1860440041371680 | B83: 普通订单 | C83: 面具 | D83: 泾川人打车，别花冤枉钱！ 滴滴网约车，价格透明不加价 喝酒不开车，出行更安全 赶高铁、跑机场、下乡镇都方便 代人约车，一键搞定 长途1公里1块钱 乡镇价比出租更划算 县城出发只算单趟 微信小程序滴滴出行 提前看价，明明白白消费#城市公交 #出租车司机 #网约车 #滴滴出行 #泾川 | E83: https://www.douyin.com/video/7619622592362705846 | F83: 46104.679 | G83: 投放结束 | H83: 1000 | I83: 1000 | J83: 999.21 | K83: 点赞评论量 | L83: 1695 | M83: 0.59 | R83: 60844 | S83: 0.123 | T83: 1676 | U83: 10 | V83: 9 | W83: 218 | X83: 64 | Z83: 6.0 小时 | AA83: 系统智能投放 | AC83: =SUM(T83:V83)
A84: 1860439955164755 | B84: 普通订单 | C84: 东方先生 | D84: 第一次遇到聋哑人滴滴司机，100元一点爱心。 #北漂人民辛苦了 | E84: https://www.douyin.com/note/7619935329013573091 | F84: 46104.678 | G84: 投放完成 | H84: 1000 | I84: 1000 | J84: 1000 | K84: 点赞评论量 | L84: 54627 | M84: 18.31 | R84: 54627 | S84: 未获得授权 | T84: 370 | U84: 144 | V84: 20 | W84: 419 | X84: 5 | Z84: 6.0 小时 | AA84: 系统智能投放 | AC84: =SUM(T84:V84)
A85: 1860440725864460 | B85: 普通订单 | C85: 💐/₁₂.₁₅ ᵕ̈ xzq✨ | D85: 呼啦啦，已到达桐乡啦🤪🤪 第二次参加半马啦，感谢桐乡半马在8个报名之中作为第二个选择了我哈哈哈😘😘一下高铁打车滴滴觉得司机超级热情到酒店后还祝我明天可以跑到好成绩，呜呜呜，真的超级感动😭😭 这次酒店到起跑点3分钟左右步行简直不要太棒啦吼吼吼🥳🥳 赛事包领取也超级便捷🤗🤗三分钟搞定。 最后希望明天不要出太阳😭😭要不然我可要跑不动了，加油加油😇😇 #马拉松 #中长跑 #白羊座 #日常ootd #甜妹 | E85: https://www.douyin.com/video/7619605942468253051 | F85: 46104.687 | G85: 投放终止 | H85: 1000 | I85: 1000 | J85: 999.63 | K85: 点赞评论量 | L85: 60749 | M85: 16.46 | R85: 60749 | S85: 未获得授权 | T85: 1513 | U85: 27 | V85: 6 | W85: 370 | X85: 21 | Z85: 6.0 小时 | AA85: 系统智能投放 | AC85: =SUM(T85:V85)
A86: 1860440585244688 | B86: 普通订单 | C86: 小仙仙🌈 | D86: 打了那么多次车，第一次遇到后车座提供充电线的，而且还是三插头的，给师傅点赞👍#滴滴司机 #滴滴 | E86: https://www.douyin.com/video/7618960753446510009 | F86: 46104.685 | G86: 投放结束 | H86: 5000 | I86: 5000 | J86: 4998 | K86: 点赞评论量 | L86: 604390 | M86: 8.27 | R86: 604390 | S86: 未获得授权 | T86: 1252 | U86: 167 | V86: 17 | W86: 876 | X86: 20 | Z86: 6.0 小时 | AA86: 系统智能投放 | AC86: =SUM(T86:V86)
A87: 1860440503776396 | B87: 普通订单 | C87: 贝贝公主👸 | D87: #特斯拉 #滴滴打车 也是坐上特斯拉了，滴滴打车，人生第一次哈哈哈哈哈哈哈哈哈 | E87: https://www.douyin.com/note/7620309274209021605 | F87: 46104.684 | G87: 投放结束 | H87: 1000 | I87: 1000 | J87: 999.78 | K87: 点赞评论量 | L87: 94784 | M87: 10.55 | R87: 94784 | S87: 未获得授权 | T87: 537 | U87: 19 | V87: 10 | W87: 189 | X87: 14 | Z87: 6.0 小时 | AA87: 系统智能投放 | AC87: =SUM(T87:V87)
A88: 1860440445024698 | B88: 普通订单 | C88: 🫘纸 | D88: 第一次打滴滴司机怎么这么帅啊，无意冒犯。#滴滴司机 | E88: https://www.douyin.com/note/7619346681800231592 | F88: 46104.683 | G88: 投放终止 | H88: 1000 | I88: 1000 | J88: 999.82 | K88: 点赞评论量 | L88: 67746 | M88: 14.76 | R88: 67746 | S88: 未获得授权 | T88: 8402 | U88: 95 | V88: 354 | W88: 3340 | X88: 11 | Z88: 6.0 小时 | AA88: 系统智能投放 | AC88: =SUM(T88:V88)
A89: 1860440272597004 | B89: 普通订单 | C89: 扭瓶盖小能手🤨 | D89: 今日心情被耗到1%🧸 拖着疲惫的身体打了一辆滴滴🚗 拉开车门的瞬间，看到了满车玩偶—— 司机是一位北方的退役军人小哥哥🚕@霍拉拉 短暂的车程，在愉快的聊天中满血复活✨ 热爱生活的人，真的会闪闪发光💛 #治愈系 #满车玩偶 #陌生人的温暖 | E89: https://www.douyin.com/video/7619392937248262208 | F89: 46104.682 | G89: 投放结束 | H89: 1000 | I89: 1000 | J89: 999.82 | K89: 点赞评论量 | L89: 61323 | M89: 16.3 | R89: 61323 | S89: 未获得授权 | T89: 1117 | U89: 12 | V89: 51 | W89: 81 | X89: 21 | Z89: 6.0 小时 | AA89: 系统智能投放 | AC89: =SUM(T89:V89)
A90: 1860524414901387 | B90: 普通订单 | C90: 🫘纸 | D90: 第一次打滴滴司机怎么这么帅啊，无意冒犯。#滴滴司机 | E90: https://www.douyin.com/note/7619346681800231592 | F90: 46105.61 | G90: 投放终止 | H90: 5000 | I90: 5000 | J90: 3416.75 | K90: 点赞评论量 | L90: 233224 | M90: 14.65 | R90: 233224 | S90: 未获得授权 | T90: 33635 | U90: 1052 | V90: 2011 | W90: 14984 | X90: 51 | Z90: 6.0 小时 | AA90: 系统智能投放 | AC90: =SUM(T90:V90)
A91: 1860524365286552 | B91: 普通订单 | C91: 哆啦萌萌^ | D91: 因为有碰到这些人让我感觉这个国家也没有网上说的那样排华与危险 当时一个人落地手机没有信号 我就在机场找了一个当地的姐姐问哪里搞流量卡 她也不知道 但她很热情的帮我问了机场的工作人员并且把我带到了那个地方 晚上走在路上会有人主动过来提醒我们遇到摩托车要小心 要把包包背在前面 还有滴滴司机 我并不知道榴莲是禁止带上车的 🤣但那个司机人也特别好 把车窗打开了也没有把我们赶下车 第二天打车也是 我只是顺口说我手机快没有电了 司机很热情的把他的充电宝借给我 还不停的找线让我妈妈也能充上电 🥹 就算是逛夜市因为不小心踩到他们的脚说了句sorry 他们也会热情的回应thankyou 虽然我英语没有那么好 但是服务员都会耐心的打开翻译和我沟通 在这里我遇到的华人都充满善意 非常感叹自己能够这么幸运 碰到的都是很好的人#马来西亚 #吉隆坡#原相机 #旅游 #留学 | E91: https://www.douyin.com/video/7619636679322387057 | F91: 46105.61 | G91: 投放完成 | H91: 5000 | I91: 5000 | J91: 5000 | K91: 点赞评论量 | L91: 272055 | M91: 18.38 | R91: 272055 | S91: 未获得授权 | T91: 59934 | U91: 51 | V91: 2003 | W91: 2583 | X91: 48 | Z91: 6.0 小时 | AA91: 系统智能投放 | AC91: =SUM(T91:V91)
A92: 1860524139272314 | B92: 普通订单 | C92: 任我行 | D92: 昨天坐滴滴，竟然打到了一辆汉的绝版车，大家猜猜是啥车？ | E92: https://www.douyin.com/note/7619897380909579002 | F92: 46105.608 | G92: 投放完成 | H92: 1000 | I92: 1000 | J92: 1000 | K92: 点赞评论量 | L92: 56250 | M92: 17.78 | R92: 56250 | S92: 未获得授权 | T92: 1680 | U92: 71 | V92: 3 | W92: 119 | X92: 19 | Z92: 6.0 小时 | AA92: 系统智能投放 | AC92: =SUM(T92:V92)
A93: 1860523931054220 | B93: 普通订单 | C93: 瓜田学姐 | D93: 曾被全网唱衰的女乘客匹配女司机功能 如今被狠狠打脸 #女司机 #出租车 #打车 #女性力量 | E93: https://www.douyin.com/video/7620371187046075682 | F93: 46105.605 | G93: 审核不通过 | H93: 1000 | I93: 1000 | J93: 0 | K93: 点赞评论量 | L93: 0 | M93: 0 | R93: 0 | S93: 未获得授权 | T93: 0 | U93: 0 | V93: 0 | W93: 0 | X93: 0 | Z93: 6.0 小时 | AA93: 系统智能投放 | AC93: =SUM(T93:V93)
A94: 1860523746436202 | B94: 普通订单 | C94: 刘量AI | D94: 什么？1句话滴滴AI就能帮你打到满意的车 #AI#AI打车#滴滴打车#AI出行#AI小滴 | E94: https://www.douyin.com/video/7620296845138728549 | F94: 46105.603 | G94: 投放完成 | H94: 1000 | I94: 1000 | J94: 1000 | K94: 点赞评论量 | L94: 67849 | M94: 14.74 | R94: 67849 | S94: 未获得授权 | T94: 2448 | U94: 46 | V94: 11 | W94: 42 | X94: 27 | Z94: 6.0 小时 | AA94: 系统智能投放 | AC94: =SUM(T94:V94)
A95: 1860614533851184 | B95: 普通订单 | C95: 摸鱼大小姐 | D95: 女生之间的善意 从来不是刻意营造的模样 #女司机 #打车 #网约车 #正能量 | E95: https://www.douyin.com/video/7620717387695869226 | F95: 46106.605 | G95: 投放完成 | H95: 1000 | I95: 1000 | J95: 1000 | K95: 点赞评论量 | L95: 58819 | M95: 17 | R95: 58819 | S95: 未获得授权 | T95: 7779 | U95: 691 | V95: 203 | W95: 425 | X95: 13 | Z95: 6.0 小时 | AA95: 系统智能投放 | AC95: =SUM(T95:V95)
... A203: 1864441868578000 | B203: 普通订单 | C203: 秋恋雪 | D203: 吹着长安街的晚风，邂逅天安门的夜色。遇到超暖心的滴滴师傅，细心放缓车速，成全每一份想定格盛世风景的心意。平凡人，最动人的温柔。#吃喝玩乐分享计划 #天安门 #北京夜景 #视觉冲击旅行 #视觉盛宴城市记忆 | E203: https://www.douyin.com/video/7636020034524274043 | F203: 46148.851 | G203: 投放完成 | H203: 1000 | I203: 1000 | J203: 1000 | K203: 点赞评论量 | L203: 54243 | M203: 18.44 | R203: 54243 | S203: 未获得授权 | T203: 4237 | U203: 292 | V203: 34 | W203: 76 | X203: 5 | Z203: 6.0 小时 | AA203: 系统智能投放 | AC203: =SUM(T203:V203)
A204: 1864441777438764 | B204: 普通订单 | C204: 吴安芝 | D204: 我评论了@浮生 的作品： 想起我之前夏天和朋友打车，朋友用的某地图打的一口价的车，司机就说，一口价的车没有空调服务司机还振振有词。我在某滴上打车，特惠也好特价也好，都有空调 | E204: https://www.douyin.com/note/7636204932429437370 | F204: 46148.85 | G204: 投放完成 | H204: 1000 | I204: 1000 | J204: 1000 | K204: 点赞评论量 | L204: 10546 | M204: 0.09 | R204: 1623280 | S204: 0.183 | T204: 9869 | U204: 462 | V204: 215 | W204: 8167 | X204: 1428 | Z204: 6.0 小时 | AA204: 系统智能投放 | AC204: =SUM(T204:V204)
A205: 1864532074910819 | B205: 普通订单 | C205: 马超Aster | D205: 负债百万的滴滴司机告诉我，要好好爱自己 #滴滴司机 #爱情 #爱自己 #生活 #陌生人的温暖 | E205: https://www.douyin.com/video/7636040612411755802 | F205: 46149.847 | G205: 投放完成 | H205: 5000 | I205: 5000 | J205: 5000 | K205: 点赞评论量 | L205: 283764 | M205: 17.62 | R205: 283764 | S205: 未获得授权 | T205: 18755 | U205: 443 | V205: 3364 | W205: 3800 | X205: 200 | Z205: 6.0 小时 | AA205: 系统智能投放 | AC205: =SUM(T205:V205)
A206: 1864531923846564 | B206: 普通订单 | C206: 吴安芝 | D206: 我评论了@浮生 的作品： 想起我之前夏天和朋友打车，朋友用的某地图打的一口价的车，司机就说，一口价的车没有空调服务司机还振振有词。我在某滴上打车，特惠也好特价也好，都有空调 | E206: https://www.douyin.com/note/7636204932429437370 | F206: 46149.845 | G206: 投放完成 | H206: 5000 | I206: 5000 | J206: 5000 | K206: 点赞评论量 | L206: 21630 | M206: 0.23 | R206: 4099537 | S206: 0.186 | T206: 20259 | U206: 721 | V206: 650 | W206: 16779 | X206: 1742 | Z206: 6.0 小时 | AA206: 系统智能投放 | AC206: =SUM(T206:V206)
A207: 1864531771825208 | B207: 普通订单 | C207: 克莱因蓝 | D207: 现在滴滴瞬间都这么有品吗！#打车#出租车司机 | E207: https://www.douyin.com/video/7637044455720278251 | F207: 46149.844 | G207: 投放完成 | H207: 1000 | I207: 1000 | J207: 1000 | K207: 点赞评论量 | L207: 54251 | M207: 18.43 | R207: 54251 | S207: 未获得授权 | T207: 780 | U207: 10 | V207: 22 | W207: 85 | X207: 5 | Z207: 6.0 小时 | AA207: 系统智能投放 | AC207: =SUM(T207:V207)
A208: 1864531483448548 | B208: 普通订单 | C208: 萬家幺女万和香 | D208: 今天坐滴滴车，师傅问我在哪里下单？我说在微信里面，他说怎么坐车的全部都是美女坐我的车？我说那你走桃花运了，他说美女，你气质太好，我说你也长得很帅，到底是他犯花痴，还是我犯花痴？都夸对方长得帅，其实夸对方帅也是一种礼貌 | E208: https://www.douyin.com/video/7636826521273382309 | F208: 46149.84 | G208: 投放完成 | H208: 1000 | I208: 1000 | J208: 1000 | K208: 点赞评论量 | L208: 55416 | M208: 18.05 | R208: 55416 | S208: 未获得授权 | T208: 82 | U208: 2 | V208: 40 | W208: 272 | X208: 4 | Z208: 6.0 小时 | AA208: 系统智能投放 | AC208: =SUM(T208:V208)
A209: 1864627431004168 | B209: 普通订单 | C209: 马超Aster | D209: 负债百万的滴滴司机告诉我，要好好爱自己 #滴滴司机 #爱情 #爱自己 #生活 #陌生人的温暖 | E209: https://www.douyin.com/video/7636040612411755802 | F209: 46150.899 | G209: 投放完成 | H209: 5000 | I209: 5000 | J209: 5000 | K209: 点赞评论量 | L209: 273724 | M209: 18.27 | R209: 273724 | S209: 未获得授权 | T209: 18654 | U209: 284 | V209: 3463 | W209: 4310 | X209: 167 | Z209: 6.0 小时 | AA209: 系统智能投放 | AC209: =SUM(T209:V209)
A210: 1864627335958556 | B210: 普通订单 | C210: 吉玺 | D210: 家长是孩子的首任老师。现在只要有人对我们释放善意，孩子都会有感恩之心。比如昨天的滴滴司机，态度友善，还一路畅聊临下车我习惯性说了一声：“谢谢”！师傅立马说：期待下次还接你的订单，慢走！孩儿在旁边说：妈妈，给师傅一个好评吧，好评多了他的订单会多。 去餐厅吃饭，饭店老板炒了一大盆龙虾自己吃，我带着孩儿在邻桌吃，老板拿了孩子的筷子去夹了几只小龙虾笑眯眯地说：孩子你试试味道吧，我们都还没开始吃，是干净的，不辣的。瞬间我们的盘子里多了几只有温度、热气腾腾的虾，这个世界不缺善意，你要把爱先洒出去，能接住能量的人，爱出者爱返福往者福来。 | E210: https://www.douyin.com/video/7636643841961216127 | F210: 46150.898 | G210: 投放完成 | H210: 1000 | I210: 1000 | J210: 1000 | K210: 点赞评论量 | L210: 55634 | M210: 17.97 | R210: 55634 | S210: 未获得授权 | T210: 737 | U210: 13 | V210: 4 | W210: 91 | X210: 5 | Z210: 6.0 小时 | AA210: 系统智能投放 | AC210: =SUM(T210:V210)
A211: 1864711080844361 | B211: 普通订单 | C211: 弦外故事 | D211: 刷爆朋友圈！谁能猜到网约车后座是歌神 陈奕迅打车偶遇歌迷沉浸式听歌 Eason忍不住开口跟唱恶搞司机 网友：滴滴现在还缺人么？ #陈奕迅 #唱歌 #明星 #删了她 | E211: https://www.douyin.com/video/7637394139268615462 | F211: 46151.823 | G211: 投放完成 | H211: 1000 | I211: 1000 | J211: 1000 | K211: 点赞评论-质量优先 | L211: 60844 | M211: 16.44 | R211: 60844 | S211: 未获得授权 | T211: 382 | U211: 33 | V211: 41 | W211: 152 | X211: 6 | Z211: 6.0 小时 | AA211: 系统智能投放 | AC211: =SUM(T211:V211)
A212: 1864889771296812 | B212: 普通订单 | C212: 漫寻星📸. | D212: 常熟这个不起眼的小城市，却有着网约公交😍不仅覆盖了部分公交线网空白，还方便了市民出行，别看车小，却总能跑出最快的时速，试运营期间，只需3元/人次，就能开启这段美妙旅程，非常有性价比🤓#公交车 #公交迷 #公共交通 #城市公交 #网约公交 | E212: https://www.douyin.com/video/7637869144147080817 | F212: 46153.795 | G212: 投放完成 | H212: 1000 | I212: 1000 | J212: 1000 | K212: 点赞评论量 | L212: 53472 | M212: 18.7 | R212: 53472 | S212: 未获得授权 | T212: 2678 | U212: 13 | V212: 80 | W212: 115 | X212: 14 | Z212: 6.0 小时 | AA212: 系统智能投放 | AC212: =SUM(T212:V212)
A213: 1865068424264896 | B213: 普通订单 | C213: 徐伟华 | D213: 出发啦！今天滴滴车司机是我的老乡，车内非常整洁！给他点赞！ | E213: https://www.douyin.com/note/7638470477203931643 | F213: 46155.767 | G213: 投放完成 | H213: 1000 | I213: 1000 | J213: 1000 | K213: 点赞评论-质量优先 | L213: 95313 | M213: 10.49 | R213: 95313 | S213: 未获得授权 | T213: 35 | U213: 0 | V213: 5 | W213: 595 | X213: 2 | Z213: 6.0 小时 | AA213: 系统智能投放 | AC213: =SUM(T213:V213)
A214: 1865068346767592 | B214: 普通订单 | C214: 蘅若 | D214: 是不是南方的滴滴司机都帮忙拿行李呀，莫名的感觉很好 | E214: https://www.douyin.com/note/7638835615421411577 | F214: 46155.766 | G214: 审核不通过 | H214: 1000 | I214: 1000 | J214: 0 | K214: 点赞评论-质量优先 | L214: 0 | M214: 0 | R214: 0 | S214: 未获得授权 | T214: 0 | U214: 0 | V214: 0 | W214: 0 | X214: 0 | Z214: 6.0 小时 | AA214: 系统智能投放 | AC214: =SUM(T214:V214)
A215: 1865249760710688 | B215: 普通订单 | C215: 骑境•路飞 | D215: 外胎爆了怎么办？ #扎胎了怎么办 #货拉拉 外胎首爆，完全没气，又穿鞋锁鞋，该咋么办呢？ 虽然只有2公里，但还是需要打车回家。 带自行车打车依旧很顺利：接单后提前给师傅说有自行车要带，到目的地后给一下感谢费……屡试不爽，但我还是不想爆胎打车 | E215: https://www.douyin.com/video/7638908016368917681 | F215: 46157.769 | G215: 投放完成 | H215: 1000 | I215: 1000 | J215: 1000 | K215: 点赞评论量 | L215: 78253 | M215: 12.78 | R215: 78253 | S215: 未获得授权 | T215: 815 | U215: 5 | V215: 0 | W215: 1347 | X215: 2 | Z215: 6.0 小时 | AA215: 系统智能投放 | AC215: =SUM(T215:V215)
A216: 1865249556421812 | B216: 普通订单 | C216: 不吃韭菜~ | D216: 第一次打到聋哑司机的车 当时赶着去上班 上车第一句话报了自己手机尾号 然而师傅没有理我 我抬头想继续说 司机师傅把手机给我 输入后四位 我才注意到 他是聋哑司机 瞬间愣住了 赶紧打开豆包搜了一下 原来聋哑师傅也能当滴滴司机 突然觉得他们这一行也好不容易 在车上我也不觉得危险⚠️ 师傅全程很认真的在开车 虽然医院🏥里有点绕 但师傅还是很耐心和我打手势问路 下车时我还是习惯性说了句谢谢师傅 然后用临时学的手语给他点赞👍 他也给我回了一个谢谢和赞👍的动作 然后笑着和我挥手🙋 努力生活的大家也一定要 全力以赴 奔赴远方！ #你们打车见过哪些神标语 #聋哑司机 | E216: https://www.douyin.com/note/7639772595369289381 | F216: 46157.766 | G216: 投放完成 | H216: 1000 | I216: 1000 | J216: 1000 | K216: 点赞评论量 | L216: 60167 | M216: 16.62 | R216: 60167 | S216: 未获得授权 | T216: 3773 | U216: 21 | V216: 51 | W216: 86 | X216: 6 | Z216: 6.0 小时 | AA216: 系统智能投放 | AC216: =SUM(T216:V216)
A217: 1865249516947616 | B217: 普通订单 | C217: 幕兮彤 | D217: 好可爱#拼车趣事 #滴滴司机 | E217: https://www.douyin.com/note/7639700717046112383 | F217: 46157.766 | G217: 投放完成 | H217: 1000 | I217: 1000 | J217: 1000 | K217: 点赞评论量 | L217: 52567 | M217: 19.02 | R217: 52567 | S217: 未获得授权 | T217: 326 | U217: 0 | V217: 21 | W217: 106 | X217: 0 | Z217: 6.0 小时 | AA217: 系统智能投放 | AC217: =SUM(T217:V217)
A218: 1865249459190891 | B218: 普通订单 | C218: 婷宝儿💖 | D218: 平时上班打了这么多滴滴，第一次遇到这么干净又帅气的司机！坐起心情都要舒畅些 | E218: https://www.douyin.com/video/7639539369804821434 | F218: 46157.765 | G218: 投放完成 | H218: 1000 | I218: 1000 | J218: 1000 | K218: 点赞评论量 | L218: 72074 | M218: 13.87 | R218: 72074 | S218: 未获得授权 | T218: 188 | U218: 4 | V218: 15 | W218: 1416 | X218: 6 | Z218: 6.0 小时 | AA218: 系统智能投放 | AC218: =SUM(T218:V218)
... A269: 1867603160164681 | B269: 普通订单 | C269: 苏二小姐 | D269: #滴滴公交车 #公交网约车 网约公交车来了🎈 | E269: https://www.douyin.com/video/7648121194428425573 | F269: 46183.745 | G269: 投放完成 | H269: 1000 | I269: 1000 | J269: 1000 | K269: 点赞评论量 | L269: 69229 | M269: 14.44 | R269: 69229 | S269: 未获得授权 | T269: 1704 | U269: 36 | V269: 245 | W269: 70 | X269: 4 | Z269: 6.0 小时 | AA269: 系统智能投放 | AC269: =SUM(T269:V269)

Sheet 年度统计表
A1: 月份 | B1: 总互动量 | C1: 投放金额 | D1: 综合CPE
A2: 1月 | B2: 2725473 | C2: 466700 | D2: =C2/B2
A3: 2月 | B3: 149508 | C3: 33000 | D3: =C3/B3
A4: 3月 | B4: 1974887 | C4: ='3月加热汇总'!K2 | D4: =C4/B4
A5: 4月 | B5: ='4月加热汇总'!N2 | C5: ='4月加热汇总'!O2 | D5: =C5/B5
A6: 5月 | B6: ='5月加热汇总'!N2 | C6: ='5月加热汇总'!O2 | D6: =C6/B6
A7: 6月 | B7: ='6月加热汇总'!N2 | C7: ='6月加热汇总'!O2 | D7: =C7/B7
A18: 合计 | B18: =SUM(B2:B17) | C18: =SUM(C2:C17) | D18: =C18/B18
